Workbook
Name NativeTimeline_Fecha_Operación_REAL: #N/A
Name NativeTimeline_Fecha_valor_REAL: #N/A
Name Slicer_Cuenta: #N/A
Name Slicer_Tipo: #N/A

Sheet Sheet1
A2: Fecha valor REAL | B2: (All)
A4: Row Labels | B4: Average of Importe
A5: Alquiler | B5: -895.5
A6: Café | B6: -2.9951822
A7: Compras | B7: -23.4
A8: Deporte | B8: -3.645
A9: Deudas | B9: -58.793913
A10: Donación | B10: -30
A11: Entretenimiento | B11: -15.794573
A12: Establecernos | B12: -237.344
A13: Inversión | B13: -383.82353
A14: Master | B14: -627.91944
A15: Mercado | B15: -25.993321
A16: Navidad | B16: -70.83814
... A26: Grand Total | B26: -38.41223
N53: Average of Saldo | O53: Column Labels
N54: Row Labels | O54: Cristina | P54: Cuentas | Q54: Nomina | R54: Grand Total
N55: 2023 | O55: 2940.0624 | P55: 491.05949 | Q55: 643.44028 | R55: 1216.832
N56: Qtr2 | O56: 1775.4392 | P56: 975.7725 | R56: 1587.2824
N57: Jun | O57: 1775.4392 | P57: 975.7725 | R57: 1587.2824
N58: 45090 | O58: 3000 | R58: 3000
N59: 45091 | O59: 2489.23 | R59: 2489.23
N60: 45092 | O60: 2218.93 | R60: 2218.93
N61: 45096 | O61: 1586.53 | R61: 1586.53
N62: 45098 | O62: 955.28 | R62: 955.28
N63: 45101 | O63: 950.78 | R63: 950.78
N64: 45103 | O64: 947.38 | R64: 947.38
N65: 45104 | O65: 942.38 | P65: 5 | R65: 473.69
N66: 45105 | O66: 935.98 | P66: 1301.52 | R66: 1179.6733
N67: 45106 | P67: 1295.05 | R67: 1295.05
N68: Qtr3 | O68: 2278.7012 | P68: 284.1416 | Q68: 894.39 | R68: 985.36382
N69: Jul | O69: 1986.205 | P69: 681.348 | R69: 1702.5404
N70: 45108 | O70: 932.98 | R70: 932.98
N71: 45110 | P71: 395.05 | R71: 395.05
N72: 45112 | O72: 2182.6967 | R72: 2182.6967
N73: 45113 | O73: 2176.575 | R73: 2176.575
N74: 45114 | O74: 2147.81 | R74: 2147.81
N75: 45115 | O75: 2121.92 | R75: 2121.92
N76: 45118 | O76: 2113.81 | R76: 2113.81
N77: 45119 | O77: 2098.465 | R77: 2098.465
N78: 45121 | O78: 2281.97 | R78: 2281.97
N79: 45125 | O79: 2251.47 | P79: 378.67 | R79: 1315.07
N80: 45128 | O80: 2183.41 | R80: 2183.41
N81: 45130 | O81: 2166.61 | R81: 2166.61
N82: 45132 | O82: 1166.61 | P82: 1003.67 | R82: 1057.9833
N83: 45134 | P83: 625.68 | R83: 625.68
N84: 45137 | O84: 1165.01 | R84: 1165.01
N85: Aug | O85: 1471.3317 | P85: 643.40125 | Q85: 374.1 | R85: 920.2125
N86: 45139 | O86: 1108.4 | Q86: 744.1 | R86: 926.25
N87: 45140 | O87: 208.4 | R87: 208.4
N88: 45142 | O88: 1932.63 | P88: 1257.68 | Q88: 4.1 | R88: 1141.954
N89: 45143 | P89: 381.88 | R89: 381.88
N90: 45145 | O90: 1894.67 | R90: 1894.67
N91: 45147 | P91: 285.44 | R91: 285.44
N92: 45156 | P92: 245.7 | R92: 245.7
N93: 45161 | P93: 232.07 | R93: 232.07
N94: 45166 | P94: 229.08 | R94: 229.08
N95: 45168 | O95: 1841.945 | R95: 1841.945
N96: Sep | O96: 2840.3206 | P96: 205.75274 | Q96: 955.60059 | R96: 826.05825
N97: 45170 | O97: 3339.61 | P97: 76.77 | R97: 1381.906
N98: 45171 | O98: 2856.87 | P98: 32.72 | R98: 974.10333
N99: 45172 | O99: 2820.46 | P99: 25.71 | R99: 1888.8767
N100: 45173 | O100: 2805.46 | P100: 3.91 | Q100: 2033.45 | R100: 1614.2733
N101: 45176 | O101: 2792.61 | P101: 203.91 | Q101: 1833.45 | R101: 1609.99
N102: 45177 | O102: 2781.3 | R102: 2781.3
N103: 45178 | P103: 177.9975 | R103: 177.9975
A104: Row Labels | B104: Sum of Importe | N104: 45179 | P104: 222.71 | R104: 222.71
A105: 2023 | B105: 4716.38 | N105: 45180 | P105: 179.79333 | Q105: 1733.45 | R105: 401.74429
A106: Qtr2 | B106: 2231.03 | N106: 45181 | O106: 2777.2 | P106: 36.925 | R106: 584.98
A107: Jun | B107: 2231.03 | N107: 45182 | O107: 2772.3 | P107: 521.59667 | Q107: 1233.45 | R107: 1390.4733
A108: 45090 | B108: 3000 | N108: 45183 | P108: 410.57 | R108: 410.57
A109: 45091 | B109: -775.77 | N109: 45184 | P109: 150.48 | Q109: 933.45 | R109: 541.965
A110: 45092 | B110: -5.3 | N110: 45185 | O110: 2761.14 | P110: 299.4475 | R110: 791.786
A111: 45096 | B111: -1262.4 | N111: 45186 | P111: 427.41 | R111: 427.41
A112: 45098 | B112: -1.25 | N112: 45187 | P112: 421.31 | Q112: 533.45 | R112: 458.69
A113: 45101 | B113: -4.5 | N113: 45189 | P113: 299.55 | R113: 299.55
A114: 45103 | B114: -3.4 | N114: 45190 | P114: 276.23 | R114: 276.23
A115: 45104 | B115: 0 | N115: 45191 | P115: 199.51 | R115: 199.51
A116: 45105 | B116: 1286.64 | N116: 45192 | O116: 2751.14 | P116: 166.26 | R116: 1200.212
A117: 45106 | B117: -2.99 | N117: 45193 | P117: 112.40333 | R117: 112.40333
A118: Qtr3 | B118: 880.82 | N118: 45194 | P118: 76.373333 | R118: 76.373333
A119: Jul | B119: -440.34 | N119: 45195 | O119: 2740.64 | R119: 2740.64
A120: 45108 | B120: -3 | N120: 45196 | O120: 2721.59 | P120: 72.25 | Q120: 529.95 | R120: 1107.93
A121: 45110 | B121: -900 | N121: 45197 | Q121: 480.352 | R121: 480.352
A122: 45112 | B122: 1246.25 | N122: 45198 | P122: 244.8675 | Q122: 215.35333 | R122: 232.21857
A123: 45113 | B123: -4.31 | N123: 45199 | P123: 239.24 | Q123: 2183.37 | R123: 1535.3267
A124: 45114 | B124: -27.11 | N124: Qtr4 | O124: 3416.921 | P124: 631.05938 | Q124: 618.86273 | R124: 1282.9266
A125: 45115 | B125: -31.02 | N125: Oct | O125: 3315.3095 | P125: 562.30097 | Q125: 383.4169 | R125: 1288.3806
A126: 45118 | B126: -2.98 | N126: 45200 | P126: 215.1 | Q126: 2148.37 | R126: 1503.9467
A127: 45119 | B127: -19.64 | N127: 45201 | O127: 2343.6867 | P127: 820.36 | Q127: 1227.77 | R127: 1544.3862
A128: 45121 | B128: 187.8 | N128: 45202 | O128: 3696.78 | R128: 3696.78
A129: 45125 | B129: -46.88 | N129: 45203 | P129: 1497.86 | Q129: 716.97 | R129: 1237.5633
A130: 45128 | B130: -68.06 | N130: 45204 | O130: 3692.72 | Q130: 705.49 | R130: 2199.105
A131: 45130 | B131: -16.8 | N131: 45205 | P131: 1486.74 | Q131: 685.5 | R131: 1086.12
A132: 45132 | B132: -750 | N132: 45206 | O132: 3686.72 | P132: 1475.52 | Q132: 640.138 | R132: 1502.7967
A133: 45134 | B133: -2.99 | N133: 45207 | Q133: 605.51 | R133: 605.51
A134: 45137 | B134: -1.6 | N134: 45208 | O134: 3635.59 | P134: 1224.45 | Q134: 564.175 | R134: 1497.0975
A135: Aug | B135: 268.36 | N135: 45209 | P135: 1202.65 | Q135: 537.17 | R135: 869.91
A136: 45139 | B136: 687.49 | N136: 45210 | P136: 428.38 | R136: 428.38
A137: 45140 | B137: -900 | N137: 45211 | P137: 402.91 | Q137: 518.37 | R137: 431.775
...

Sheet Análisis del presupuesto
B1: Total gastado
B2: Jan | C2: Feb | D2: Mar | E2: Apr | F2: May | G2: Jun | H2: Jul | I2: Aug | J2: Sep | K2: Oct | L2: Nov | M2: Dec
A3: Aporte a la casa | B3: =SUMIFS(Data!$I:$I, Data!$F:$F, $B59, Data!$C:$C, ">=" & DATE(2025, MATCH(C$56, {"Jan","Feb","Mar","Apr","May","Jun","Jul","Aug","Sep","Oct","Nov","Dec"}, 0), 1), Data!C:C, "<" & EDATE(DATE(2025, MATCH(C$56, {"Jan","Feb","Mar","Apr","May","Jun","Jul","Aug","Sep","Oct","Nov","Dec"}, 0), 1), 1)) -> 200 | C3: =SUMIFS(Data!$I:$I, Data!$F:$F, $B59, Data!$C:$C, ">=" & DATE(2025, MATCH(D$56, {"Jan","Feb","Mar","Apr","May","Jun","Jul","Aug","Sep","Oct","Nov","Dec"}, 0), 1), Data!D:D, "<" & EDATE(DATE(2025, MATCH(D$56, {"Jan","Feb","Mar","Apr","May","Jun","Jul","Aug","Sep","Oct","Nov","Dec"}, 0), 1), 1)) -> 600 | D3: =SUMIFS(Data!$I:$I, Data!$F:$F, $B59, Data!$C:$C, ">=" & DATE(2025, MATCH(E$56, {"Jan","Feb","Mar","Apr","May","Jun","Jul","Aug","Sep","Oct","Nov","Dec"}, 0), 1), Data!E:E, "<" & EDATE(DATE(2025, MATCH(E$56, {"Jan","Feb","Mar","Apr","May","Jun","Jul","Aug","Sep","Oct","Nov","Dec"}, 0), 1), 1)) -> 0 | E3: =SUMIFS(Data!$I:$I, Data!$F:$F, $B59, Data!$C:$C, ">=" & DATE(2025, MATCH(F$56, {"Jan","Feb","Mar","Apr","May","Jun","Jul","Aug","Sep","Oct","Nov","Dec"}, 0), 1), Data!F:F, "<" & EDATE(DATE(2025, MATCH(F$56, {"Jan","Feb","Mar","Apr","May","Jun","Jul","Aug","Sep","Oct","Nov","Dec"}, 0), 1), 1)) -> 0 | F3: =SUMIFS(Data!$I:$I, Data!$F:$F, $B59, Data!$C:$C, ">=" & DATE(2025, MATCH(G$56, {"Jan","Feb","Mar","Apr","May","Jun","Jul","Aug","Sep","Oct","Nov","Dec"}, 0), 1), Data!G:G, "<" & EDATE(DATE(2025, MATCH(G$56, {"Jan","Feb","Mar","Apr","May","Jun","Jul","Aug","Sep","Oct","Nov","Dec"}, 0), 1), 1)) -> 0 | G3: =SUMIFS(Data!$I:$I, Data!$F:$F, $B59, Data!$C:$C, ">=" & DATE(2025, MATCH(H$56, {"Jan","Feb","Mar","Apr","May","Jun","Jul","Aug","Sep","Oct","Nov","Dec"}, 0), 1), Data!H:H, "<" & EDATE(DATE(2025, MATCH(H$56, {"Jan","Feb","Mar","Apr","May","Jun","Jul","Aug","Sep","Oct","Nov","Dec"}, 0), 1), 1)) -> 0 | H3: =SUMIFS(Data!$I:$I, Data!$F:$F, $B59, Data!$C:$C, ">=" & DATE(2025, MATCH(I$56, {"Jan","Feb","Mar","Apr","May","Jun","Jul","Aug","Sep","Oct","Nov","Dec"}, 0), 1), Data!I:I, "<" & EDATE(DATE(2025, MATCH(I$56, {"Jan","Feb","Mar","Apr","May","Jun","Jul","Aug","Sep","Oct","Nov","Dec"}, 0), 1), 1)) -> 1416 | I3: =SUMIFS(Data!$I:$I, Data!$F:$F, $B59, Data!$C:$C, ">=" & DATE(2025, MATCH(J$56, {"Jan","Feb","Mar","Apr","May","Jun","Jul","Aug","Sep","Oct","Nov","Dec"}, 0), 1), Data!J:J, "<" & EDATE(DATE(2025, MATCH(J$56, {"Jan","Feb","Mar","Apr","May","Jun","Jul","Aug","Sep","Oct","Nov","Dec"}, 0), 1), 1)) -> 0 | J3: =SUMIFS(Data!$I:$I, Data!$F:$F, $B59, Data!$C:$C, ">=" & DATE(2025, MATCH(K$56, {"Jan","Feb","Mar","Apr","May","Jun","Jul","Aug","Sep","Oct","Nov","Dec"}, 0), 1), Data!K:K, "<" & EDATE(DATE(2025, MATCH(K$56, {"Jan","Feb","Mar","Apr","May","Jun","Jul","Aug","Sep","Oct","Nov","Dec"}, 0), 1), 1)) -> 1400 | K3: =SUMIFS(Data!$I:$I, Data!$F:$F, $B59, Data!$C:$C, ">=" & DATE(2025, MATCH(L$56, {"Jan","Feb","Mar","Apr","May","Jun","Jul","Aug","Sep","Oct","Nov","Dec"}, 0), 1), Data!L:L, "<" & EDATE(DATE(2025, MATCH(L$56, {"Jan","Feb","Mar","Apr","May","Jun","Jul","Aug","Sep","Oct","Nov","Dec"}, 0), 1), 1)) -> 0 | L3: =SUMIFS(Data!$I:$I, Data!$F:$F, $B59, Data!$C:$C, ">=" & DATE(2025, MATCH(M$56, {"Jan","Feb","Mar","Apr","May","Jun","Jul","Aug","Sep","Oct","Nov","Dec"}, 0), 1), Data!M:M, "<" & EDATE(DATE(2025, MATCH(M$56, {"Jan","Feb","Mar","Apr","May","Jun","Jul","Aug","Sep","Oct","Nov","Dec"}, 0), 1), 1)) -> 0 | M3: =SUMIFS(Data!$I:$I, Data!$F:$F, $B59, Data!$C:$C, ">=" & DATE(2025, MATCH(N$56, {"Jan","Feb","Mar","Apr","May","Jun","Jul","Aug","Sep","Oct","Nov","Dec"}, 0), 1), Data!N:N, "<" & EDATE(DATE(2025, MATCH(N$56, {"Jan","Feb","Mar","Apr","May","Jun","Jul","Aug","Sep","Oct","Nov","Dec"}, 0), 1), 1)) -> 0
A4: Sueldo | B4: =SUMIFS(Data!I:I, Data!F:F, $B60, Data!C:C, ">=" & DATE(2025, MATCH(C$56, {"Jan","Feb","Mar","Apr","May","Jun","Jul","Aug","Sep","Oct","Nov","Dec"}, 0), 1), Data!C:C, "<" & EDATE(DATE(2025, MATCH(C$56, {"Jan","Feb","Mar","Apr","May","Jun","Jul","Aug","Sep","Oct","Nov","Dec"}, 0), 1), 1)) -> 4529.03 | C4: =SUMIFS(Data!$I:$I, Data!$F:$F, $B60, Data!$C:$C, ">=" & DATE(2025, MATCH(D$56, {"Jan","Feb","Mar","Apr","May","Jun","Jul","Aug","Sep","Oct","Nov","Dec"}, 0), 1), Data!D:D, "<" & EDATE(DATE(2025, MATCH(D$56, {"Jan","Feb","Mar","Apr","May","Jun","Jul","Aug","Sep","Oct","Nov","Dec"}, 0), 1), 1)) -> 15788.77 | D4: =SUMIFS(Data!$I:$I, Data!$F:$F, $B60, Data!$C:$C, ">=" & DATE(2025, MATCH(E$56, {"Jan","Feb","Mar","Apr","May","Jun","Jul","Aug","Sep","Oct","Nov","Dec"}, 0), 1), Data!E:E, "<" & EDATE(DATE(2025, MATCH(E$56, {"Jan","Feb","Mar","Apr","May","Jun","Jul","Aug","Sep","Oct","Nov","Dec"}, 0), 1), 1)) -> 10082.66 | E4: =SUMIFS(Data!$I:$I, Data!$F:$F, $B60, Data!$C:$C, ">=" & DATE(2025, MATCH(F$56, {"Jan","Feb","Mar","Apr","May","Jun","Jul","Aug","Sep","Oct","Nov","Dec"}, 0), 1), Data!F:F, "<" & EDATE(DATE(2025, MATCH(F$56, {"Jan","Feb","Mar","Apr","May","Jun","Jul","Aug","Sep","Oct","Nov","Dec"}, 0), 1), 1)) -> 0 | F4: =SUMIFS(Data!$I:$I, Data!$F:$F, $B60, Data!$C:$C, ">=" & DATE(2025, MATCH(G$56, {"Jan","Feb","Mar","Apr","May","Jun","Jul","Aug","Sep","Oct","Nov","Dec"}, 0), 1), Data!G:G, "<" & EDATE(DATE(2025, MATCH(G$56, {"Jan","Feb","Mar","Apr","May","Jun","Jul","Aug","Sep","Oct","Nov","Dec"}, 0), 1), 1)) -> 0 | G4: =SUMIFS(Data!$I:$I, Data!$F:$F, $B60, Data!$C:$C, ">=" & DATE(2025, MATCH(H$56, {"Jan","Feb","Mar","Apr","May","Jun","Jul","Aug","Sep","Oct","Nov","Dec"}, 0), 1), Data!H:H, "<" & EDATE(DATE(2025, MATCH(H$56, {"Jan","Feb","Mar","Apr","May","Jun","Jul","Aug","Sep","Oct","Nov","Dec"}, 0), 1), 1)) -> 0 | H4: =SUMIFS(Data!$I:$I, Data!$F:$F, $B60, Data!$C:$C, ">=" & DATE(2025, MATCH(I$56, {"Jan","Feb","Mar","Apr","May","Jun","Jul","Aug","Sep","Oct","Nov","Dec"}, 0), 1), Data!I:I, "<" & EDATE(DATE(2025, MATCH(I$56, {"Jan","Feb","Mar","Apr","May","Jun","Jul","Aug","Sep","Oct","Nov","Dec"}, 0), 1), 1)) -> 36625.58 | I4: =SUMIFS(Data!$I:$I, Data!$F:$F, $B60, Data!$C:$C, ">=" & DATE(2025, MATCH(J$56, {"Jan","Feb","Mar","Apr","May","Jun","Jul","Aug","Sep","Oct","Nov","Dec"}, 0), 1), Data!J:J, "<" & EDATE(DATE(2025, MATCH(J$56, {"Jan","Feb","Mar","Apr","May","Jun","Jul","Aug","Sep","Oct","Nov","Dec"}, 0), 1), 1)) -> 0 | J4: =SUMIFS(Data!$I:$I, Data!$F:$F, $B60, Data!$C:$C, ">=" & DATE(2025, MATCH(K$56, {"Jan","Feb","Mar","Apr","May","Jun","Jul","Aug","Sep","Oct","Nov","Dec"}, 0), 1), Data!K:K, "<" & EDATE(DATE(2025, MATCH(K$56, {"Jan","Feb","Mar","Apr","May","Jun","Jul","Aug","Sep","Oct","Nov","Dec"}, 0), 1), 1)) -> 34421.45 | K4: =SUMIFS(Data!$I:$I, Data!$F:$F, $B60, Data!$C:$C, ">=" & DATE(2025, MATCH(L$56, {"Jan","Feb","Mar","Apr","May","Jun","Jul","Aug","Sep","Oct","Nov","Dec"}, 0), 1), Data!L:L, "<" & EDATE(DATE(2025, MATCH(L$56, {"Jan","Feb","Mar","Apr","May","Jun","Jul","Aug","Sep","Oct","Nov","Dec"}, 0), 1), 1)) -> 0 | L4: =SUMIFS(Data!$I:$I, Data!$F:$F, $B60, Data!$C:$C, ">=" & DATE(2025, MATCH(M$56, {"Jan","Feb","Mar","Apr","May","Jun","Jul","Aug","Sep","Oct","Nov","Dec"}, 0), 1), Data!M:M, "<" & EDATE(DATE(2025, MATCH(M$56, {"Jan","Feb","Mar","Apr","May","Jun","Jul","Aug","Sep","Oct","Nov","Dec"}, 0), 1), 1)) -> 0 | M4: =SUMIFS(Data!$I:$I, Data!$F:$F, $B60, Data!$C:$C, ">=" & DATE(2025, MATCH(N$56, {"Jan","Feb","Mar","Apr","May","Jun","Jul","Aug","Sep","Oct","Nov","Dec"}, 0), 1), Data!N:N, "<" & EDATE(DATE(2025, MATCH(N$56, {"Jan","Feb","Mar","Apr","May","Jun","Jul","Aug","Sep","Oct","Nov","Dec"}, 0), 1), 1)) -> 0
B5: =SUMIFS(Data!I:I, Data!F:F, $B61, Data!C:C, ">=" & DATE(2025, MATCH(C$56, {"Jan","Feb","Mar","Apr","May","Jun","Jul","Aug","Sep","Oct","Nov","Dec"}, 0), 1), Data!C:C, "<" & EDATE(DATE(2025, MATCH(C$56, {"Jan","Feb","Mar","Apr","May","Jun","Jul","Aug","Sep","Oct","Nov","Dec"}, 0), 1), 1)) -> 0 | C5: =SUMIFS(Data!$I:$I, Data!$F:$F, $B61, Data!$C:$C, ">=" & DATE(2025, MATCH(D$56, {"Jan","Feb","Mar","Apr","May","Jun","Jul","Aug","Sep","Oct","Nov","Dec"}, 0), 1), Data!D:D, "<" & EDATE(DATE(2025, MATCH(D$56, {"Jan","Feb","Mar","Apr","May","Jun","Jul","Aug","Sep","Oct","Nov","Dec"}, 0), 1), 1)) -> 0 | D5: =SUMIFS(Data!$I:$I, Data!$F:$F, $B61, Data!$C:$C, ">=" & DATE(2025, MATCH(E$56, {"Jan","Feb","Mar","Apr","May","Jun","Jul","Aug","Sep","Oct","Nov","Dec"}, 0), 1), Data!E:E, "<" & EDATE(DATE(2025, MATCH(E$56, {"Jan","Feb","Mar","Apr","May","Jun","Jul","Aug","Sep","Oct","Nov","Dec"}, 0), 1), 1)) -> 0 | E5: =SUMIFS(Data!$I:$I, Data!$F:$F, $B61, Data!$C:$C, ">=" & DATE(2025, MATCH(F$56, {"Jan","Feb","Mar","Apr","May","Jun","Jul","Aug","Sep","Oct","Nov","Dec"}, 0), 1), Data!F:F, "<" & EDATE(DATE(2025, MATCH(F$56, {"Jan","Feb","Mar","Apr","May","Jun","Jul","Aug","Sep","Oct","Nov","Dec"}, 0), 1), 1)) -> 0 | F5: =SUMIFS(Data!$I:$I, Data!$F:$F, $B61, Data!$C:$C, ">=" & DATE(2025, MATCH(G$56, {"Jan","Feb","Mar","Apr","May","Jun","Jul","Aug","Sep","Oct","Nov","Dec"}, 0), 1), Data!G:G, "<" & EDATE(DATE(2025, MATCH(G$56, {"Jan","Feb","Mar","Apr","May","Jun","Jul","Aug","Sep","Oct","Nov","Dec"}, 0), 1), 1)) -> 0 | G5: =SUMIFS(Data!$I:$I, Data!$F:$F, $B61, Data!$C:$C, ">=" & DATE(2025, MATCH(H$56, {"Jan","Feb","Mar","Apr","May","Jun","Jul","Aug","Sep","Oct","Nov","Dec"}, 0), 1), Data!H:H, "<" & EDATE(DATE(2025, MATCH(H$56, {"Jan","Feb","Mar","Apr","May","Jun","Jul","Aug","Sep","Oct","Nov","Dec"}, 0), 1), 1)) -> 0 | H5: =SUMIFS(Data!$I:$I, Data!$F:$F, $B61, Data!$C:$C, ">=" & DATE(2025, MATCH(I$56, {"Jan","Feb","Mar","Apr","May","Jun","Jul","Aug","Sep","Oct","Nov","Dec"}, 0), 1), Data!I:I, "<" & EDATE(DATE(2025, MATCH(I$56, {"Jan","Feb","Mar","Apr","May","Jun","Jul","Aug","Sep","Oct","Nov","Dec"}, 0), 1), 1)) -> 0 | I5: =SUMIFS(Data!$I:$I, Data!$F:$F, $B61, Data!$C:$C, ">=" & DATE(2025, MATCH(J$56, {"Jan","Feb","Mar","Apr","May","Jun","Jul","Aug","Sep","Oct","Nov","Dec"}, 0), 1), Data!J:J, "<" & EDATE(DATE(2025, MATCH(J$56, {"Jan","Feb","Mar","Apr","May","Jun","Jul","Aug","Sep","Oct","Nov","Dec"}, 0), 1), 1)) -> 0 | J5: =SUMIFS(Data!$I:$I, Data!$F:$F, $B61, Data!$C:$C, ">=" & DATE(2025, MATCH(K$56, {"Jan","Feb","Mar","Apr","May","Jun","Jul","Aug","Sep","Oct","Nov","Dec"}, 0), 1), Data!K:K, "<" & EDATE(DATE(2025, MATCH(K$56, {"Jan","Feb","Mar","Apr","May","Jun","Jul","Aug","Sep","Oct","Nov","Dec"}, 0), 1), 1)) -> 0 | K5: =SUMIFS(Data!$I:$I, Data!$F:$F, $B61, Data!$C:$C, ">=" & DATE(2025, MATCH(L$56, {"Jan","Feb","Mar","Apr","May","Jun","Jul","Aug","Sep","Oct","Nov","Dec"}, 0), 1), Data!L:L, "<" & EDATE(DATE(2025, MATCH(L$56, {"Jan","Feb","Mar","Apr","May","Jun","Jul","Aug","Sep","Oct","Nov","Dec"}, 0), 1), 1)) -> 0 | L5: =SUMIFS(Data!$I:$I, Data!$F:$F, $B61, Data!$C:$C, ">=" & DATE(2025, MATCH(M$56, {"Jan","Feb","Mar","Apr","May","Jun","Jul","Aug","Sep","Oct","Nov","Dec"}, 0), 1), Data!M:M, "<" & EDATE(DATE(2025, MATCH(M$56, {"Jan","Feb","Mar","Apr","May","Jun","Jul","Aug","Sep","Oct","Nov","Dec"}, 0), 1), 1)) -> 0 | M5: =SUMIFS(Data!$I:$I, Data!$F:$F, $B61, Data!$C:$C, ">=" & DATE(2025, MATCH(N$56, {"Jan","Feb","Mar","Apr","May","Jun","Jul","Aug","Sep","Oct","Nov","Dec"}, 0), 1), Data!N:N, "<" & EDATE(DATE(2025, MATCH(N$56, {"Jan","Feb","Mar","Apr","May","Jun","Jul","Aug","Sep","Oct","Nov","Dec"}, 0), 1), 1)) -> 0
A6: Alquiler | B6: =SUMIFS(Data!I:I, Data!F:F, $B62, Data!C:C, ">=" & DATE(2025, MATCH(C$56, {"Jan","Feb","Mar","Apr","May","Jun","Jul","Aug","Sep","Oct","Nov","Dec"}, 0), 1), Data!C:C, "<" & EDATE(DATE(2025, MATCH(C$56, {"Jan","Feb","Mar","Apr","May","Jun","Jul","Aug","Sep","Oct","Nov","Dec"}, 0), 1), 1)) -> 0 | C6: =SUMIFS(Data!$I:$I, Data!$F:$F, $B62, Data!$C:$C, ">=" & DATE(2025, MATCH(D$56, {"Jan","Feb","Mar","Apr","May","Jun","Jul","Aug","Sep","Oct","Nov","Dec"}, 0), 1), Data!D:D, "<" & EDATE(DATE(2025, MATCH(D$56, {"Jan","Feb","Mar","Apr","May","Jun","Jul","Aug","Sep","Oct","Nov","Dec"}, 0), 1), 1)) -> -1872 | D6: =SUMIFS(Data!$I:$I, Data!$F:$F, $B62, Data!$C:$C, ">=" & DATE(2025, MATCH(E$56, {"Jan","Feb","Mar","Apr","May","Jun","Jul","Aug","Sep","Oct","Nov","Dec"}, 0), 1), Data!E:E, "<" & EDATE(DATE(2025, MATCH(E$56, {"Jan","Feb","Mar","Apr","May","Jun","Jul","Aug","Sep","Oct","Nov","Dec"}, 0), 1), 1)) -> -1836 | E6: =SUMIFS(Data!$I:$I, Data!$F:$F, $B62, Data!$C:$C, ">=" & DATE(2025, MATCH(F$56, {"Jan","Feb","Mar","Apr","May","Jun","Jul","Aug","Sep","Oct","Nov","Dec"}, 0), 1), Data!F:F, "<" & EDATE(DATE(2025, MATCH(F$56, {"Jan","Feb","Mar","Apr","May","Jun","Jul","Aug","Sep","Oct","Nov","Dec"}, 0), 1), 1)) -> 0 | F6: =SUMIFS(Data!$I:$I, Data!$F:$F, $B62, Data!$C:$C, ">=" & DATE(2025, MATCH(G$56, {"Jan","Feb","Mar","Apr","May","Jun","Jul","Aug","Sep","Oct","Nov","Dec"}, 0), 1), Data!G:G, "<" & EDATE(DATE(2025, MATCH(G$56, {"Jan","Feb","Mar","Apr","May","Jun","Jul","Aug","Sep","Oct","Nov","Dec"}, 0), 1), 1)) -> 0 | G6: =SUMIFS(Data!$I:$I, Data!$F:$F, $B62, Data!$C:$C, ">=" & DATE(2025, MATCH(H$56, {"Jan","Feb","Mar","Apr","May","Jun","Jul","Aug","Sep","Oct","Nov","Dec"}, 0), 1), Data!H:H, "<" & EDATE(DATE(2025, MATCH(H$56, {"Jan","Feb","Mar","Apr","May","Jun","Jul","Aug","Sep","Oct","Nov","Dec"}, 0), 1), 1)) -> 0 | H6: =SUMIFS(Data!$I:$I, Data!$F:$F, $B62, Data!$C:$C, ">=" & DATE(2025, MATCH(I$56, {"Jan","Feb","Mar","Apr","May","Jun","Jul","Aug","Sep","Oct","Nov","Dec"}, 0), 1), Data!I:I, "<" & EDATE(DATE(2025, MATCH(I$56, {"Jan","Feb","Mar","Apr","May","Jun","Jul","Aug","Sep","Oct","Nov","Dec"}, 0), 1), 1)) -> -9895 | I6: =SUMIFS(Data!$I:$I, Data!$F:$F, $B62, Data!$C:$C, ">=" & DATE(2025, MATCH(J$56, {"Jan","Feb","Mar","Apr","May","Jun","Jul","Aug","Sep","Oct","Nov","Dec"}, 0), 1), Data!J:J, "<" & EDATE(DATE(2025, MATCH(J$56, {"Jan","Feb","Mar","Apr","May","Jun","Jul","Aug","Sep","Oct","Nov","Dec"}, 0), 1), 1)) -> 0 | J6: =SUMIFS(Data!$I:$I, Data!$F:$F, $B62, Data!$C:$C, ">=" & DATE(2025, MATCH(K$56, {"Jan","Feb","Mar","Apr","May","Jun","Jul","Aug","Sep","Oct","Nov","Dec"}, 0), 1), Data!K:K, "<" & EDATE(DATE(2025, MATCH(K$56, {"Jan","Feb","Mar","Apr","May","Jun","Jul","Aug","Sep","Oct","Nov","Dec"}, 0), 1), 1)) -> -8041 | K6: =SUMIFS(Data!$I:$I, Data!$F:$F, $B62, Data!$C:$C, ">=" & DATE(2025, MATCH(L$56, {"Jan","Feb","Mar","Apr","May","Jun","Jul","Aug","Sep","Oct","Nov","Dec"}, 0), 1), Data!L:L, "<" & EDATE(DATE(2025, MATCH(L$56, {"Jan","Feb","Mar","Apr","May","Jun","Jul","Aug","Sep","Oct","Nov","Dec"}, 0), 1), 1)) -> 0 | L6: =SUMIFS(Data!$I:$I, Data!$F:$F, $B62, Data!$C:$C, ">=" & DATE(2025, MATCH(M$56, {"Jan","Feb","Mar","Apr","May","Jun","Jul","Aug","Sep","Oct","Nov","Dec"}, 0), 1), Data!M:M, "<" & EDATE(DATE(2025, MATCH(M$56, {"Jan","Feb","Mar","Apr","May","Jun","Jul","Aug","Sep","Oct","Nov","Dec"}, 0), 1), 1)) -> 0 | M6: =SUMIFS(Data!$I:$I, Data!$F:$F, $B62, Data!$C:$C, ">=" & DATE(2025, MATCH(N$56, {"Jan","Feb","Mar","Apr","May","Jun","Jul","Aug","Sep","Oct","Nov","Dec"}, 0), 1), Data!N:N, "<" & EDATE(DATE(2025, MATCH(N$56, {"Jan","Feb","Mar","Apr","May","Jun","Jul","Aug","Sep","Oct","Nov","Dec"}, 0), 1), 1)) -> 0
A7: ayes | B7: =SUMIFS(Data!I:I, Data!F:F, $B63, Data!C:C, ">=" & DATE(2025, MATCH(C$56, {"Jan","Feb","Mar","Apr","May","Jun","Jul","Aug","Sep","Oct","Nov","Dec"}, 0), 1), Data!C:C, "<" & EDATE(DATE(2025, MATCH(C$56, {"Jan","Feb","Mar","Apr","May","Jun","Jul","Aug","Sep","Oct","Nov","Dec"}, 0), 1), 1)) -> 0 | C7: =SUMIFS(Data!$I:$I, Data!$F:$F, $B63, Data!$C:$C, ">=" & DATE(2025, MATCH(D$56, {"Jan","Feb","Mar","Apr","May","Jun","Jul","Aug","Sep","Oct","Nov","Dec"}, 0), 1), Data!D:D, "<" & EDATE(DATE(2025, MATCH(D$56, {"Jan","Feb","Mar","Apr","May","Jun","Jul","Aug","Sep","Oct","Nov","Dec"}, 0), 1), 1)) -> 0 | D7: =SUMIFS(Data!$I:$I, Data!$F:$F, $B63, Data!$C:$C, ">=" & DATE(2025, MATCH(E$56, {"Jan","Feb","Mar","Apr","May","Jun","Jul","Aug","Sep","Oct","Nov","Dec"}, 0), 1), Data!E:E, "<" & EDATE(DATE(2025, MATCH(E$56, {"Jan","Feb","Mar","Apr","May","Jun","Jul","Aug","Sep","Oct","Nov","Dec"}, 0), 1), 1)) -> 0 | E7: =SUMIFS(Data!$I:$I, Data!$F:$F, $B63, Data!$C:$C, ">=" & DATE(2025, MATCH(F$56, {"Jan","Feb","Mar","Apr","May","Jun","Jul","Aug","Sep","Oct","Nov","Dec"}, 0), 1), Data!F:F, "<" & EDATE(DATE(2025, MATCH(F$56, {"Jan","Feb","Mar","Apr","May","Jun","Jul","Aug","Sep","Oct","Nov","Dec"}, 0), 1), 1)) -> 0 | F7: =SUMIFS(Data!$I:$I, Data!$F:$F, $B63, Data!$C:$C, ">=" & DATE(2025, MATCH(G$56, {"Jan","Feb","Mar","Apr","May","Jun","Jul","Aug","Sep","Oct","Nov","Dec"}, 0), 1), Data!G:G, "<" & EDATE(DATE(2025, MATCH(G$56, {"Jan","Feb","Mar","Apr","May","Jun","Jul","Aug","Sep","Oct","Nov","Dec"}, 0), 1), 1)) -> 0 | G7: =SUMIFS(Data!$I:$I, Data!$F:$F, $B63, Data!$C:$C, ">=" & DATE(2025, MATCH(H$56, {"Jan","Feb","Mar","Apr","May","Jun","Jul","Aug","Sep","Oct","Nov","Dec"}, 0), 1), Data!H:H, "<" & EDATE(DATE(2025, MATCH(H$56, {"Jan","Feb","Mar","Apr","May","Jun","Jul","Aug","Sep","Oct","Nov","Dec"}, 0), 1), 1)) -> 0 | H7: =SUMIFS(Data!$I:$I, Data!$F:$F, $B63, Data!$C:$C, ">=" & DATE(2025, MATCH(I$56, {"Jan","Feb","Mar","Apr","May","Jun","Jul","Aug","Sep","Oct","Nov","Dec"}, 0), 1), Data!I:I, "<" & EDATE(DATE(2025, MATCH(I$56, {"Jan","Feb","Mar","Apr","May","Jun","Jul","Aug","Sep","Oct","Nov","Dec"}, 0), 1), 1)) -> 0 | I7: =SUMIFS(Data!$I:$I, Data!$F:$F, $B63, Data!$C:$C, ">=" & DATE(2025, MATCH(J$56, {"Jan","Feb","Mar","Apr","May","Jun","Jul","Aug","Sep","Oct","Nov","Dec"}, 0), 1), Data!J:J, "<" & EDATE(DATE(2025, MATCH(J$56, {"Jan","Feb","Mar","Apr","May","Jun","Jul","Aug","Sep","Oct","Nov","Dec"}, 0), 1), 1)) -> 0 | J7: =SUMIFS(Data!$I:$I, Data!$F:$F, $B63, Data!$C:$C, ">=" & DATE(2025, MATCH(K$56, {"Jan","Feb","Mar","Apr","May","Jun","Jul","Aug","Sep","Oct","Nov","Dec"}, 0), 1), Data!K:K, "<" & EDATE(DATE(2025, MATCH(K$56, {"Jan","Feb","Mar","Apr","May","Jun","Jul","Aug","Sep","Oct","Nov","Dec"}, 0), 1), 1)) -> 0 | K7: =SUMIFS(Data!$I:$I, Data!$F:$F, $B63, Data!$C:$C, ">=" & DATE(2025, MATCH(L$56, {"Jan","Feb","Mar","Apr","May","Jun","Jul","Aug","Sep","Oct","Nov","Dec"}, 0), 1), Data!L:L, "<" & EDATE(DATE(2025, MATCH(L$56, {"Jan","Feb","Mar","Apr","May","Jun","Jul","Aug","Sep","Oct","Nov","Dec"}, 0), 1), 1)) -> 0 | L7: =SUMIFS(Data!$I:$I, Data!$F:$F, $B63, Data!$C:$C, ">=" & DATE(2025, MATCH(M$56, {"Jan","Feb","Mar","Apr","May","Jun","Jul","Aug","Sep","Oct","Nov","Dec"}, 0), 1), Data!M:M, "<" & EDATE(DATE(2025, MATCH(M$56, {"Jan","Feb","Mar","Apr","May","Jun","Jul","Aug","Sep","Oct","Nov","Dec"}, 0), 1), 1)) -> 0 | M7: =SUMIFS(Data!$I:$I, Data!$F:$F, $B63, Data!$C:$C, ">=" & DATE(2025, MATCH(N$56, {"Jan","Feb","Mar","Apr","May","Jun","Jul","Aug","Sep","Oct","Nov","Dec"}, 0), 1), Data!N:N, "<" & EDATE(DATE(2025, MATCH(N$56, {"Jan","Feb","Mar","Apr","May","Jun","Jul","Aug","Sep","Oct","Nov","Dec"}, 0), 1), 1)) -> 0
A8: café | B8: =SUMIFS(Data!I:I, Data!F:F, $B64, Data!C:C, ">=" & DATE(2025, MATCH(C$56, {"Jan","Feb","Mar","Apr","May","Jun","Jul","Aug","Sep","Oct","Nov","Dec"}, 0), 1), Data!C:C, "<" & EDATE(DATE(2025, MATCH(C$56, {"Jan","Feb","Mar","Apr","May","Jun","Jul","Aug","Sep","Oct","Nov","Dec"}, 0), 1), 1)) -> -33.2 | C8: =SUMIFS(Data!$I:$I, Data!$F:$F, $B64, Data!$C:$C, ">=" & DATE(2025, MATCH(D$56, {"Jan","Feb","Mar","Apr","May","Jun","Jul","Aug","Sep","Oct","Nov","Dec"}, 0), 1), Data!D:D, "<" & EDATE(DATE(2025, MATCH(D$56, {"Jan","Feb","Mar","Apr","May","Jun","Jul","Aug","Sep","Oct","Nov","Dec"}, 0), 1), 1)) -> -18.29 | D8: =SUMIFS(Data!$I:$I, Data!$F:$F, $B64, Data!$C:$C, ">=" & DATE(2025, MATCH(E$56, {"Jan","Feb","Mar","Apr","May","Jun","Jul","Aug","Sep","Oct","Nov","Dec"}, 0), 1), Data!E:E, "<" & EDATE(DATE(2025, MATCH(E$56, {"Jan","Feb","Mar","Apr","May","Jun","Jul","Aug","Sep","Oct","Nov","Dec"}, 0), 1), 1)) -> 0 | E8: =SUMIFS(Data!$I:$I, Data!$F:$F, $B64, Data!$C:$C, ">=" & DATE(2025, MATCH(F$56, {"Jan","Feb","Mar","Apr","May","Jun","Jul","Aug","Sep","Oct","Nov","Dec"}, 0), 1), Data!F:F, "<" & EDATE(DATE(2025, MATCH(F$56, {"Jan","Feb","Mar","Apr","May","Jun","Jul","Aug","Sep","Oct","Nov","Dec"}, 0), 1), 1)) -> 0 | F8: =SUMIFS(Data!$I:$I, Data!$F:$F, $B64, Data!$C:$C, ">=" & DATE(2025, MATCH(G$56, {"Jan","Feb","Mar","Apr","May","Jun","Jul","Aug","Sep","Oct","Nov","Dec"}, 0), 1), Data!G:G, "<" & EDATE(DATE(2025, MATCH(G$56, {"Jan","Feb","Mar","Apr","May","Jun","Jul","Aug","Sep","Oct","Nov","Dec"}, 0), 1), 1)) -> 0 | G8: =SUMIFS(Data!$I:$I, Data!$F:$F, $B64, Data!$C:$C, ">=" & DATE(2025, MATCH(H$56, {"Jan","Feb","Mar","Apr","May","Jun","Jul","Aug","Sep","Oct","Nov","Dec"}, 0), 1), Data!H:H, "<" & EDATE(DATE(2025, MATCH(H$56, {"Jan","Feb","Mar","Apr","May","Jun","Jul","Aug","Sep","Oct","Nov","Dec"}, 0), 1), 1)) -> 0 | H8: =SUMIFS(Data!$I:$I, Data!$F:$F, $B64, Data!$C:$C, ">=" & DATE(2025, MATCH(I$56, {"Jan","Feb","Mar","Apr","May","Jun","Jul","Aug","Sep","Oct","Nov","Dec"}, 0), 1), Data!I:I, "<" & EDATE(DATE(2025, MATCH(I$56, {"Jan","Feb","Mar","Apr","May","Jun","Jul","Aug","Sep","Oct","Nov","Dec"}, 0), 1), 1)) -> -34.79 | I8: =SUMIFS(Data!$I:$I, Data!$F:$F, $B64, Data!$C:$C, ">=" & DATE(2025, MATCH(J$56, {"Jan","Feb","Mar","Apr","May","Jun","Jul","Aug","Sep","Oct","Nov","Dec"}, 0), 1), Data!J:J, "<" & EDATE(DATE(2025, MATCH(J$56, {"Jan","Feb","Mar","Apr","May","Jun","Jul","Aug","Sep","Oct","Nov","Dec"}, 0), 1), 1)) -> 0 | J8: =SUMIFS(Data!$I:$I, Data!$F:$F, $B64, Data!$C:$C, ">=" & DATE(2025, MATCH(K$56, {"Jan","Feb","Mar","Apr","May","Jun","Jul","Aug","Sep","Oct","Nov","Dec"}, 0), 1), Data!K:K, "<" & EDATE(DATE(2025, MATCH(K$56, {"Jan","Feb","Mar","Apr","May","Jun","Jul","Aug","Sep","Oct","Nov","Dec"}, 0), 1), 1)) -> -28.79 | K8: =SUMIFS(Data!$I:$I, Data!$F:$F, $B64, Data!$C:$C, ">=" & DATE(2025, MATCH(L$56, {"Jan","Feb","Mar","Apr","May","Jun","Jul","Aug","Sep","Oct","Nov","Dec"}, 0), 1), Data!L:L, "<" & EDATE(DATE(2025, MATCH(L$56, {"Jan","Feb","Mar","Apr","May","Jun","Jul","Aug","Sep","Oct","Nov","Dec"}, 0), 1), 1)) -> 0 | L8: =SUMIFS(Data!$I:$I, Data!$F:$F, $B64, Data!$C:$C, ">=" & DATE(2025, MATCH(M$56, {"Jan","Feb","Mar","Apr","May","Jun","Jul","Aug","Sep","Oct","Nov","Dec"}, 0), 1), Data!M:M, "<" & EDATE(DATE(2025, MATCH(M$56, {"Jan","Feb","Mar","Apr","May","Jun","Jul","Aug","Sep","Oct","Nov","Dec"}, 0), 1), 1)) -> 0 | M8: =SUMIFS(Data!$I:$I, Data!$F:$F, $B64, Data!$C:$C, ">=" & DATE(2025, MATCH(N$56, {"Jan","Feb","Mar","Apr","May","Jun","Jul","Aug","Sep","Oct","Nov","Dec"}, 0), 1), Data!N:N, "<" & EDATE(DATE(2025, MATCH(N$56, {"Jan","Feb","Mar","Apr","May","Jun","Jul","Aug","Sep","Oct","Nov","Dec"}, 0), 1), 1)) -> 0
A9: Compras | B9: =SUMIFS(Data!I:I, Data!F:F, $B65, Data!C:C, ">=" & DATE(2025, MATCH(C$56, {"Jan","Feb","Mar","Apr","May","Jun","Jul","Aug","Sep","Oct","Nov","Dec"}, 0), 1), Data!C:C, "<" & EDATE(DATE(2025, MATCH(C$56, {"Jan","Feb","Mar","Apr","May","Jun","Jul","Aug","Sep","Oct","Nov","Dec"}, 0), 1), 1)) -> -252.33 | C9: =SUMIFS(Data!$I:$I, Data!$F:$F, $B65, Data!$C:$C, ">=" & DATE(2025, MATCH(D$56, {"Jan","Feb","Mar","Apr","May","Jun","Jul","Aug","Sep","Oct","Nov","Dec"}, 0), 1), Data!D:D, "<" & EDATE(DATE(2025, MATCH(D$56, {"Jan","Feb","Mar","Apr","May","Jun","Jul","Aug","Sep","Oct","Nov","Dec"}, 0), 1), 1)) -> -1231.36 | D9: =SUMIFS(Data!$I:$I, Data!$F:$F, $B65, Data!$C:$C, ">=" & DATE(2025, MATCH(E$56, {"Jan","Feb","Mar","Apr","May","Jun","Jul","Aug","Sep","Oct","Nov","Dec"}, 0), 1), Data!E:E, "<" & EDATE(DATE(2025, MATCH(E$56, {"Jan","Feb","Mar","Apr","May","Jun","Jul","Aug","Sep","Oct","Nov","Dec"}, 0), 1), 1)) -> -1092.27 | E9: =SUMIFS(Data!$I:$I, Data!$F:$F, $B65, Data!$C:$C, ">=" & DATE(2025, MATCH(F$56, {"Jan","Feb","Mar","Apr","May","Jun","Jul","Aug","Sep","Oct","Nov","Dec"}, 0), 1), Data!F:F, "<" & EDATE(DATE(2025, MATCH(F$56, {"Jan","Feb","Mar","Apr","May","Jun","Jul","Aug","Sep","Oct","Nov","Dec"}, 0), 1), 1)) -> 0 | F9: =SUMIFS(Data!$I:$I, Data!$F:$F, $B65, Data!$C:$C, ">=" & DATE(2025, MATCH(G$56, {"Jan","Feb","Mar","Apr","May","Jun","Jul","Aug","Sep","Oct","Nov","Dec"}, 0), 1), Data!G:G, "<" & EDATE(DATE(2025, MATCH(G$56, {"Jan","Feb","Mar","Apr","May","Jun","Jul","Aug","Sep","Oct","Nov","Dec"}, 0), 1), 1)) -> 0 | G9: =SUMIFS(Data!$I:$I, Data!$F:$F, $B65, Data!$C:$C, ">=" & DATE(2025, MATCH(H$56, {"Jan","Feb","Mar","Apr","May","Jun","Jul","Aug","Sep","Oct","Nov","Dec"}, 0), 1), Data!H:H, "<" & EDATE(DATE(2025, MATCH(H$56, {"Jan","Feb","Mar","Apr","May","Jun","Jul","Aug","Sep","Oct","Nov","Dec"}, 0), 1), 1)) -> 0 | H9: =SUMIFS(Data!$I:$I, Data!$F:$F, $B65, Data!$C:$C, ">=" & DATE(2025, MATCH(I$56, {"Jan","Feb","Mar","Apr","May","Jun","Jul","Aug","Sep","Oct","Nov","Dec"}, 0), 1), Data!I:I, "<" & EDATE(DATE(2025, MATCH(I$56, {"Jan","Feb","Mar","Apr","May","Jun","Jul","Aug","Sep","Oct","Nov","Dec"}, 0), 1), 1)) -> -5736.73 | I9: =SUMIFS(Data!$I:$I, Data!$F:$F, $B65, Data!$C:$C, ">=" & DATE(2025, MATCH(J$56, {"Jan","Feb","Mar","Apr","May","Jun","Jul","Aug","Sep","Oct","Nov","Dec"}, 0), 1), Data!J:J, "<" & EDATE(DATE(2025, MATCH(J$56, {"Jan","Feb","Mar","Apr","May","Jun","Jul","Aug","Sep","Oct","Nov","Dec"}, 0), 1), 1)) -> 0 | J9: =SUMIFS(Data!$I:$I, Data!$F:$F, $B65, Data!$C:$C, ">=" & DATE(2025, MATCH(K$56, {"Jan","Feb","Mar","Apr","May","Jun","Jul","Aug","Sep","Oct","Nov","Dec"}, 0), 1), Data!K:K, "<" & EDATE(DATE(2025, MATCH(K$56, {"Jan","Feb","Mar","Apr","May","Jun","Jul","Aug","Sep","Oct","Nov","Dec"}, 0), 1), 1)) -> -5358.32 | K9: =SUMIFS(Data!$I:$I, Data!$F:$F, $B65, Data!$C:$C, ">=" & DATE(2025, MATCH(L$56, {"Jan","Feb","Mar","Apr","May","Jun","Jul","Aug","Sep","Oct","Nov","Dec"}, 0), 1), Data!L:L, "<" & EDATE(DATE(2025, MATCH(L$56, {"Jan","Feb","Mar","Apr","May","Jun","Jul","Aug","Sep","Oct","Nov","Dec"}, 0), 1), 1)) -> 0 | L9: =SUMIFS(Data!$I:$I, Data!$F:$F, $B65, Data!$C:$C, ">=" & DATE(2025, MATCH(M$56, {"Jan","Feb","Mar","Apr","May","Jun","Jul","Aug","Sep","Oct","Nov","Dec"}, 0), 1), Data!M:M, "<" & EDATE(DATE(2025, MATCH(M$56, {"Jan","Feb","Mar","Apr","May","Jun","Jul","Aug","Sep","Oct","Nov","Dec"}, 0), 1), 1)) -> 0 | M9: =SUMIFS(Data!$I:$I, Data!$F:$F, $B65, Data!$C:$C, ">=" & DATE(2025, MATCH(N$56, {"Jan","Feb","Mar","Apr","May","Jun","Jul","Aug","Sep","Oct","Nov","Dec"}, 0), 1), Data!N:N, "<" & EDATE(DATE(2025, MATCH(N$56, {"Jan","Feb","Mar","Apr","May","Jun","Jul","Aug","Sep","Oct","Nov","Dec"}, 0), 1), 1)) -> 0
A10: Deporte | B10: =SUMIFS(Data!I:I, Data!F:F, $B66, Data!C:C, ">=" & DATE(2025, MATCH(C$56, {"Jan","Feb","Mar","Apr","May","Jun","Jul","Aug","Sep","Oct","Nov","Dec"}, 0), 1), Data!C:C, "<" & EDATE(DATE(2025, MATCH(C$56, {"Jan","Feb","Mar","Apr","May","Jun","Jul","Aug","Sep","Oct","Nov","Dec"}, 0), 1), 1)) -> 0 | C10: =SUMIFS(Data!$I:$I, Data!$F:$F, $B66, Data!$C:$C, ">=" & DATE(2025, MATCH(D$56, {"Jan","Feb","Mar","Apr","May","Jun","Jul","Aug","Sep","Oct","Nov","Dec"}, 0), 1), Data!D:D, "<" & EDATE(DATE(2025, MATCH(D$56, {"Jan","Feb","Mar","Apr","May","Jun","Jul","Aug","Sep","Oct","Nov","Dec"}, 0), 1), 1)) -> 0 | D10: =SUMIFS(Data!$I:$I, Data!$F:$F, $B66, Data!$C:$C, ">=" & DATE(2025, MATCH(E$56, {"Jan","Feb","Mar","Apr","May","Jun","Jul","Aug","Sep","Oct","Nov","Dec"}, 0), 1), Data!E:E, "<" & EDATE(DATE(2025, MATCH(E$56, {"Jan","Feb","Mar","Apr","May","Jun","Jul","Aug","Sep","Oct","Nov","Dec"}, 0), 1), 1)) -> 0 | E10: =SUMIFS(Data!$I:$I, Data!$F:$F, $B66, Data!$C:$C, ">=" & DATE(2025, MATCH(F$56, {"Jan","Feb","Mar","Apr","May","Jun","Jul","Aug","Sep","Oct","Nov","Dec"}, 0), 1), Data!F:F, "<" & EDATE(DATE(2025, MATCH(F$56, {"Jan","Feb","Mar","Apr","May","Jun","Jul","Aug","Sep","Oct","Nov","Dec"}, 0), 1), 1)) -> 0 | F10: =SUMIFS(Data!$I:$I, Data!$F:$F, $B66, Data!$C:$C, ">=" & DATE(2025, MATCH(G$56, {"Jan","Feb","Mar","Apr","May","Jun","Jul","Aug","Sep","Oct","Nov","Dec"}, 0), 1), Data!G:G, "<" & EDATE(DATE(2025, MATCH(G$56, {"Jan","Feb","Mar","Apr","May","Jun","Jul","Aug","Sep","Oct","Nov","Dec"}, 0), 1), 1)) -> 0 | G10: =SUMIFS(Data!$I:$I, Data!$F:$F, $B66, Data!$C:$C, ">=" & DATE(2025, MATCH(H$56, {"Jan","Feb","Mar","Apr","May","Jun","Jul","Aug","Sep","Oct","Nov","Dec"}, 0), 1), Data!H:H, "<" & EDATE(DATE(2025, MATCH(H$56, {"Jan","Feb","Mar","Apr","May","Jun","Jul","Aug","Sep","Oct","Nov","Dec"}, 0), 1), 1)) -> 0 | H10: =SUMIFS(Data!$I:$I, Data!$F:$F, $B66, Data!$C:$C, ">=" & DATE(2025, MATCH(I$56, {"Jan","Feb","Mar","Apr","May","Jun","Jul","Aug","Sep","Oct","Nov","Dec"}, 0), 1), Data!I:I, "<" & EDATE(DATE(2025, MATCH(I$56, {"Jan","Feb","Mar","Apr","May","Jun","Jul","Aug","Sep","Oct","Nov","Dec"}, 0), 1), 1)) -> -42.86 | I10: =SUMIFS(Data!$I:$I, Data!$F:$F, $B66, Data!$C:$C, ">=" & DATE(2025, MATCH(J$56, {"Jan","Feb","Mar","Apr","May","Jun","Jul","Aug","Sep","Oct","Nov","Dec"}, 0), 1), Data!J:J, "<" & EDATE(DATE(2025, MATCH(J$56, {"Jan","Feb","Mar","Apr","May","Jun","Jul","Aug","Sep","Oct","Nov","Dec"}, 0), 1), 1)) -> 0 | J10: =SUMIFS(Data!$I:$I, Data!$F:$F, $B66, Data!$C:$C, ">=" & DATE(2025, MATCH(K$56, {"Jan","Feb","Mar","Apr","May","Jun","Jul","Aug","Sep","Oct","Nov","Dec"}, 0), 1), Data!K:K, "<" & EDATE(DATE(2025, MATCH(K$56, {"Jan","Feb","Mar","Apr","May","Jun","Jul","Aug","Sep","Oct","Nov","Dec"}, 0), 1), 1)) -> -42.86 | K10: =SUMIFS(Data!$I:$I, Data!$F:$F, $B66, Data!$C:$C, ">=" & DATE(2025, MATCH(L$56, {"Jan","Feb","Mar","Apr","May","Jun","Jul","Aug","Sep","Oct","Nov","Dec"}, 0), 1), Data!L:L, "<" & EDATE(DATE(2025, MATCH(L$56, {"Jan","Feb","Mar","Apr","May","Jun","Jul","Aug","Sep","Oct","Nov","Dec"}, 0), 1), 1)) -> 0 | L10: =SUMIFS(Data!$I:$I, Data!$F:$F, $B66, Data!$C:$C, ">=" & DATE(2025, MATCH(M$56, {"Jan","Feb","Mar","Apr","May","Jun","Jul","Aug","Sep","Oct","Nov","Dec"}, 0), 1), Data!M:M, "<" & EDATE(DATE(2025, MATCH(M$56, {"Jan","Feb","Mar","Apr","May","Jun","Jul","Aug","Sep","Oct","Nov","Dec"}, 0), 1), 1)) -> 0 | M10: =SUMIFS(Data!$I:$I, Data!$F:$F, $B66, Data!$C:$C, ">=" & DATE(2025, MATCH(N$56, {"Jan","Feb","Mar","Apr","May","Jun","Jul","Aug","Sep","Oct","Nov","Dec"}, 0), 1), Data!N:N, "<" & EDATE(DATE(2025, MATCH(N$56, {"Jan","Feb","Mar","Apr","May","Jun","Jul","Aug","Sep","Oct","Nov","Dec"}, 0), 1), 1)) -> 0
A11: Deudas | B11: =SUMIFS(Data!I:I, Data!F:F, $B67, Data!C:C, ">=" & DATE(2025, MATCH(C$56, {"Jan","Feb","Mar","Apr","May","Jun","Jul","Aug","Sep","Oct","Nov","Dec"}, 0), 1), Data!C:C, "<" & EDATE(DATE(2025, MATCH(C$56, {"Jan","Feb","Mar","Apr","May","Jun","Jul","Aug","Sep","Oct","Nov","Dec"}, 0), 1), 1)) -> -68.32 | C11: =SUMIFS(Data!$I:$I, Data!$F:$F, $B67, Data!$C:$C, ">=" & DATE(2025, MATCH(D$56, {"Jan","Feb","Mar","Apr","May","Jun","Jul","Aug","Sep","Oct","Nov","Dec"}, 0), 1), Data!D:D, "<" & EDATE(DATE(2025, MATCH(D$56, {"Jan","Feb","Mar","Apr","May","Jun","Jul","Aug","Sep","Oct","Nov","Dec"}, 0), 1), 1)) -> -136.64 | D11: =SUMIFS(Data!$I:$I, Data!$F:$F, $B67, Data!$C:$C, ">=" & DATE(2025, MATCH(E$56, {"Jan","Feb","Mar","Apr","May","Jun","Jul","Aug","Sep","Oct","Nov","Dec"}, 0), 1), Data!E:E, "<" & EDATE(DATE(2025, MATCH(E$56, {"Jan","Feb","Mar","Apr","May","Jun","Jul","Aug","Sep","Oct","Nov","Dec"}, 0), 1), 1)) -> 0 | E11: =SUMIFS(Data!$I:$I, Data!$F:$F, $B67, Data!$C:$C, ">=" & DATE(2025, MATCH(F$56, {"Jan","Feb","Mar","Apr","May","Jun","Jul","Aug","Sep","Oct","Nov","Dec"}, 0), 1), Data!F:F, "<" & EDATE(DATE(2025, MATCH(F$56, {"Jan","Feb","Mar","Apr","May","Jun","Jul","Aug","Sep","Oct","Nov","Dec"}, 0), 1), 1)) -> 0 | F11: =SUMIFS(Data!$I:$I, Data!$F:$F, $B67, Data!$C:$C, ">=" & DATE(2025, MATCH(G$56, {"Jan","Feb","Mar","Apr","May","Jun","Jul","Aug","Sep","Oct","Nov","Dec"}, 0), 1), Data!G:G, "<" & EDATE(DATE(2025, MATCH(G$56, {"Jan","Feb","Mar","Apr","May","Jun","Jul","Aug","Sep","Oct","Nov","Dec"}, 0), 1), 1)) -> 0 | G11: =SUMIFS(Data!$I:$I, Data!$F:$F, $B67, Data!$C:$C, ">=" & DATE(2025, MATCH(H$56, {"Jan","Feb","Mar","Apr","May","Jun","Jul","Aug","Sep","Oct","Nov","Dec"}, 0), 1), Data!H:H, "<" & EDATE(DATE(2025, MATCH(H$56, {"Jan","Feb","Mar","Apr","May","Jun","Jul","Aug","Sep","Oct","Nov","Dec"}, 0), 1), 1)) -> 0 | H11: =SUMIFS(Data!$I:$I, Data!$F:$F, $B67, Data!$C:$C, ">=" & DATE(2025, MATCH(I$56, {"Jan","Feb","Mar","Apr","May","Jun","Jul","Aug","Sep","Oct","Nov","Dec"}, 0), 1), Data!I:I, "<" & EDATE(DATE(2025, MATCH(I$56, {"Jan","Feb","Mar","Apr","May","Jun","Jul","Aug","Sep","Oct","Nov","Dec"}, 0), 1), 1)) -> -36 | I11: =SUMIFS(Data!$I:$I, Data!$F:$F, $B67, Data!$C:$C, ">=" & DATE(2025, MATCH(J$56, {"Jan","Feb","Mar","Apr","May","Jun","Jul","Aug","Sep","Oct","Nov","Dec"}, 0), 1), Data!J:J, "<" & EDATE(DATE(2025, MATCH(J$56, {"Jan","Feb","Mar","Apr","May","Jun","Jul","Aug","Sep","Oct","Nov","Dec"}, 0), 1), 1)) -> 0 | J11: =SUMIFS(Data!$I:$I, Data!$F:$F, $B67, Data!$C:$C, ">=" & DATE(2025, MATCH(K$56, {"Jan","Feb","Mar","Apr","May","Jun","Jul","Aug","Sep","Oct","Nov","Dec"}, 0), 1), Data!K:K, "<" & EDATE(DATE(2025, MATCH(K$56, {"Jan","Feb","Mar","Apr","May","Jun","Jul","Aug","Sep","Oct","Nov","Dec"}, 0), 1), 1)) -> -36 | K11: =SUMIFS(Data!$I:$I, Data!$F:$F, $B67, Data!$C:$C, ">=" & DATE(2025, MATCH(L$56, {"Jan","Feb","Mar","Apr","May","Jun","Jul","Aug","Sep","Oct","Nov","Dec"}, 0), 1), Data!L:L, "<" & EDATE(DATE(2025, MATCH(L$56, {"Jan","Feb","Mar","Apr","May","Jun","Jul","Aug","Sep","Oct","Nov","Dec"}, 0), 1), 1)) -> 0 | L11: =SUMIFS(Data!$I:$I, Data!$F:$F, $B67, Data!$C:$C, ">=" & DATE(2025, MATCH(M$56, {"Jan","Feb","Mar","Apr","May","Jun","Jul","Aug","Sep","Oct","Nov","Dec"}, 0), 1), Data!M:M, "<" & EDATE(DATE(2025, MATCH(M$56, {"Jan","Feb","Mar","Apr","May","Jun","Jul","Aug","Sep","Oct","Nov","Dec"}, 0), 1), 1)) -> 0 | M11: =SUMIFS(Data!$I:$I, Data!$F:$F, $B67, Data!$C:$C, ">=" & DATE(2025, MATCH(N$56, {"Jan","Feb","Mar","Apr","May","Jun","Jul","Aug","Sep","Oct","Nov","Dec"}, 0), 1), Data!N:N, "<" & EDATE(DATE(2025, MATCH(N$56, {"Jan","Feb","Mar","Apr","May","Jun","Jul","Aug","Sep","Oct","Nov","Dec"}, 0), 1), 1)) -> 0
A12: Donación | B12: =SUMIFS(Data!I:I, Data!F:F, $B68, Data!C:C, ">=" & DATE(2025, MATCH(C$56, {"Jan","Feb","Mar","Apr","May","Jun","Jul","Aug","Sep","Oct","Nov","Dec"}, 0), 1), Data!C:C, "<" & EDATE(DATE(2025, MATCH(C$56, {"Jan","Feb","Mar","Apr","May","Jun","Jul","Aug","Sep","Oct","Nov","Dec"}, 0), 1), 1)) -> 0 | C12: =SUMIFS(Data!$I:$I, Data!$F:$F, $B68, Data!$C:$C, ">=" & DATE(2025, MATCH(D$56, {"Jan","Feb","Mar","Apr","May","Jun","Jul","Aug","Sep","Oct","Nov","Dec"}, 0), 1), Data!D:D, "<" & EDATE(DATE(2025, MATCH(D$56, {"Jan","Feb","Mar","Apr","May","Jun","Jul","Aug","Sep","Oct","Nov","Dec"}, 0), 1), 1)) -> 0 | D12: =SUMIFS(Data!$I:$I, Data!$F:$F, $B68, Data!$C:$C, ">=" & DATE(2025, MATCH(E$56, {"Jan","Feb","Mar","Apr","May","Jun","Jul","Aug","Sep","Oct","Nov","Dec"}, 0), 1), Data!E:E, "<" & EDATE(DATE(2025, MATCH(E$56, {"Jan","Feb","Mar","Apr","May","Jun","Jul","Aug","Sep","Oct","Nov","Dec"}, 0), 1), 1)) -> 0 | E12: =SUMIFS(Data!$I:$I, Data!$F:$F, $B68, Data!$C:$C, ">=" & DATE(2025, MATCH(F$56, {"Jan","Feb","Mar","Apr","May","Jun","Jul","Aug","Sep","Oct","Nov","Dec"}, 0), 1), Data!F:F, "<" & EDATE(DATE(2025, MATCH(F$56, {"Jan","Feb","Mar","Apr","May","Jun","Jul","Aug","Sep","Oct","Nov","Dec"}, 0), 1), 1)) -> 0 | F12: =SUMIFS(Data!$I:$I, Data!$F:$F, $B68, Data!$C:$C, ">=" & DATE(2025, MATCH(G$56, {"Jan","Feb","Mar","Apr","May","Jun","Jul","Aug","Sep","Oct","Nov","Dec"}, 0), 1), Data!G:G, "<" & EDATE(DATE(2025, MATCH(G$56, {"Jan","Feb","Mar","Apr","May","Jun","Jul","Aug","Sep","Oct","Nov","Dec"}, 0), 1), 1)) -> 0 | G12: =SUMIFS(Data!$I:$I, Data!$F:$F, $B68, Data!$C:$C, ">=" & DATE(2025, MATCH(H$56, {"Jan","Feb","Mar","Apr","May","Jun","Jul","Aug","Sep","Oct","Nov","Dec"}, 0), 1), Data!H:H, "<" & EDATE(DATE(2025, MATCH(H$56, {"Jan","Feb","Mar","Apr","May","Jun","Jul","Aug","Sep","Oct","Nov","Dec"}, 0), 1), 1)) -> 0 | H12: =SUMIFS(Data!$I:$I, Data!$F:$F, $B68, Data!$C:$C, ">=" & DATE(2025, MATCH(I$56, {"Jan","Feb","Mar","Apr","May","Jun","Jul","Aug","Sep","Oct","Nov","Dec"}, 0), 1), Data!I:I, "<" & EDATE(DATE(2025, MATCH(I$56, {"Jan","Feb","Mar","Apr","May","Jun","Jul","Aug","Sep","Oct","Nov","Dec"}, 0), 1), 1)) -> 0 | I12: =SUMIFS(Data!$I:$I, Data!$F:$F, $B68, Data!$C:$C, ">=" & DATE(2025, MATCH(J$56, {"Jan","Feb","Mar","Apr","May","Jun","Jul","Aug","Sep","Oct","Nov","Dec"}, 0), 1), Data!J:J, "<" & EDATE(DATE(2025, MATCH(J$56, {"Jan","Feb","Mar","Apr","May","Jun","Jul","Aug","Sep","Oct","Nov","Dec"}, 0), 1), 1)) -> 0 | J12: =SUMIFS(Data!$I:$I, Data!$F:$F, $B68, Data!$C:$C, ">=" & DATE(2025, MATCH(K$56, {"Jan","Feb","Mar","Apr","May","Jun","Jul","Aug","Sep","Oct","Nov","Dec"}, 0), 1), Data!K:K, "<" & EDATE(DATE(2025, MATCH(K$56, {"Jan","Feb","Mar","Apr","May","Jun","Jul","Aug","Sep","Oct","Nov","Dec"}, 0), 1), 1)) -> 0 | K12: =SUMIFS(Data!$I:$I, Data!$F:$F, $B68, Data!$C:$C, ">=" & DATE(2025, MATCH(L$56, {"Jan","Feb","Mar","Apr","May","Jun","Jul","Aug","Sep","Oct","Nov","Dec"}, 0), 1), Data!L:L, "<" & EDATE(DATE(2025, MATCH(L$56, {"Jan","Feb","Mar","Apr","May","Jun","Jul","Aug","Sep","Oct","Nov","Dec"}, 0), 1), 1)) -> 0 | L12: =SUMIFS(Data!$I:$I, Data!$F:$F, $B68, Data!$C:$C, ">=" & DATE(2025, MATCH(M$56, {"Jan","Feb","Mar","Apr","May","Jun","Jul","Aug","Sep","Oct","Nov","Dec"}, 0), 1), Data!M:M, "<" & EDATE(DATE(2025, MATCH(M$56, {"Jan","Feb","Mar","Apr","May","Jun","Jul","Aug","Sep","Oct","Nov","Dec"}, 0), 1), 1)) -> 0 | M12: =SUMIFS(Data!$I:$I, Data!$F:$F, $B68, Data!$C:$C, ">=" & DATE(2025, MATCH(N$56, {"Jan","Feb","Mar","Apr","May","Jun","Jul","Aug","Sep","Oct","Nov","Dec"}, 0), 1), Data!N:N, "<" & EDATE(DATE(2025, MATCH(N$56, {"Jan","Feb","Mar","Apr","May","Jun","Jul","Aug","Sep","Oct","Nov","Dec"}, 0), 1), 1)) -> 0
A13: E'Kabel | B13: =SUMIFS(Data!I:I, Data!F:F, $B69, Data!C:C, ">=" & DATE(2025, MATCH(C$56, {"Jan","Feb","Mar","Apr","May","Jun","Jul","Aug","Sep","Oct","Nov","Dec"}, 0), 1), Data!C:C, "<" & EDATE(DATE(2025, MATCH(C$56, {"Jan","Feb","Mar","Apr","May","Jun","Jul","Aug","Sep","Oct","Nov","Dec"}, 0), 1), 1)) -> 0 | C13: =SUMIFS(Data!$I:$I, Data!$F:$F, $B69, Data!$C:$C, ">=" & DATE(2025, MATCH(D$56, {"Jan","Feb","Mar","Apr","May","Jun","Jul","Aug","Sep","Oct","Nov","Dec"}, 0), 1), Data!D:D, "<" & EDATE(DATE(2025, MATCH(D$56, {"Jan","Feb","Mar","Apr","May","Jun","Jul","Aug","Sep","Oct","Nov","Dec"}, 0), 1), 1)) -> 0 | D13: =SUMIFS(Data!$I:$I, Data!$F:$F, $B69, Data!$C:$C, ">=" & DATE(2025, MATCH(E$56, {"Jan","Feb","Mar","Apr","May","Jun","Jul","Aug","Sep","Oct","Nov","Dec"}, 0), 1), Data!E:E, "<" & EDATE(DATE(2025, MATCH(E$56, {"Jan","Feb","Mar","Apr","May","Jun","Jul","Aug","Sep","Oct","Nov","Dec"}, 0), 1), 1)) -> 0 | E13: =SUMIFS(Data!$I:$I, Data!$F:$F, $B69, Data!$C:$C, ">=" & DATE(2025, MATCH(F$56, {"Jan","Feb","Mar","Apr","May","Jun","Jul","Aug","Sep","Oct","Nov","Dec"}, 0), 1), Data!F:F, "<" & EDATE(DATE(2025, MATCH(F$56, {"Jan","Feb","Mar","Apr","May","Jun","Jul","Aug","Sep","Oct","Nov","Dec"}, 0), 1), 1)) -> 0 | F13: =SUMIFS(Data!$I:$I, Data!$F:$F, $B69, Data!$C:$C, ">=" & DATE(2025, MATCH(G$56, {"Jan","Feb","Mar","Apr","May","Jun","Jul","Aug","Sep","Oct","Nov","Dec"}, 0), 1), Data!G:G, "<" & EDATE(DATE(2025, MATCH(G$56, {"Jan","Feb","Mar","Apr","May","Jun","Jul","Aug","Sep","Oct","Nov","Dec"}, 0), 1), 1)) -> 0 | G13: =SUMIFS(Data!$I:$I, Data!$F:$F, $B69, Data!$C:$C, ">=" & DATE(2025, MATCH(H$56, {"Jan","Feb","Mar","Apr","May","Jun","Jul","Aug","Sep","Oct","Nov","Dec"}, 0), 1), Data!H:H, "<" & EDATE(DATE(2025, MATCH(H$56, {"Jan","Feb","Mar","Apr","May","Jun","Jul","Aug","Sep","Oct","Nov","Dec"}, 0), 1), 1)) -> 0 | H13: =SUMIFS(Data!$I:$I, Data!$F:$F, $B69, Data!$C:$C, ">=" & DATE(2025, MATCH(I$56, {"Jan","Feb","Mar","Apr","May","Jun","Jul","Aug","Sep","Oct","Nov","Dec"}, 0), 1), Data!I:I, "<" & EDATE(DATE(2025, MATCH(I$56, {"Jan","Feb","Mar","Apr","May","Jun","Jul","Aug","Sep","Oct","Nov","Dec"}, 0), 1), 1)) -> 0 | I13: =SUMIFS(Data!$I:$I, Data!$F:$F, $B69, Data!$C:$C, ">=" & DATE(2025, MATCH(J$56, {"Jan","Feb","Mar","Apr","May","Jun","Jul","Aug","Sep","Oct","Nov","Dec"}, 0), 1), Data!J:J, "<" & EDATE(DATE(2025, MATCH(J$56, {"Jan","Feb","Mar","Apr","May","Jun","Jul","Aug","Sep","Oct","Nov","Dec"}, 0), 1), 1)) -> 0 | J13: =SUMIFS(Data!$I:$I, Data!$F:$F, $B69, Data!$C:$C, ">=" & DATE(2025, MATCH(K$56, {"Jan","Feb","Mar","Apr","May","Jun","Jul","Aug","Sep","Oct","Nov","Dec"}, 0), 1), Data!K:K, "<" & EDATE(DATE(2025, MATCH(K$56, {"Jan","Feb","Mar","Apr","May","Jun","Jul","Aug","Sep","Oct","Nov","Dec"}, 0), 1), 1)) -> 0 | K13: =SUMIFS(Data!$I:$I, Data!$F:$F, $B69, Data!$C:$C, ">=" & DATE(2025, MATCH(L$56, {"Jan","Feb","Mar","Apr","May","Jun","Jul","Aug","Sep","Oct","Nov","Dec"}, 0), 1), Data!L:L, "<" & EDATE(DATE(2025, MATCH(L$56, {"Jan","Feb","Mar","Apr","May","Jun","Jul","Aug","Sep","Oct","Nov","Dec"}, 0), 1), 1)) -> 0 | L13: =SUMIFS(Data!$I:$I, Data!$F:$F, $B69, Data!$C:$C, ">=" & DATE(2025, MATCH(M$56, {"Jan","Feb","Mar","Apr","May","Jun","Jul","Aug","Sep","Oct","Nov","Dec"}, 0), 1), Data!M:M, "<" & EDATE(DATE(2025, MATCH(M$56, {"Jan","Feb","Mar","Apr","May","Jun","Jul","Aug","Sep","Oct","Nov","Dec"}, 0), 1), 1)) -> 0 | M13: =SUMIFS(Data!$I:$I, Data!$F:$F, $B69, Data!$C:$C, ">=" & DATE(2025, MATCH(N$56, {"Jan","Feb","Mar","Apr","May","Jun","Jul","Aug","Sep","Oct","Nov","Dec"}, 0), 1), Data!N:N, "<" & EDATE(DATE(2025, MATCH(N$56, {"Jan","Feb","Mar","Apr","May","Jun","Jul","Aug","Sep","Oct","Nov","Dec"}, 0), 1), 1)) -> 0
A14: Entretenimiento | B14: =SUMIFS(Data!I:I, Data!F:F, $B70, Data!C:C, ">=" & DATE(2025, MATCH(C$56, {"Jan","Feb","Mar","Apr","May","Jun","Jul","Aug","Sep","Oct","Nov","Dec"}, 0), 1), Data!C:C, "<" & EDATE(DATE(2025, MATCH(C$56, {"Jan","Feb","Mar","Apr","May","Jun","Jul","Aug","Sep","Oct","Nov","Dec"}, 0), 1), 1)) -> -818.57 | C14: =SUMIFS(Data!$I:$I, Data!$F:$F, $B70, Data!$C:$C, ">=" & DATE(2025, MATCH(D$56, {"Jan","Feb","Mar","Apr","May","Jun","Jul","Aug","Sep","Oct","Nov","Dec"}, 0), 1), Data!D:D, "<" & EDATE(DATE(2025, MATCH(D$56, {"Jan","Feb","Mar","Apr","May","Jun","Jul","Aug","Sep","Oct","Nov","Dec"}, 0), 1), 1)) -> -792.61 | D14: =SUMIFS(Data!$I:$I, Data!$F:$F, $B70, Data!$C:$C, ">=" & DATE(2025, MATCH(E$56, {"Jan","Feb","Mar","Apr","May","Jun","Jul","Aug","Sep","Oct","Nov","Dec"}, 0), 1), Data!E:E, "<" & EDATE(DATE(2025, MATCH(E$56, {"Jan","Feb","Mar","Apr","May","Jun","Jul","Aug","Sep","Oct","Nov","Dec"}, 0), 1), 1)) -> -787.25 | E14: =SUMIFS(Data!$I:$I, Data!$F:$F, $B70, Data!$C:$C, ">=" & DATE(2025, MATCH(F$56, {"Jan","Feb","Mar","Apr","May","Jun","Jul","Aug","Sep","Oct","Nov","Dec"}, 0), 1), Data!F:F, "<" & EDATE(DATE(2025, MATCH(F$56, {"Jan","Feb","Mar","Apr","May","Jun","Jul","Aug","Sep","Oct","Nov","Dec"}, 0), 1), 1)) -> 0 | F14: =SUMIFS(Data!$I:$I, Data!$F:$F, $B70, Data!$C:$C, ">=" & DATE(2025, MATCH(G$56, {"Jan","Feb","Mar","Apr","May","Jun","Jul","Aug","Sep","Oct","Nov","Dec"}, 0), 1), Data!G:G, "<" & EDATE(DATE(2025, MATCH(G$56, {"Jan","Feb","Mar","Apr","May","Jun","Jul","Aug","Sep","Oct","Nov","Dec"}, 0), 1), 1)) -> 0 | G14: =SUMIFS(Data!$I:$I, Data!$F:$F, $B70, Data!$C:$C, ">=" & DATE(2025, MATCH(H$56, {"Jan","Feb","Mar","Apr","May","Jun","Jul","Aug","Sep","Oct","Nov","Dec"}, 0), 1), Data!H:H, "<" & EDATE(DATE(2025, MATCH(H$56, {"Jan","Feb","Mar","Apr","May","Jun","Jul","Aug","Sep","Oct","Nov","Dec"}, 0), 1), 1)) -> 0 | H14: =SUMIFS(Data!$I:$I, Data!$F:$F, $B70, Data!$C:$C, ">=" & DATE(2025, MATCH(I$56, {"Jan","Feb","Mar","Apr","May","Jun","Jul","Aug","Sep","Oct","Nov","Dec"}, 0), 1), Data!I:I, "<" & EDATE(DATE(2025, MATCH(I$56, {"Jan","Feb","Mar","Apr","May","Jun","Jul","Aug","Sep","Oct","Nov","Dec"}, 0), 1), 1)) -> -8052.66 | I14: =SUMIFS(Data!$I:$I, Data!$F:$F, $B70, Data!$C:$C, ">=" & DATE(2025, MATCH(J$56, {"Jan","Feb","Mar","Apr","May","Jun","Jul","Aug","Sep","Oct","Nov","Dec"}, 0), 1), Data!J:J, "<" & EDATE(DATE(2025, MATCH(J$56, {"Jan","Feb","Mar","Apr","May","Jun","Jul","Aug","Sep","Oct","Nov","Dec"}, 0), 1), 1)) -> 0 | J14: =SUMIFS(Data!$I:$I, Data!$F:$F, $B70, Data!$C:$C, ">=" & DATE(2025, MATCH(K$56, {"Jan","Feb","Mar","Apr","May","Jun","Jul","Aug","Sep","Oct","Nov","Dec"}, 0), 1), Data!K:K, "<" & EDATE(DATE(2025, MATCH(K$56, {"Jan","Feb","Mar","Apr","May","Jun","Jul","Aug","Sep","Oct","Nov","Dec"}, 0), 1), 1)) -> -5795.58 | K14: =SUMIFS(Data!$I:$I, Data!$F:$F, $B70, Data!$C:$C, ">=" & DATE(2025, MATCH(L$56, {"Jan","Feb","Mar","Apr","May","Jun","Jul","Aug","Sep","Oct","Nov","Dec"}, 0), 1), Data!L:L, "<" & EDATE(DATE(2025, MATCH(L$56, {"Jan","Feb","Mar","Apr","May","Jun","Jul","Aug","Sep","Oct","Nov","Dec"}, 0), 1), 1)) -> 0 | L14: =SUMIFS(Data!$I:$I, Data!$F:$F, $B70, Data!$C:$C, ">=" & DATE(2025, MATCH(M$56, {"Jan","Feb","Mar","Apr","May","Jun","Jul","Aug","Sep","Oct","Nov","Dec"}, 0), 1), Data!M:M, "<" & EDATE(DATE(2025, MATCH(M$56, {"Jan","Feb","Mar","Apr","May","Jun","Jul","Aug","Sep","Oct","Nov","Dec"}, 0), 1), 1)) -> 0 | M14: =SUMIFS(Data!$I:$I, Data!$F:$F, $B70, Data!$C:$C, ">=" & DATE(2025, MATCH(N$56, {"Jan","Feb","Mar","Apr","May","Jun","Jul","Aug","Sep","Oct","Nov","Dec"}, 0), 1), Data!N:N, "<" & EDATE(DATE(2025, MATCH(N$56, {"Jan","Feb","Mar","Apr","May","Jun","Jul","Aug","Sep","Oct","Nov","Dec"}, 0), 1), 1)) -> 0
A15: Establecernos | B15: =SUMIFS(Data!I:I, Data!F:F, $B71, Data!C:C, ">=" & DATE(2025, MATCH(C$56, {"Jan","Feb","Mar","Apr","May","Jun","Jul","Aug","Sep","Oct","Nov","Dec"}, 0), 1), Data!C:C, "<" & EDATE(DATE(2025, MATCH(C$56, {"Jan","Feb","Mar","Apr","May","Jun","Jul","Aug","Sep","Oct","Nov","Dec"}, 0), 1), 1)) -> 0 | C15: =SUMIFS(Data!$I:$I, Data!$F:$F, $B71, Data!$C:$C, ">=" & DATE(2025, MATCH(D$56, {"Jan","Feb","Mar","Apr","May","Jun","Jul","Aug","Sep","Oct","Nov","Dec"}, 0), 1), Data!D:D, "<" & EDATE(DATE(2025, MATCH(D$56, {"Jan","Feb","Mar","Apr","May","Jun","Jul","Aug","Sep","Oct","Nov","Dec"}, 0), 1), 1)) -> 0 | D15: =SUMIFS(Data!$I:$I, Data!$F:$F, $B71, Data!$C:$C, ">=" & DATE(2025, MATCH(E$56, {"Jan","Feb","Mar","Apr","May","Jun","Jul","Aug","Sep","Oct","Nov","Dec"}, 0), 1), Data!E:E, "<" & EDATE(DATE(2025, MATCH(E$56, {"Jan","Feb","Mar","Apr","May","Jun","Jul","Aug","Sep","Oct","Nov","Dec"}, 0), 1), 1)) -> 0 | E15: =SUMIFS(Data!$I:$I, Data!$F:$F, $B71, Data!$C:$C, ">=" & DATE(2025, MATCH(F$56, {"Jan","Feb","Mar","Apr","May","Jun","Jul","Aug","Sep","Oct","Nov","Dec"}, 0), 1), Data!F:F, "<" & EDATE(DATE(2025, MATCH(F$56, {"Jan","Feb","Mar","Apr","May","Jun","Jul","Aug","Sep","Oct","Nov","Dec"}, 0), 1), 1)) -> 0 | F15: =SUMIFS(Data!$I:$I, Data!$F:$F, $B71, Data!$C:$C, ">=" & DATE(2025, MATCH(G$56, {"Jan","Feb","Mar","Apr","May","Jun","Jul","Aug","Sep","Oct","Nov","Dec"}, 0), 1), Data!G:G, "<" & EDATE(DATE(2025, MATCH(G$56, {"Jan","Feb","Mar","Apr","May","Jun","Jul","Aug","Sep","Oct","Nov","Dec"}, 0), 1), 1)) -> 0 | G15: =SUMIFS(Data!$I:$I, Data!$F:$F, $B71, Data!$C:$C, ">=" & DATE(2025, MATCH(H$56, {"Jan","Feb","Mar","Apr","May","Jun","Jul","Aug","Sep","Oct","Nov","Dec"}, 0), 1), Data!H:H, "<" & EDATE(DATE(2025, MATCH(H$56, {"Jan","Feb","Mar","Apr","May","Jun","Jul","Aug","Sep","Oct","Nov","Dec"}, 0), 1), 1)) -> 0 | H15: =SUMIFS(Data!$I:$I, Data!$F:$F, $B71, Data!$C:$C, ">=" & DATE(2025, MATCH(I$56, {"Jan","Feb","Mar","Apr","May","Jun","Jul","Aug","Sep","Oct","Nov","Dec"}, 0), 1), Data!I:I, "<" & EDATE(DATE(2025, MATCH(I$56, {"Jan","Feb","Mar","Apr","May","Jun","Jul","Aug","Sep","Oct","Nov","Dec"}, 0), 1), 1)) -> 0 | I15: =SUMIFS(Data!$I:$I, Data!$F:$F, $B71, Data!$C:$C, ">=" & DATE(2025, MATCH(J$56, {"Jan","Feb","Mar","Apr","May","Jun","Jul","Aug","Sep","Oct","Nov","Dec"}, 0), 1), Data!J:J, "<" & EDATE(DATE(2025, MATCH(J$56, {"Jan","Feb","Mar","Apr","May","Jun","Jul","Aug","Sep","Oct","Nov","Dec"}, 0), 1), 1)) -> 0 | J15: =SUMIFS(Data!$I:$I, Data!$F:$F, $B71, Data!$C:$C, ">=" & DATE(2025, MATCH(K$56, {"Jan","Feb","Mar","Apr","May","Jun","Jul","Aug","Sep","Oct","Nov","Dec"}, 0), 1), Data!K:K, "<" & EDATE(DATE(2025, MATCH(K$56, {"Jan","Feb","Mar","Apr","May","Jun","Jul","Aug","Sep","Oct","Nov","Dec"}, 0), 1), 1)) -> 0 | K15: =SUMIFS(Data!$I:$I, Data!$F:$F, $B71, Data!$C:$C, ">=" & DATE(2025, MATCH(L$56, {"Jan","Feb","Mar","Apr","May","Jun","Jul","Aug","Sep","Oct","Nov","Dec"}, 0), 1), Data!L:L, "<" & EDATE(DATE(2025, MATCH(L$56, {"Jan","Feb","Mar","Apr","May","Jun","Jul","Aug","Sep","Oct","Nov","Dec"}, 0), 1), 1)) -> 0 | L15: =SUMIFS(Data!$I:$I, Data!$F:$F, $B71, Data!$C:$C, ">=" & DATE(2025, MATCH(M$56, {"Jan","Feb","Mar","Apr","May","Jun","Jul","Aug","Sep","Oct","Nov","Dec"}, 0), 1), Data!M:M, "<" & EDATE(DATE(2025, MATCH(M$56, {"Jan","Feb","Mar","Apr","May","Jun","Jul","Aug","Sep","Oct","Nov","Dec"}, 0), 1), 1)) -> 0 | M15: =SUMIFS(Data!$I:$I, Data!$F:$F, $B71, Data!$C:$C, ">=" & DATE(2025, MATCH(N$56, {"Jan","Feb","Mar","Apr","May","Jun","Jul","Aug","Sep","Oct","Nov","Dec"}, 0), 1), Data!N:N, "<" & EDATE(DATE(2025, MATCH(N$56, {"Jan","Feb","Mar","Apr","May","Jun","Jul","Aug","Sep","Oct","Nov","Dec"}, 0), 1), 1)) -> 0
A16: Financiero | B16: =SUMIFS(Data!I:I, Data!F:F, $B72, Data!C:C, ">=" & DATE(2025, MATCH(C$56, {"Jan","Feb","Mar","Apr","May","Jun","Jul","Aug","Sep","Oct","Nov","Dec"}, 0), 1), Data!C:C, "<" & EDATE(DATE(2025, MATCH(C$56, {"Jan","Feb","Mar","Apr","May","Jun","Jul","Aug","Sep","Oct","Nov","Dec"}, 0), 1), 1)) -> -1.32 | C16: =SUMIFS(Data!$I:$I, Data!$F:$F, $B72, Data!$C:$C, ">=" & DATE(2025, MATCH(D$56, {"Jan","Feb","Mar","Apr","May","Jun","Jul","Aug","Sep","Oct","Nov","Dec"}, 0), 1), Data!D:D, "<" & EDATE(DATE(2025, MATCH(D$56, {"Jan","Feb","Mar","Apr","May","Jun","Jul","Aug","Sep","Oct","Nov","Dec"}, 0), 1), 1)) -> -231.07 | D16: =SUMIFS(Data!$I:$I, Data!$F:$F, $B72, Data!$C:$C, ">=" & DATE(2025, MATCH(E$56, {"Jan","Feb","Mar","Apr","May","Jun","Jul","Aug","Sep","Oct","Nov","Dec"}, 0), 1), Data!E:E, "<" & EDATE(DATE(2025, MATCH(E$56, {"Jan","Feb","Mar","Apr","May","Jun","Jul","Aug","Sep","Oct","Nov","Dec"}, 0), 1), 1)) -> -0.58 | E16: =SUMIFS(Data!$I:$I, Data!$F:$F, $B72, Data!$C:$C, ">=" & DATE(2025, MATCH(F$56, {"Jan","Feb","Mar","Apr","May","Jun","Jul","Aug","Sep","Oct","Nov","Dec"}, 0), 1), Data!F:F, "<" & EDATE(DATE(2025, MATCH(F$56, {"Jan","Feb","Mar","Apr","May","Jun","Jul","Aug","Sep","Oct","Nov","Dec"}, 0), 1), 1)) -> 0 | F16: =SUMIFS(Data!$I:$I, Data!$F:$F, $B72, Data!$C:$C, ">=" & DATE(2025, MATCH(G$56, {"Jan","Feb","Mar","Apr","May","Jun","Jul","Aug","Sep","Oct","Nov","Dec"}, 0), 1), Data!G:G, "<" & EDATE(DATE(2025, MATCH(G$56, {"Jan","Feb","Mar","Apr","May","Jun","Jul","Aug","Sep","Oct","Nov","Dec"}, 0), 1), 1)) -> 0 | G16: =SUMIFS(Data!$I:$I, Data!$F:$F, $B72, Data!$C:$C, ">=" & DATE(2025, MATCH(H$56, {"Jan","Feb","Mar","Apr","May","Jun","Jul","Aug","Sep","Oct","Nov","Dec"}, 0), 1), Data!H:H, "<" & EDATE(DATE(2025, MATCH(H$56, {"Jan","Feb","Mar","Apr","May","Jun","Jul","Aug","Sep","Oct","Nov","Dec"}, 0), 1), 1)) -> 0 | H16: =SUMIFS(Data!$I:$I, Data!$F:$F, $B72, Data!$C:$C, ">=" & DATE(2025, MATCH(I$56, {"Jan","Feb","Mar","Apr","May","Jun","Jul","Aug","Sep","Oct","Nov","Dec"}, 0), 1), Data!I:I, "<" & EDATE(DATE(2025, MATCH(I$56, {"Jan","Feb","Mar","Apr","May","Jun","Jul","Aug","Sep","Oct","Nov","Dec"}, 0), 1), 1)) -> -467.27 | I16: =SUMIFS(Data!$I:$I, Data!$F:$F, $B72, Data!$C:$C, ">=" & DATE(2025, MATCH(J$56, {"Jan","Feb","Mar","Apr","May","Jun","Jul","Aug","Sep","Oct","Nov","Dec"}, 0), 1), Data!J:J, "<" & EDATE(DATE(2025, MATCH(J$56, {"Jan","Feb","Mar","Apr","May","Jun","Jul","Aug","Sep","Oct","Nov","Dec"}, 0), 1), 1)) -> 0 | J16: =SUMIFS(Data!$I:$I, Data!$F:$F, $B72, Data!$C:$C, ">=" & DATE(2025, MATCH(K$56, {"Jan","Feb","Mar","Apr","May","Jun","Jul","Aug","Sep","Oct","Nov","Dec"}, 0), 1), Data!K:K, "<" & EDATE(DATE(2025, MATCH(K$56, {"Jan","Feb","Mar","Apr","May","Jun","Jul","Aug","Sep","Oct","Nov","Dec"}, 0), 1), 1)) -> -464.22 | K16: =SUMIFS(Data!$I:$I, Data!$F:$F, $B72, Data!$C:$C, ">=" & DATE(2025, MATCH(L$56, {"Jan","Feb","Mar","Apr","May","Jun","Jul","Aug","Sep","Oct","Nov","Dec"}, 0), 1), Data!L:L, "<" & EDATE(DATE(2025, MATCH(L$56, {"Jan","Feb","Mar","Apr","May","Jun","Jul","Aug","Sep","Oct","Nov","Dec"}, 0), 1), 1)) -> 0 | L16: =SUMIFS(Data!$I:$I, Data!$F:$F, $B72, Data!$C:$C, ">=" & DATE(2025, MATCH(M$56, {"Jan","Feb","Mar","Apr","May","Jun","Jul","Aug","Sep","Oct","Nov","Dec"}, 0), 1), Data!M:M, "<" & EDATE(DATE(2025, MATCH(M$56, {"Jan","Feb","Mar","Apr","May","Jun","Jul","Aug","Sep","Oct","Nov","Dec"}, 0), 1), 1)) -> 0 | M16: =SUMIFS(Data!$I:$I, Data!$F:$F, $B72, Data!$C:$C, ">=" & DATE(2025, MATCH(N$56, {"Jan","Feb","Mar","Apr","May","Jun","Jul","Aug","Sep","Oct","Nov","Dec"}, 0), 1), Data!N:N, "<" & EDATE(DATE(2025, MATCH(N$56, {"Jan","Feb","Mar","Apr","May","Jun","Jul","Aug","Sep","Oct","Nov","Dec"}, 0), 1), 1)) -> 0
A17: Inversión | B17: =SUMIFS(Data!I:I, Data!F:F, $B73, Data!C:C, ">=" & DATE(2025, MATCH(C$56, {"Jan","Feb","Mar","Apr","May","Jun","Jul","Aug","Sep","Oct","Nov","Dec"}, 0), 1), Data!C:C, "<" & EDATE(DATE(2025, MATCH(C$56, {"Jan","Feb","Mar","Apr","May","Jun","Jul","Aug","Sep","Oct","Nov","Dec"}, 0), 1), 1)) -> -300 | C17: =SUMIFS(Data!$I:$I, Data!$F:$F, $B73, Data!$C:$C, ">=" & DATE(2025, MATCH(D$56, {"Jan","Feb","Mar","Apr","May","Jun","Jul","Aug","Sep","Oct","Nov","Dec"}, 0), 1), Data!D:D, "<" & EDATE(DATE(2025, MATCH(D$56, {"Jan","Feb","Mar","Apr","May","Jun","Jul","Aug","Sep","Oct","Nov","Dec"}, 0), 1), 1)) -> -1900 | D17: =SUMIFS(Data!$I:$I, Data!$F:$F, $B73, Data!$C:$C, ">=" & DATE(2025, MATCH(E$56, {"Jan","Feb","Mar","Apr","May","Jun","Jul","Aug","Sep","Oct","Nov","Dec"}, 0), 1), Data!E:E, "<" & EDATE(DATE(2025, MATCH(E$56, {"Jan","Feb","Mar","Apr","May","Jun","Jul","Aug","Sep","Oct","Nov","Dec"}, 0), 1), 1)) -> -1100 | E17: =SUMIFS(Data!$I:$I, Data!$F:$F, $B73, Data!$C:$C, ">=" & DATE(2025, MATCH(F$56, {"Jan","Feb","Mar","Apr","May","Jun","Jul","Aug","Sep","Oct","Nov","Dec"}, 0), 1), Data!F:F, "<" & EDATE(DATE(2025, MATCH(F$56, {"Jan","Feb","Mar","Apr","May","Jun","Jul","Aug","Sep","Oct","Nov","Dec"}, 0), 1), 1)) -> 0 | F17: =SUMIFS(Data!$I:$I, Data!$F:$F, $B73, Data!$C:$C, ">=" & DATE(2025, MATCH(G$56, {"Jan","Feb","Mar","Apr","May","Jun","Jul","Aug","Sep","Oct","Nov","Dec"}, 0), 1), Data!G:G, "<" & EDATE(DATE(2025, MATCH(G$56, {"Jan","Feb","Mar","Apr","May","Jun","Jul","Aug","Sep","Oct","Nov","Dec"}, 0), 1), 1)) -> 0 | G17: =SUMIFS(Data!$I:$I, Data!$F:$F, $B73, Data!$C:$C, ">=" & DATE(2025, MATCH(H$56, {"Jan","Feb","Mar","Apr","May","Jun","Jul","Aug","Sep","Oct","Nov","Dec"}, 0), 1), Data!H:H, "<" & EDATE(DATE(2025, MATCH(H$56, {"Jan","Feb","Mar","Apr","May","Jun","Jul","Aug","Sep","Oct","Nov","Dec"}, 0), 1), 1)) -> 0 | H17: =SUMIFS(Data!$I:$I, Data!$F:$F, $B73, Data!$C:$C, ">=" & DATE(2025, MATCH(I$56, {"Jan","Feb","Mar","Apr","May","Jun","Jul","Aug","Sep","Oct","Nov","Dec"}, 0), 1), Data!I:I, "<" & EDATE(DATE(2025, MATCH(I$56, {"Jan","Feb","Mar","Apr","May","Jun","Jul","Aug","Sep","Oct","Nov","Dec"}, 0), 1), 1)) -> -6150 | I17: =SUMIFS(Data!$I:$I, Data!$F:$F, $B73, Data!$C:$C, ">=" & DATE(2025, MATCH(J$56, {"Jan","Feb","Mar","Apr","May","Jun","Jul","Aug","Sep","Oct","Nov","Dec"}, 0), 1), Data!J:J, "<" & EDATE(DATE(2025, MATCH(J$56, {"Jan","Feb","Mar","Apr","May","Jun","Jul","Aug","Sep","Oct","Nov","Dec"}, 0), 1), 1)) -> 0 | J17: =SUMIFS(Data!$I:$I, Data!$F:$F, $B73, Data!$C:$C, ">=" & DATE(2025, MATCH(K$56, {"Jan","Feb","Mar","Apr","May","Jun","Jul","Aug","Sep","Oct","Nov","Dec"}, 0), 1), Data!K:K, "<" & EDATE(DATE(2025, MATCH(K$56, {"Jan","Feb","Mar","Apr","May","Jun","Jul","Aug","Sep","Oct","Nov","Dec"}, 0), 1), 1)) -> -5300 | K17: =SUMIFS(Data!$I:$I, Data!$F:$F, $B73, Data!$C:$C, ">=" & DATE(2025, MATCH(L$56, {"Jan","Feb","Mar","Apr","May","Jun","Jul","Aug","Sep","Oct","Nov","Dec"}, 0), 1), Data!L:L, "<" & EDATE(DATE(2025, MATCH(L$56, {"Jan","Feb","Mar","Apr","May","Jun","Jul","Aug","Sep","Oct","Nov","Dec"}, 0), 1), 1)) -> 0 | L17: =SUMIFS(Data!$I:$I, Data!$F:$F, $B73, Data!$C:$C, ">=" & DATE(2025, MATCH(M$56, {"Jan","Feb","Mar","Apr","May","Jun","Jul","Aug","Sep","Oct","Nov","Dec"}, 0), 1), Data!M:M, "<" & EDATE(DATE(2025, MATCH(M$56, {"Jan","Feb","Mar","Apr","May","Jun","Jul","Aug","Sep","Oct","Nov","Dec"}, 0), 1), 1)) -> 0 | M17: =SUMIFS(Data!$I:$I, Data!$F:$F, $B73, Data!$C:$C, ">=" & DATE(2025, MATCH(N$56, {"Jan","Feb","Mar","Apr","May","Jun","Jul","Aug","Sep","Oct","Nov","Dec"}, 0), 1), Data!N:N, "<" & EDATE(DATE(2025, MATCH(N$56, {"Jan","Feb","Mar","Apr","May","Jun","Jul","Aug","Sep","Oct","Nov","Dec"}, 0), 1), 1)) -> 0
... A29: (blank) | B29: =SUMIFS(Data!I:I, Data!F:F, $B85, Data!C:C, ">=" & DATE(2025, MATCH(C$56, {"Jan","Feb","Mar","Apr","May","Jun","Jul","Aug","Sep","Oct","Nov","Dec"}, 0), 1), Data!C:C, "<" & EDATE(DATE(2025, MATCH(C$56, {"Jan","Feb","Mar","Apr","May","Jun","Jul","Aug","Sep","Oct","Nov","Dec"}, 0), 1), 1)) -> 0 | C29: =SUMIFS(Data!$I:$I, Data!$F:$F, $B85, Data!$C:$C, ">=" & DATE(2025, MATCH(D$56, {"Jan","Feb","Mar","Apr","May","Jun","Jul","Aug","Sep","Oct","Nov","Dec"}, 0), 1), Data!D:D, "<" & EDATE(DATE(2025, MATCH(D$56, {"Jan","Feb","Mar","Apr","May","Jun","Jul","Aug","Sep","Oct","Nov","Dec"}, 0), 1), 1)) -> 0 | D29: =SUMIFS(Data!$I:$I, Data!$F:$F, $B85, Data!$C:$C, ">=" & DATE(2025, MATCH(E$56, {"Jan","Feb","Mar","Apr","May","Jun","Jul","Aug","Sep","Oct","Nov","Dec"}, 0), 1), Data!E:E, "<" & EDATE(DATE(2025, MATCH(E$56, {"Jan","Feb","Mar","Apr","May","Jun","Jul","Aug","Sep","Oct","Nov","Dec"}, 0), 1), 1)) -> 0 | E29: =SUMIFS(Data!$I:$I, Data!$F:$F, $B85, Data!$C:$C, ">=" & DATE(2025, MATCH(F$56, {"Jan","Feb","Mar","Apr","May","Jun","Jul","Aug","Sep","Oct","Nov","Dec"}, 0), 1), Data!F:F, "<" & EDATE(DATE(2025, MATCH(F$56, {"Jan","Feb","Mar","Apr","May","Jun","Jul","Aug","Sep","Oct","Nov","Dec"}, 0), 1), 1)) -> 0 | F29: =SUMIFS(Data!$I:$I, Data!$F:$F, $B85, Data!$C:$C, ">=" & DATE(2025, MATCH(G$56, {"Jan","Feb","Mar","Apr","May","Jun","Jul","Aug","Sep","Oct","Nov","Dec"}, 0), 1), Data!G:G, "<" & EDATE(DATE(2025, MATCH(G$56, {"Jan","Feb","Mar","Apr","May","Jun","Jul","Aug","Sep","Oct","Nov","Dec"}, 0), 1), 1)) -> 0 | G29: =SUMIFS(Data!$I:$I, Data!$F:$F, $B85, Data!$C:$C, ">=" & DATE(2025, MATCH(H$56, {"Jan","Feb","Mar","Apr","May","Jun","Jul","Aug","Sep","Oct","Nov","Dec"}, 0), 1), Data!H:H, "<" & EDATE(DATE(2025, MATCH(H$56, {"Jan","Feb","Mar","Apr","May","Jun","Jul","Aug","Sep","Oct","Nov","Dec"}, 0), 1), 1)) -> 0 | H29: =SUMIFS(Data!$I:$I, Data!$F:$F, $B85, Data!$C:$C, ">=" & DATE(2025, MATCH(I$56, {"Jan","Feb","Mar","Apr","May","Jun","Jul","Aug","Sep","Oct","Nov","Dec"}, 0), 1), Data!I:I, "<" & EDATE(DATE(2025, MATCH(I$56, {"Jan","Feb","Mar","Apr","May","Jun","Jul","Aug","Sep","Oct","Nov","Dec"}, 0), 1), 1)) -> 0 | I29: =SUMIFS(Data!$I:$I, Data!$F:$F, $B85, Data!$C:$C, ">=" & DATE(2025, MATCH(J$56, {"Jan","Feb","Mar","Apr","May","Jun","Jul","Aug","Sep","Oct","Nov","Dec"}, 0), 1), Data!J:J, "<" & EDATE(DATE(2025, MATCH(J$56, {"Jan","Feb","Mar","Apr","May","Jun","Jul","Aug","Sep","Oct","Nov","Dec"}, 0), 1), 1)) -> 0 | J29: =SUMIFS(Data!$I:$I, Data!$F:$F, $B85, Data!$C:$C, ">=" & DATE(2025, MATCH(K$56, {"Jan","Feb","Mar","Apr","May","Jun","Jul","Aug","Sep","Oct","Nov","Dec"}, 0), 1), Data!K:K, "<" & EDATE(DATE(2025, MATCH(K$56, {"Jan","Feb","Mar","Apr","May","Jun","Jul","Aug","Sep","Oct","Nov","Dec"}, 0), 1), 1)) -> 0 | K29: =SUMIFS(Data!$I:$I, Data!$F:$F, $B85, Data!$C:$C, ">=" & DATE(2025, MATCH(L$56, {"Jan","Feb","Mar","Apr","May","Jun","Jul","Aug","Sep","Oct","Nov","Dec"}, 0), 1), Data!L:L, "<" & EDATE(DATE(2025, MATCH(L$56, {"Jan","Feb","Mar","Apr","May","Jun","Jul","Aug","Sep","Oct","Nov","Dec"}, 0), 1), 1)) -> 0 | L29: =SUMIFS(Data!$I:$I, Data!$F:$F, $B85, Data!$C:$C, ">=" & DATE(2025, MATCH(M$56, {"Jan","Feb","Mar","Apr","May","Jun","Jul","Aug","Sep","Oct","Nov","Dec"}, 0), 1), Data!M:M, "<" & EDATE(DATE(2025, MATCH(M$56, {"Jan","Feb","Mar","Apr","May","Jun","Jul","Aug","Sep","Oct","Nov","Dec"}, 0), 1), 1)) -> 0 | M29: =SUMIFS(Data!$I:$I, Data!$F:$F, $B85, Data!$C:$C, ">=" & DATE(2025, MATCH(N$56, {"Jan","Feb","Mar","Apr","May","Jun","Jul","Aug","Sep","Oct","Nov","Dec"}, 0), 1), Data!N:N, "<" & EDATE(DATE(2025, MATCH(N$56, {"Jan","Feb","Mar","Apr","May","Jun","Jul","Aug","Sep","Oct","Nov","Dec"}, 0), 1), 1)) -> 0
B33: =IFERROR(B3 / INDEX(C$54:O$86, MATCH($A3, $B$54:$B$86, 0), MATCH(C$56, C$56:O$56, 0)), "") -> 1 | C33: =IFERROR(C3 / INDEX(D$54:P$86, MATCH($A3, $B$54:$B$86, 0), MATCH(D$56, D$56:P$56, 0)), "") -> 3 | D33: =IFERROR(D3 / INDEX(E$54:Q$86, MATCH($A3, $B$54:$B$86, 0), MATCH(E$56, E$56:Q$56, 0)), "") -> 0 | E33: =IFERROR(E3 / INDEX(F$54:R$86, MATCH($A3, $B$54:$B$86, 0), MATCH(F$56, F$56:R$56, 0)), "") -> 0 | F33: =IFERROR(F3 / INDEX(G$54:S$86, MATCH($A3, $B$54:$B$86, 0), MATCH(G$56, G$56:S$56, 0)), "") -> 0 | G33: =IFERROR(G3 / INDEX(H$54:T$86, MATCH($A3, $B$54:$B$86, 0), MATCH(H$56, H$56:T$56, 0)), "") -> 0 | H33: =IFERROR(H3 / INDEX(I$54:U$86, MATCH($A3, $B$54:$B$86, 0), MATCH(I$56, I$56:U$56, 0)), "") -> 7.08 | I33: =IFERROR(I3 / INDEX(J$54:V$86, MATCH($A3, $B$54:$B$86, 0), MATCH(J$56, J$56:V$56, 0)), "") -> 0 | ... M33: =IFERROR(M3 / INDEX(N$54:Z$86, MATCH($A3, $B$54:$B$86, 0), MATCH(N$56, N$56:Z$56, 0)), "") -> 0
C54: 2025
C55: Qtr1 | F55: Qtr2 | I55: Qtr3 | L55: Qtr4
C56: Jan | D56: Feb | E56: Mar | F56: Apr | G56: May | H56: Jun | I56: Jul | J56: Aug | K56: Sep | L56: Oct | M56: Nov | N56: Dec
C58: =SUM(C59:C60) -> 4600.66 | D58: =SUM(D59:D60) -> 4600.66 | E58: =SUM(E59:E60) -> 4600.66 | F58: =SUM(F59:F60) -> 4600.66 | G58: =SUM(G59:G60) -> 4600.66 | H58: =SUM(H59:H60) -> 4600.66 | I58: =SUM(I59:I60) -> 4600.66 | J58: =SUM(J59:J60) -> 4600.66 | ... N58: =SUM(N59:N60) -> 4600.66 | O58: =SUM(C58:N58) -> 55207.92
B59: Aporte a la casa | C59: 200 | D59: 200 | E59: 200 | F59: 200 | G59: 200 | H59: 200 | I59: 200 | J59: 200 | K59: 200 | L59: 200 | M59: 200 | N59: 200 | O59: =SUM(C59:N59) -> 2400
B60: Sueldo | C60: =2200.33*2 -> 4400.66 | D60: =2200.33*2 -> 4400.66 | E60: =2200.33*2 -> 4400.66 | F60: =2200.33*2 -> 4400.66 | G60: =2200.33*2 -> 4400.66 | H60: =2200.33*2 -> 4400.66 | I60: =2200.33*2 -> 4400.66 | J60: =2200.33*2 -> 4400.66 | ... N60: =2200.33*2 -> 4400.66 | O60: =SUM(C60:N60) -> 52807.92
C61: =SUM(C62:C85) -> -3727.01 | D61: =SUM(D62:D85) -> -3927.01 | E61: =SUM(E62:E85) -> -4327.01 | F61: =SUM(F62:F85) -> -3777.01 | G61: =SUM(G62:G85) -> -3827.01 | H61: =SUM(H62:H85) -> -3658.69 | I61: =SUM(I62:I85) -> -3849.43 | J61: =SUM(J62:J85) -> -3754.404 | ... N61: =SUM(N62:N85) -> -4454.404 | O61: =SUM(C61:N61) -> -47315.19
B62: Alquiler | C62: -918 | D62: -918 | E62: -918 | F62: -918 | G62: -918 | H62: -918 | I62: =-918*1.03 -> -945.54 | J62: =-918*1.03 -> -945.54 | K62: =-918*1.03 -> -945.54 | L62: =-918*1.03 -> -945.54 | M62: =-918*1.03 -> -945.54 | N62: =-918*1.03 -> -945.54 | O62: =SUM(C62:N62) -> -11181.24
B63: ayes | C63: 0 | D63: 0 | E63: 0 | F63: 0 | G63: 0 | H63: 0 | I63: 0 | J63: 0 | K63: 0 | L63: 0 | M63: 0 | N63: 0 | O63: =SUM(C63:N63) -> 0
B64: café | C64: -40 | D64: -40 | E64: -40 | F64: -40 | G64: -40 | H64: -40 | I64: -40 | J64: -40 | K64: -40 | L64: -40 | M64: -40 | N64: -40 | O64: =SUM(C64:N64) -> -480
B65: Compras | C65: -300 | D65: -300 | E65: -300 | F65: -300 | G65: -300 | H65: -300 | I65: -300 | J65: -300 | K65: -300 | L65: -300 | M65: -300 | N65: -300 | O65: =SUM(C65:N65) -> -3600
B66: Deporte | C66: 0 | D66: 0 | E66: 0 | F66: 0 | G66: 0 | H66: 0 | I66: 0 | J66: 0 | K66: 0 | L66: 0 | M66: 0 | N66: 0 | O66: =SUM(C66:N66) -> 0
B67: Deudas | C67: -68.32 | D67: -68.32 | E67: -68.32 | F67: -68.32 | G67: -68.32 | H67: 0 | I67: 0 | J67: 0 | K67: 0 | L67: 0 | M67: 0 | N67: 0 | O67: =SUM(C67:N67) -> -341.6
B68: Donación | C68: 0 | D68: 0 | E68: 0 | F68: 0 | G68: 0 | H68: 0 | I68: 0 | J68: 0 | K68: 0 | L68: 0 | M68: 0 | N68: 0 | O68: =SUM(C68:N68) -> 0
B69: E'Kabel | C69: 0 | D69: 0 | E69: 0 | F69: 0 | G69: 0 | H69: 0 | I69: 0 | J69: 0 | K69: 0 | L69: 0 | M69: 0 | N69: 0 | O69: =SUM(C69:N69) -> 0
B70: Entretenimiento | C70: -520 | D70: -520 | E70: -520 | F70: -520 | G70: -520 | H70: -520 | I70: -520 | J70: -520 | K70: -520 | L70: -520 | M70: -520 | N70: -520 | O70: =SUM(C70:N70) -> -6240
B71: Establecernos | C71: 0 | D71: 0 | E71: 0 | F71: 0 | G71: 0 | H71: 0 | I71: 0 | J71: 0 | K71: 0 | L71: 0 | M71: 0 | N71: 0 | O71: =SUM(C71:N71) -> 0
B72: Financiero | C72: -0.61 | D72: -0.61 | E72: -0.61 | F72: -0.61 | G72: -0.61 | H72: -0.61 | I72: -0.61 | J72: -0.61 | K72: -0.61 | L72: -0.61 | M72: -0.61 | N72: -0.61 | O72: =SUM(C72:N72) -> -7.32
B73: Inversión | C73: -700 | D73: -700 | E73: -700 | F73: -700 | G73: -700 | H73: -700 | I73: -700 | J73: -700 | K73: -700 | L73: -700 | M73: -700 | N73: -700 | O73: =SUM(C73:N73) -> -8400
B74: Master | C74: 0 | D74: 0 | E74: 0 | F74: 0 | G74: 0 | H74: 0 | I74: 0 | J74: 0 | K74: 0 | L74: 0 | M74: 0 | N74: 0 | O74: =SUM(C74:N74) -> 0
... B79: Reparaciones | C79: -20 | D79: -20 | E79: -20 | F79: -20 | G79: -20 | H79: -20 | I79: -20 | J79: -20 | K79: -20 | L79: -20 | M79: -20 | N79: -20 | O79: =SUM(C79:N79) -> -240
B80: Seguro | C80: -99.48 | D80: -99.48 | E80: -99.48 | F80: -99.48 | G80: -99.48 | H80: -99.48 | I80: -99.48 | J80: =I80*1.05 -> -104.454 | K80: -104.454 | L80: -104.454 | M80: -104.454 | N80: -104.454 | O80: =SUM(C80:N80) -> -1218.63
B81: Servicios | C81: -234 | D81: -234 | E81: -234 | F81: -234 | G81: -234 | H81: -234 | I81: -234 | J81: -234 | K81: -234 | L81: -234 | M81: -234 | N81: -234 | O81: =SUM(C81:N81) -> -2808
B82: Suscripciones | C82: =-20.22-17.99-2.99 -> -41.2 | D82: =-20.22-17.99-2.99 -> -41.2 | E82: =-20.22-17.99-2.99 -> -41.2 | F82: =-20.22-17.99-2.99 -> -41.2 | G82: =-20.22-17.99-2.99 -> -41.2 | H82: =-20.22-17.99-2.99 -> -41.2 | I82: =-20.22-17.99-2.99 -> -41.2 | J82: =-20.22-17.99-2.99 -> -41.2 | ... N82: =-20.22-17.99-2.99 -> -41.2 | O82: =SUM(C82:N82) -> -494.4
B83: Transporte | C83: -65.4 | D83: -65.4 | E83: -65.4 | F83: -65.4 | G83: -65.4 | H83: -65.4 | I83: =-64.3*2 -> -128.6 | J83: =-64.3*2 -> -128.6 | K83: =-64.3*2 -> -128.6 | L83: =-64.3*2 -> -128.6 | M83: =-64.3*2 -> -128.6 | N83: =-64.3*2 -> -128.6 | O83: =SUM(C83:N83) -> -1164
B84: Vacaciones | C84: 0 | D84: -200 | E84: -600 | F84: 0 | G84: -100 | H84: 0 | I84: -100 | J84: 0 | K84: 0 | L84: -200 | M84: 0 | N84: 0 | O84: =SUM(C84:N84) -> -1200
B85: (blank) | C85: 0 | D85: 0 | E85: 0 | F85: 0 | G85: 0 | H85: 0 | I85: 0 | J85: 0 | K85: 0 | L85: 0 | M85: 0 | N85: 0 | O85: =SUM(C85:N85) -> 0
C86: =SUM(C58+C61) -> 873.65 | D86: =SUM(D58+D61) -> 673.65 | E86: =SUM(E58+E61) -> 273.65 | F86: =SUM(F58+F61) -> 823.65 | G86: =SUM(G58+G61) -> 773.65 | H86: =SUM(H58+H61) -> 941.97 | I86: =SUM(I58+I61) -> 751.23 | J86: =SUM(J58+J61) -> 846.256 | ... N86: =SUM(N58+N61) -> 146.256 | O86: =SUM(C86:N86) -> 7892.73

Sheet Sheet2
A1: Tipo | B1: Servicios
A3: Sum of Importe | B3: Column Labels
B4: 2023 | K4: 2023 Total | L4: 2024 | AF4: 2024 Total | AG4: 2025 | AU4: 2025 Total | AV4: Grand Total
B5: Qtr4 | J5: Qtr4 Total | L5: Qtr1 | N5: Qtr1 Total | O5: Qtr2 | S5: Qtr2 Total | T5: Qtr3 | Y5: Qtr3 Total | Z5: Qtr4 | AE5: Qtr4 Total | AG5: Qtr1 | AO5: Qtr1 Total | AP5: Qtr2 | AT5: Qtr2 Total
B6: Oct | C6: Oct Total | D6: Nov | F6: Nov Total | G6: Dec | I6: Dec Total | L6: Feb | M6: Feb Total | O6: Apr | P6: Apr Total | Q6: Jun | R6: Jun Total | T6: Jul | U6: Jul Total | V6: Sep | X6: Sep Total | Z6: Nov | AB6: Nov Total | AC6: Dec | AD6: Dec Total | AG6: Jan | AI6: Jan Total | AJ6: Feb | AK6: Feb Total | AL6: Mar | AN6: Mar Total | AP6: Apr | AQ6: Apr Total | AR6: May | AS6: May Total
A7: Row Labels | B7: 45225 | D7: 45237 | E7: 45238 | G7: 45271 | H7: 45280 | L7: 45334 | O7: 45384 | Q7: 45446 | T7: 45495 | V7: 45554 | W7: 45558 | Z7: 45602 | AA7: 45621 | AC7: 45635 | AG7: 45664 | AH7: 45684 | AJ7: 45691 | AL7: 45727 | AM7: 45744 | AP7: 45749 | AR7: 45782
A8: LIQUIDACION DEL CONTRATO 4326161 300 | H8: -0.01 | I8: -0.01 | J8: -0.01 | K8: -0.01 | V8: -0.01 | X8: -0.01 | Y8: -0.01 | AF8: -0.01 | AV8: -0.02
A9: RECIBO IBERDROLA CLIENTES, S.A.U Nº RECIBO 0073 0100 755 CBSJJVJ REF. MANDATO 286734314000 | D9: -9.52 | F9: -9.52 | J9: -9.52 | K9: -9.52 | AV9: -9.52
A10: RECIBO IBERDROLA CLIENTES, S.A.U Nº RECIBO 0073 0100 755 CBTGWDG REF. MANDATO 275734314000 | E10: -9.94 | F10: -9.94 | J10: -9.94 | K10: -9.94 | AV10: -9.94
A11: RECIBO Naturgy Clientes, S.A.U. Nº RECIBO 0073 0100 755 CHLRKHY REF. MANDATO 000000259696 | Z11: -46.2 | AB11: -46.2 | AE11: -46.2 | AF11: -46.2 | AV11: -46.2
A12: RECIBO Naturgy Clientes, S.A.U. Nº RECIBO 0073 0100 755 CHWNLPM REF. MANDATO 000000259696 | AC12: -46.2 | AD12: -46.2 | AE12: -46.2 | AF12: -46.2 | AV12: -46.2
A13: RECIBO Naturgy Clientes, S.A.U. Nº RECIBO 0073 0100 755 CJGMLSD REF. MANDATO 000000259696 | AG13: -46.2 | AI13: -46.2 | AO13: -46.2 | AU13: -46.2 | AV13: -46.2
A14: RECIBO Naturgy Clientes, S.A.U. Nº RECIBO 0073 0100 755 CJPGJHF REF. MANDATO 000000259696 | AJ14: -50.82 | AK14: -50.82 | AO14: -50.82 | AU14: -50.82 | AV14: -50.82
A15: RECIBO Naturgy Clientes, S.A.U. Nº RECIBO 0073 0100 755 CKCKCSJ REF. MANDATO 000000259696 | AL15: -50.82 | AN15: -50.82 | AO15: -50.82 | AU15: -50.82 | AV15: -50.82
A16: RECIBO Naturgy Clientes, S.A.U. Nº RECIBO 0073 0100 755 CKVBKKM REF. MANDATO 000000259696 | AR16: -50.82 | AS16: -50.82 | AT16: -50.82 | AU16: -50.82 | AV16: -50.82
A17: RECIBO Naturgy Clientes. SAU Nº RECIBO 0073 0100 755 CKKMLVH REF MANDATO 000000259696 | AP17: -50.82 | AQ17: -50.82 | AT17: -50.82 | AU17: -50.82 | AV17: -50.82
A18: RECIBO TOTALENERGIES CLIENTESSAU N? RECIBO 0073 0100 755 CDQHNMH REF. MANDATO NCESIGS241020230000000 | O18: -133.07 | P18: -133.07 | S18: -133.07 | AF18: -133.07 | AV18: -133.07
A19: RECIBO TOTALENERGIES CLIENTESSAU N? RECIBO 0073 0100 755 CFLKGSF REF. MANDATO NCESIGS241020230000000 | Q19: -110.26 | R19: -110.26 | S19: -110.26 | AF19: -110.26 | AV19: -110.26
A20: RECIBO TotalEnergies ClientesSAU Nº RECIBO 0073 0100 755 CCGBYHL REF. MANDATO NCESIGS241020230000000 | G20: -20.66 | I20: -20.66 | J20: -20.66 | K20: -20.66 | AV20: -20.66
A21: RECIBO TOTALENERGIES CLIENTESSAU Nº RECIBO 0073 0100 755 CCZTHJZ REF. MANDATO NCESIGS241020230000000 | L21: -137.99 | M21: -137.99 | N21: -137.99 | AF21: -137.99 | AV21: -137.99
A22: RECIBO TOTALENERGIES CLIENTESSAU Nº RECIBO 0073 0100 755 CGBLTWG REF. MANDATO NCESIGS241020230000000 | T22: -166.67 | U22: -166.67 | Y22: -166.67 | AF22: -166.67 | AV22: -166.67
A23: RECIBO TotalEnergies ClientesSAU Nº RECIBO 0073 0100 755 CGTYYYW REF. MANDATO NCESIGS241020230000000 | W23: -172.76 | X23: -172.76 | Y23: -172.76 | AF23: -172.76 | AV23: -172.76
A24: RECIBO TotalEnergies ClientesSAU Nº RECIBO 0073 0100 755 CHQLSFJ REF. MANDATO NCESIGS241020230000000 | AA24: -80.84 | AB24: -80.84 | AE24: -80.84 | AF24: -80.84 | AV24: -80.84
A25: RECIBO TotalEnergies ClientesSAU Nº RECIBO 0073 0100 755 CJLQWND REF. MANDATO NCESIGS241020230000000 | AH25: -92.23 | AI25: -92.23 | AO25: -92.23 | AU25: -92.23 | AV25: -92.23
A26: RECIBO TotalEnergies ClientesSAU Nº RECIBO 0073 0100 755 CKHGTNR REF. MANDATO NCESIGS241020230000000 | AM26: -85.83 | AN26: -85.83 | AO26: -85.83 | AU26: -85.83 | AV26: -85.83
A27: RECIBO TotalEnergies Mercado SAU Nº RECIBO 0073 0100 755 CBPZPHV REF. MANDATO HCESIG1230620230000000 | B27: -224.21 | C27: -224.21 | J27: -224.21 | K27: -224.21 | AV27: -224.21
A28: TRANSFERENCIA DE TOTALENERGIES MERCADO ESPANA, S.A.U, CONCEPTO Abono TotalEnergies 700008400014 | B28: 31.71 | C28: 31.71 | J28: 31.71 | K28: 31.71 | AV28: 31.71
A29: Grand Total | B29: -192.5 | C29: -192.5 | D29: -9.52 | E29: -9.94 | F29: -19.46 | G29: -20.66 | H29: -0.01 | I29: -20.67 | J29: -232.63 | K29: -232.63 | L29: -137.99 | M29: -137.99 | N29: -137.99 | O29: -133.07 | P29: -133.07 | Q29: -110.26 | R29: -110.26 | S29: -243.33 | T29: -166.67 | U29: -166.67 | V29: -0.01 | W29: -172.76 | X29: -172.77 | Y29: -339.44 | Z29: -46.2 | AA29: -80.84 | AB29: -127.04 | AC29: -46.2 | AD29: -46.2 | AE29: -173.24 | AF29: -894 | AG29: -46.2 | AH29: -92.23 | AI29: -138.43 | AJ29: -50.82 | AK29: -50.82 | AL29: -50.82 | AM29: -85.83 | AN29: -136.65 | AO29: -325.9 | AP29: -50.82 | AQ29: -50.82 | AR29: -50.82 | AS29: -50.82 | AT29: -101.64 | AU29: -427.54 | AV29: -1554.17

Sheet Sheet3
A1: Cuenta | B1: (Multiple Items)
AW2: 2025 | BJ2: 2026
A3: Sum of Importe | B3: Column Labels
B4: 2023 | C4: 2024 | D4: 2025 | K4: 2025 Total | L4: 2026 | O4: 2026 Total | P4: Grand Total
D5: Qtr1 | E5: Qtr2 | H5: Qtr2 Total | I5: Qtr3 | J5: Qtr4 | L5: Qtr1 | M5: Qtr2 | N5: Qtr2 Total
E6: Apr | F6: May | G6: Jun | M6: Apr
A7: Row Labels
A8: (blank) | J8: -76.24 | K8: -76.24 | P8: -76.24
A9: Navidad | J9: -76.24 | K9: -76.24 | P9: -76.24
A10: Ingreso | B10: 36296.34 | C10: 81547.17 | D10: 25879.79 | E10: 7164.76 | F10: 5220.34 | G10: 8572.75 | H10: 20957.85 | I10: 11575.24 | J10: 21566.16 | K10: 79979.04 | L10: 47341.67 | O10: 47341.67 | P10: 245164.22
A11: Egreso | B11: -31579.96 | C11: -76090.56 | D11: -16893.15 | E11: -4114.79 | F11: -6177.03 | G11: -8847.46 | H11: -19139.28 | I11: -21560.85 | J11: -20642.71 | K11: -78235.99 | L11: -21794.15 | M11: -4009.75 | N11: -4009.75 | O11: -25803.9 | P11: -211710.41
A12: Donación | C12: -30 | P12: -30
A13: Establecernos | B13: -1186.72 | P13: -1186.72
A14: Ahorros | L14: -1500 | O14: -1500 | P14: -1500
A15: TRANSFERENCIA INMEDIATA A FAVOR DE Cristina Paz Rodríguez & Nicolás Daniel CONCEPTO Ahorro 3 meses | L15: -1500 | O15: -1500 | P15: -1500
A16: Sueldo | D16: -10.15 | K16: -10.15 | P16: -10.15
A17: (blank) | B17: -85.68 | C17: -53.72 | J17: -21.12 | K17: -21.12 | L17: -8964.51 | M17: -4009.75 | N17: -4009.75 | O17: -12974.26 | P17: -13134.78
A18: Master | B18: -4670.56 | C18: -6609.61 | D18: -22.38 | K18: -22.38 | P18: -11302.55
A19: Trabajo | C19: -1224.11 | D19: -13 | E19: -10.61 | H19: -10.61 | J19: -17.5 | K19: -41.11 | P19: -1265.22
A20: Deporte | B20: -4.5 | C20: -21.2 | J20: -72.98 | K20: -72.98 | L20: -14.82 | O20: -14.82 | P20: -113.5
A21: Reparaciones | C21: -410.75 | D21: -99 | E21: -32.41 | G21: -4.99 | H21: -37.4 | K21: -136.4 | L21: -32.19 | O21: -32.19 | P21: -579.34
A22: Café | B22: -137.06 | C22: -431.47 | D22: -69 | E22: -14.25 | F22: -50.75 | G22: -17.79 | H22: -82.79 | I22: -23.64 | J22: -17.8 | K22: -193.23 | L22: -1.3 | O22: -1.3 | P22: -763.06
A23: Deudas | B23: -444.51 | C23: -1950.6 | D23: -136.64 | E23: -136.77 | H23: -136.77 | I23: -36 | K23: -309.41 | P23: -2704.52
A24: Financiero | B24: -0.43 | C24: -97.48 | D24: -244.14 | E24: -1.53 | F24: -15.63 | H24: -17.16 | I24: -54.86 | J24: -93.29 | K24: -409.45 | L24: -1.46 | O24: -1.46 | P24: -508.82
A25: Seguro | B25: -510.1 | C25: -1559.92 | D25: -298.44 | E25: -99.48 | F25: -99.48 | G25: -99.48 | H25: -298.44 | I25: -215.32 | J25: -392.9 | K25: -1205.1 | L25: -359.52 | O25: -359.52 | P25: -3634.64
A26: Transporte | B26: -440.02 | C26: -1168 | D26: -259.52 | E26: -87.2 | F26: -86.9 | G26: -130.8 | H26: -304.9 | I26: -340.97 | J26: -381.19 | K26: -1286.58 | L26: -228.9 | O26: -228.9 | P26: -3123.5
A27: Presentes | B27: -351.99 | C27: -978.53 | D27: -542.32 | G27: -574.79 | H27: -574.79 | I27: -68.09 | J27: -183 | K27: -1368.2 | L27: -31.48 | O27: -31.48 | P27: -2730.2
A28: Suscripciones | B28: -64.19 | C28: -673.83 | D28: -187.2 | E28: -159.85 | F28: -95.44 | G28: -62.88 | H28: -318.17 | I28: -487.61 | J28: -612.26 | K28: -1605.24 | L28: -502.81 | O28: -502.81 | P28: -2846.07
A29: Vacaciones | C29: -2698.95 | F29: -524.56 | H29: -524.56 | I29: -1091.29 | J29: -59.3 | K29: -1675.15 | P29: -4374.1
A30: Navidad | C30: -805.56 | G30: -763.99 | H30: -763.99 | I30: -500 | J30: -1283.25 | K30: -2547.24 | L30: -126 | O30: -126 | P30: -3478.8
A31: Servicios | B31: -692.29 | C31: -2207.32 | D31: -740.04 | E31: -193.08 | F31: -334.68 | G31: -225.74 | H31: -753.5 | I31: -528.54 | J31: -567.12 | K31: -2589.2 | L31: -438.98 | O31: -438.98 | P31: -5927.79
A32: Compras | B32: -1106.6 | C32: -4428.59 | D32: -1410.03 | E32: -191.58 | F32: -348.84 | G32: -391.46 | H32: -931.88 | I32: -723.49 | J32: -1797.39 | K32: -4862.79 | L32: -1085.88 | O32: -1085.88 | P32: -11483.86
A33: Padres | B33: -362.79 | C33: -1139.07 | D33: -580.37 | E33: -234 | F33: -358.65 | G33: -154 | H33: -746.65 | I33: -827.34 | J33: -3416.07 | K33: -5570.43 | L33: -417.16 | O33: -417.16 | P33: -7489.45
A34: Ahorro mensual | I34: -6000 | K34: -6000 | P34: -6000
A35: TRANSFERENCIA A FAVOR DE Cristina Paz Rodríguez & Nicolás Daniel CONCEPTO: Cuenta Cris y Nico | I35: -6000 | K35: -6000 | P35: -6000
A36: Mercado | B36: -1687.65 | C36: -5798.16 | D36: -1723.94 | E36: -596.53 | F36: -682.11 | G36: -623.47 | H36: -1902.11 | I36: -1440.41 | J36: -1895.13 | K36: -6961.59 | L36: -1302.5 | O36: -1302.5 | P36: -15749.9
A37: Inversión | B37: -1800 | C37: -2800 | D37: -1700 | E37: -700 | F37: -300 | G37: -2100 | H37: -3100 | I37: -1950 | J37: -1700 | K37: -8450 | L37: -1400 | O37: -1400 | P37: -14450
A38: Alquiler | B38: -6660 | C38: -11826 | D38: -2754 | E38: -918 | F38: -918 | G38: -918 | H38: -2754 | I38: -1854 | J38: -2808 | K38: -10170 | L38: -1872 | O38: -1872 | P38: -30528
A39: Regularización | B39: -8952.82 | C39: -22098.86 | D39: -3885 | G39: -1700 | H39: -1700 | I39: -1700 | J39: -3567.02 | K39: -10852.02 | L39: -1350 | O39: -1350 | P39: -43253.7
A40: Entretenimiento | B40: -2422.05 | C40: -7078.83 | D40: -2217.98 | E40: -739.5 | F40: -2361.99 | G40: -1080.07 | H40: -4181.56 | I40: -3719.29 | J40: -1757.39 | K40: -11876.22 | L40: -2164.64 | O40: -2164.64 | P40: -23541.74
A41: Grand Total | B41: 4716.38 | C41: 5456.61 | D41: 8986.64 | E41: 3049.97 | F41: -956.69 | G41: -274.71 | H41: 1818.57 | I41: -9985.61 | J41: 847.21 | K41: 1666.81 | L41: 25547.52 | M41: -4009.75 | N41: -4009.75 | O41: 21537.77 | P41: 33377.57

Sheet Pendientes
A1: 1 | B1: Incluir la inflación en los cálculos
A2: 2 | B2: Crear las listas de servicios y suscripciones separadas donde se integren al flujo de caja completo
A3: 3 | B3: Definir escenarios (malo y bueno) según Desviación estándar

Sheet Sheet4
A3: Sum of Importe | B3: Column Labels
B4: 2026 | G4: 2026 Total | H4: Grand Total
B5: Qtr1 | E5: Qtr1 Total | F5: Qtr2
B6: Jan | C6: Feb | D6: Mar
A7: Row Labels
A8: Alquiler | B8: 200 | C8: -936 | D8: -936 | E8: -1672 | G8: -1672 | H8: -1672
A9: Aporte a la casa | D9: 200 | E9: 200 | G9: 200 | H9: 200
A10: Café | B10: -1.3 | E10: -1.3 | G10: -1.3 | H10: -1.3
A11: Compras | B11: -960.19 | C11: -78.44 | D11: 23.77 | E11: -1014.86 | G11: -1014.86 | H11: -1014.86
A12: Deporte | C12: -14.82 | E12: -14.82 | G12: -14.82 | H12: -14.82
A13: Entretenimiento | B13: -673.84 | C13: -847.93 | D13: -629.87 | E13: -2151.64 | G13: -2151.64 | H13: -2151.64
A14: Financiero | B14: -0.53 | D14: -0.93 | E14: -1.46 | G14: -1.46 | H14: -1.46
A15: Inversión | B15: -300 | C15: -700 | D15: -400 | E15: -1400 | G15: -1400 | H15: -1400
A16: Mercado | B16: -679.36 | C16: -487.97 | D16: -135.17 | E16: -1302.5 | G16: -1302.5 | H16: -1302.5
A17: Navidad | B17: 141 | C17: -126 | E17: 15 | G17: 15 | H17: 15
A18: Padres | B18: -82.34 | C18: -238.03 | D18: -81.89 | E18: -402.26 | G18: -402.26 | H18: -402.26
A19: Presentes | C19: -7.49 | D19: -23.99 | E19: -31.48 | G19: -31.48 | H19: -31.48
A20: Regularización | B20: 0 | E20: 0 | G20: 0 | H20: 0
A21: Reparaciones | D21: -32.19 | E21: -32.19 | G21: -32.19 | H21: -32.19
A22: Seguro | B22: -115.84 | C22: -127.84 | D22: -115.84 | E22: -359.52 | G22: -359.52 | H22: -359.52
A23: Servicios | B23: -240.77 | C23: -143.76 | D23: -54.45 | E23: -438.98 | G23: -438.98 | H23: -438.98
A24: Sueldo | B24: 2305.43 | C24: 4801.61 | D24: 2304.31 | E24: 9411.35 | G24: 9411.35 | H24: 9411.35
A25: Suscripciones | B25: -201.87 | C25: -161.88 | D25: -139.06 | E25: -502.81 | G25: -502.81 | H25: -502.81
A26: Transporte | B26: -65.4 | C26: -98.1 | D26: -24.7 | E26: -188.2 | G26: -188.2 | H26: -188.2
A27: (blank) | B27: -1377.41 | C27: -735.4 | D27: 29048 | E27: 26935.19 | F27: -4009.75 | G27: 22925.44 | H27: 22925.44
A28: Ahorros | B28: -1500 | E28: -1500 | G28: -1500 | H28: -1500
A29: Cristina | B29: -1500 | E29: -1500 | G29: -1500 | H29: -1500
A30: Grand Total | B30: -3552.42 | C30: 97.95 | D30: 29001.99 | E30: 25547.52 | F30: -4009.75 | G30: 21537.77 | H30: 21537.77

Sheet Analisis 2025
A1: Years (Fecha valor REAL) | B1: 2025
A3: Sum of Importe | B3: Column Labels
A4: Row Labels | B4: Jan | C4: Feb | D4: Mar | E4: Apr | F4: May | G4: Jun | H4: Jul | I4: Aug | J4: Sep | K4: Oct | L4: Nov | M4: Dec | N4: Grand Total
A5: Ahorro mensual | J5: -6000 | N5: -6000 | Q5: =+"Este año nuestro patrimonio ha crecido en "&GETPIVOTDATA("Importe",$A$3)+6000+1300+8450&" EUR" -> Este año nuestro patrimonio ha crecido en 16914.58 EUR
A6: Alquiler | C6: -918 | D6: -1836 | E6: -918 | F6: -918 | G6: -918 | I6: -1854 | K6: -936 | L6: -936 | M6: -936 | N6: -10170 | Q6: De este dinero, 8450 EUR ha sido invertido en Padres, jubilación, hijos y María
A7: Aporte a la casa | B7: 200 | C7: 200 | E7: 200 | F7: 400 | G7: 34.95 | H7: 0 | I7: 16 | J7: 200 | K7: 400 | L7: 200 | M7: 200 | N7: 2050.95 | Q7: 1300 EUR en Bitcoin
A8: Café | B8: -33.2 | C8: -29.8 | E8: -6.25 | F8: -50.75 | G8: -17.79 | I8: -6 | J8: -9.69 | K8: -3.1 | L8: -4 | M8: -10.7 | N8: -171.28 | Q8: 6000 EUR en ahorros para gastos mensuales
A9: Compras | B9: -252.33 | C9: -16.74 | D9: -1092.27 | E9: -191.58 | F9: -348.84 | G9: -391.46 | H9: -234.59 | I9: -227.29 | J9: -261.61 | K9: -1343.18 | L9: -252.06 | M9: -202.15 | N9: -4814.1
A10: Deporte | M10: -28.04 | N10: -28.04
A11: Deudas | B11: -68.32 | C11: -68.32 | E11: -136.77 | J11: -36 | N11: -309.41
A12: Entretenimiento | B12: -818.57 | C12: -504.86 | D12: -787.25 | E12: -1132.47 | F12: -1585.44 | G12: -1066.07 | H12: -1051.31 | I12: -1237.57 | J12: -1346.39 | K12: -261.91 | L12: -676.48 | M12: -711.91 | N12: -11180.23
A13: Financiero | B13: -1.32 | C13: -242.24 | D13: -0.58 | E13: -1.53 | F13: 1711.25 | H13: -3.05 | I13: -0.55 | J13: -50.54 | K13: -2.2 | L13: -90 | M13: -1.09 | N13: 1318.15
A14: Inversión | B14: -300 | C14: -700 | D14: -700 | E14: -700 | F14: -300 | G14: -2100 | H14: -300 | I14: -550 | J14: -1100 | K14: -700 | L14: -300 | M14: -700 | N14: -8450
A15: Master | D15: -22.38 | N15: -22.38
A16: Mercado | B16: -547.3 | C16: -561.25 | D16: -615.39 | E16: -596.53 | F16: -682.11 | G16: -603.57 | H16: -252.72 | I16: -604.42 | J16: -578.07 | K16: -538.77 | L16: -771.34 | M16: -585.02 | N16: -6936.49
A17: Navidad | G17: -763.99 | H17: -250 | J17: -250 | K17: -250 | L17: -342.85 | M17: -383.64 | N17: -2240.48
A18: Padres | B18: -9.72 | C18: -119 | D18: -451.65 | E18: -204 | F18: -358.65 | G18: -54 | H18: 0 | I18: -492.1 | J18: -65.67 | K18: -122 | L18: -36.33 | M18: -65.74 | N18: -1978.86
A19: Presentes | B19: -19.48 | C19: -188.25 | D19: -322.59 | G19: -574.79 | H19: -17 | I19: -51.09 | K19: -183 | N19: -1356.2
A20: Regularización | B20: 0 | C20: -85 | D20: 0 | G20: 0 | I20: 0 | K20: -61.52 | L20: 0 | M20: 0 | N20: -146.52
A21: Reparaciones | D21: -99 | E21: -32.41 | G21: -4.99 | N21: -136.4
A22: Seguro | B22: -99.48 | C22: -99.48 | D22: -99.48 | E22: -99.48 | F22: -99.48 | G22: -99.48 | H22: -99.48 | I22: 0 | J22: -115.84 | K22: -128.22 | L22: -123.84 | M22: -140.84 | N22: -1205.1
A23: Servicios | B23: -264.99 | C23: -195.1 | D23: -279.95 | E23: -193.08 | F23: -334.68 | G23: -225.74 | H23: -65.36 | I23: -194.12 | J23: -269.06 | K23: -303.98 | L23: -103.88 | M23: -127.84 | N23: -2557.78
A24: Sueldo | B24: 6729.36 | C24: 4595.37 | D24: 10082.66 | E24: 6795.7 | F24: 2295.64 | G24: 6703.9 | H24: 0 | I24: 2204.13 | J24: 6941.25 | K24: 4482.91 | L24: 2295.64 | M24: 6690.96 | N24: 59817.52
A25: Suscripciones | B25: -40.71 | C25: -40.44 | D25: -106.05 | E25: -159.85 | F25: -95.44 | G25: -62.88 | H25: -161.88 | I25: -137.33 | J25: -188.4 | K25: -213.48 | L25: -170.13 | M25: -228.65 | N25: -1605.24
A26: Trabajo | B26: 66.46 | C26: -13 | E26: -10.61 | L26: -15.75 | M26: -1.75 | N26: 25.35
A27: Transporte | B27: -92.8 | C27: -91.72 | D27: -53.2 | E27: -65.4 | F27: -65.63 | G27: -130.8 | H27: 0.09 | I27: -130.8 | J27: -123.86 | K27: -66.9 | L27: -98.1 | M27: -183.49 | N27: -1102.61
A28: Vacaciones | F28: -524.56 | H28: 38.28 | I28: -447.28 | J28: -622.29 | K28: -59.3 | N28: -1615.15
A29: (blank) | M29: -21.12 | N29: -21.12
A30: Grand Total | B30: 4447.6 | C30: 922.17 | D30: 3616.87 | E30: 2547.74 | F30: -956.69 | G30: -274.71 | H30: -2397.02 | I30: -3712.42 | J30: -3876.17 | K30: -290.65 | L30: -1425.12 | M30: 2562.98 | N30: 1164.58

Sheet Data
A1: Cuenta | B1: Fecha Operación | C1: Fecha Operación REAL | D1: Fecha Valor | E1: Fecha valor REAL | F1: Tipo | G1: Concepto | H1: Column1 | I1: Importe | J1: Column2 | K1: Saldo | L1: Tipo de movimiento | M1: Duplicado?
A2: Cristina | B2: 46177 | C2: 46118 | D2: 46177 | E2: 46118 | F2: Alquiler | G2: TRANSFERENCIA A FAVOR DE María Luz Asenjo Sainz De La Maza CONCEPTO: Alquiler | I2: -1250 | K2: 32323.14 | L2: =IF(Gastos[[#This Row],[Importe]]>0,"Ingreso","Egreso") -> Egreso | M2: =IF(AND(COUNTIFS($B$2:$B$3988,B2,$I$2:$I$3988,I2,$K$2:$K$3988,K2)>1,F2=""),"DUPLICADO","Único") -> Único
A3: Cuentas | B3: 46177 | C3: 46118 | D3: 46146 | E3: 46117 | F3: Mercado | G3: Apple pay: COMPRA EN ALCAMPO MORATALAZ, CON LA TARJETA : 5489133208360204 EL 2026-04-05 | I3: -11.91 | K3: 1300.31 | L3: =IF(Gastos[[#This Row],[Importe]]>0,"Ingreso","Egreso") -> Egreso | M3: =IF(AND(COUNTIFS($B$2:$B$3988,B3,$I$2:$I$3988,I3,$K$2:$K$3988,K3)>1,F3=""),"DUPLICADO","Único") -> Único
A4: Cristina | B4: 46177 | C4: 46118 | D4: 46146 | E4: 46117 | F4: Compras | G4: BIZUM A FAVOR DE RICARDO P R CONCEPTO: Ikea | I4: -30.96 | K4: 33573.14 | L4: =IF(Gastos[[#This Row],[Importe]]>0,"Ingreso","Egreso") -> Egreso | M4: =IF(AND(COUNTIFS($B$2:$B$3988,B4,$I$2:$I$3988,I4,$K$2:$K$3988,K4)>1,F4=""),"DUPLICADO","Único") -> Único
A5: Cristina | B5: 46177 | C5: 46118 | D5: 46146 | E5: 46117 | F5: Compras | G5: Apple pay: COMPRA EN ALCAMPO MORATALAZ, CON LA TARJETA : 5489133208122208 EL 2026-04-05 | I5: -33.11 | K5: 33604.1 | L5: =IF(Gastos[[#This Row],[Importe]]>0,"Ingreso","Egreso") -> Egreso | M5: =IF(AND(COUNTIFS($B$2:$B$3988,B5,$I$2:$I$3988,I5,$K$2:$K$3988,K5)>1,F5=""),"DUPLICADO","Único") -> Único
A6: Cuentas | B6: 46177 | C6: 46118 | D6: 46116 | E6: 46116 | F6: Mercado | G6: Apple pay: COMPRA EN MERCADONA GALERIA MORATAL, CON LA TARJETA : 5489133208360204 EL 2026-04-04 | I6: -91.41 | K6: 1312.22 | L6: =IF(Gastos[[#This Row],[Importe]]>0,"Ingreso","Egreso") -> Egreso | M6: =IF(AND(COUNTIFS($B$2:$B$3988,B6,$I$2:$I$3988,I6,$K$2:$K$3988,K6)>1,F6=""),"DUPLICADO","Único") -> Único
A7: Cristina | B7: 46177 | C7: 46118 | D7: 46116 | E7: 46116 | F7: Compras | G7: Apple pay: COMPRA EN HIPER GARDEN, CON LA TARJETA : 5489133208122208 EL 2026-04-04 | I7: -6.4 | K7: 33637.21 | L7: =IF(Gastos[[#This Row],[Importe]]>0,"Ingreso","Egreso") -> Egreso | M7: =IF(AND(COUNTIFS($B$2:$B$3988,B7,$I$2:$I$3988,I7,$K$2:$K$3988,K7)>1,F7=""),"DUPLICADO","Único") -> Único
A8: Cristina | B8: 46177 | C8: 46118 | D8: 46116 | E8: 46116 | F8: Compras | G8: Apple pay: COMPRA EN IKEA GOYA HFB, CON LA TARJETA : 5489133208122208 EL 2026-04-04 | I8: -29.45 | K8: 33643.61 | L8: =IF(Gastos[[#This Row],[Importe]]>0,"Ingreso","Egreso") -> Egreso | M8: =IF(AND(COUNTIFS($B$2:$B$3988,B8,$I$2:$I$3988,I8,$K$2:$K$3988,K8)>1,F8=""),"DUPLICADO","Único") -> Único
A9: Cuentas | B9: 46177 | C9: 46118 | D9: 46085 | E9: 46115 | F9: Mercado | G9: Apple pay: COMPRA EN ALCAMPO MORATALAZ, CON LA TARJETA : 5489133208360204 EL 2026-04-03 | I9: -13.07 | K9: 1403.63 | L9: =IF(Gastos[[#This Row],[Importe]]>0,"Ingreso","Egreso") -> Egreso | M9: =IF(AND(COUNTIFS($B$2:$B$3988,B9,$I$2:$I$3988,I9,$K$2:$K$3988,K9)>1,F9=""),"DUPLICADO","Único") -> Único
A10: Cristina | B10: 46177 | C10: 46118 | D10: 46085 | E10: 46115 | F10: Compras | G10: Apple pay: COMPRA EN MEDIA MARKT VAGUADA, CON LA TARJETA : 5489133208122208 EL 2026-04-03 | I10: -59.9 | K10: 33673.06 | L10: =IF(Gastos[[#This Row],[Importe]]>0,"Ingreso","Egreso") -> Egreso | M10: =IF(AND(COUNTIFS($B$2:$B$3988,B10,$I$2:$I$3988,I10,$K$2:$K$3988,K10)>1,F10=""),"DUPLICADO","Único") -> Único
A11: Cristina | B11: 46177 | C11: 46118 | D11: 46085 | E11: 46115 | F11: Compras | G11: Apple pay: COMPRA EN MEDIA MARKT VAGUADA, CON LA TARJETA : 5489133208122208 EL 2026-04-03 | I11: -718.35 | K11: 33732.96 | L11: =IF(Gastos[[#This Row],[Importe]]>0,"Ingreso","Egreso") -> Egreso | M11: =IF(AND(COUNTIFS($B$2:$B$3988,B11,$I$2:$I$3988,I11,$K$2:$K$3988,K11)>1,F11=""),"DUPLICADO","Único") -> Único
A12: Cristina | B12: 46177 | C12: 46118 | D12: 46085 | E12: 46115 | F12: Compras | G12: Apple pay: COMPRA EN XIN HON COMPLEMENTOS SL, CON LA TARJETA : 5489133208122208 EL 2026-04-03 | I12: -12.6 | K12: 34451.31 | L12: =IF(Gastos[[#This Row],[Importe]]>0,"Ingreso","Egreso") -> Egreso | M12: =IF(AND(COUNTIFS($B$2:$B$3988,B12,$I$2:$I$3988,I12,$K$2:$K$3988,K12)>1,F12=""),"DUPLICADO","Único") -> Único
A13: Cristina | B13: 46177 | C13: 46118 | D13: 46085 | E13: 46115 | F13: Compras | G13: BIZUM A FAVOR DE FATIMA N C CONCEPTO: Cine | I13: -26.7 | K13: 34463.91 | L13: =IF(Gastos[[#This Row],[Importe]]>0,"Ingreso","Egreso") -> Egreso | M13: =IF(AND(COUNTIFS($B$2:$B$3988,B13,$I$2:$I$3988,I13,$K$2:$K$3988,K13)>1,F13=""),"DUPLICADO","Único") -> Único
... A25: Cuentas | B25: 46026 | C25: 46113 | D25: 46026 | E25: 46113 | F25: Seguro | G25: RECIBO SANITAS S A DE SEGUROS Nº RECIBO 0073 0100 755 CPZXLBG REF. MANDATO 800018385362 | I25: -4 | K25: 1680.14 | L25: =IF(Gastos[[#This Row],[Importe]]>0,"Ingreso","Egreso") -> Egreso | M25: =IF(AND(COUNTIFS($B$2:$B$3988,B25,$I$2:$I$3988,I25,$K$2:$K$3988,K25)>1,F25=""),"DUPLICADO","Único") -> Único
A26: Cuentas | B26: 46026 | C26: 46113 | D26: 46026 | E26: 46113 | G26: LIQUIDACION DE LA TARJETA DE CREDITO 0073 0100 500 0529439 | I26: -2.67 | K26: 1684.14 | L26: =IF(Gastos[[#This Row],[Importe]]>0,"Ingreso","Egreso") -> Egreso | M26: =IF(AND(COUNTIFS($B$2:$B$3988,B26,$I$2:$I$3988,I26,$K$2:$K$3988,K26)>1,F26=""),"DUPLICADO","Único") -> Único
A27: Cristina | B27: 46026 | C27: 46113 | D27: 46026 | E27: 46113 | F27: Entretenimiento | G27: TRANSFERENCIA A FAVOR DE N Pérez Pantó & C Paz Rodriguez CONCEPTO: Entretenimiento | I27: -300 | K27: 35087.7 | L27: =IF(Gastos[[#This Row],[Importe]]>0,"Ingreso","Egreso") -> Egreso | M27: =IF(AND(COUNTIFS($B$2:$B$3988,B27,$I$2:$I$3988,I27,$K$2:$K$3988,K27)>1,F27=""),"DUPLICADO","Único") -> Único
A28: Cristina | B28: 46026 | C28: 46113 | D28: 46026 | E28: 46113 | F28: Navidad | G28: TRANSFERENCIA A FAVOR DE Cristina Paz Rodriguez CONCEPTO: Navidad | I28: -126 | K28: 35387.7 | L28: =IF(Gastos[[#This Row],[Importe]]>0,"Ingreso","Egreso") -> Egreso | M28: =IF(AND(COUNTIFS($B$2:$B$3988,B28,$I$2:$I$3988,I28,$K$2:$K$3988,K28)>1,F28=""),"DUPLICADO","Único") -> Único
A29: Nomina | B29: 46026 | C29: 46113 | D29: 46026 | E29: 46113 | F29: Vacaciones | G29: Apple pay: COMPRA EN CASCAIS ALG TVM, CON LA TARJETA : 5489133210353841 EL 2026-03-30 | I29: -11.9 | K29: 2462.97 | L29: =IF(Gastos[[#This Row],[Importe]]>0,"Ingreso","Egreso") -> Egreso | M29: =IF(AND(COUNTIFS($B$2:$B$3988,B29,$I$2:$I$3988,I29,$K$2:$K$3988,K29)>1,F29=""),"DUPLICADO","Único") -> Único
A30: Nomina | B30: 46026 | C30: 46113 | D30: 46026 | E30: 46113 | F30: Vacaciones | G30: Apple pay: COMPRA EN MCDONALDS CASCAIS, CON LA TARJETA : 5489133210353841 EL 2026-03-30 | I30: -20.2 | K30: 2474.87 | L30: =IF(Gastos[[#This Row],[Importe]]>0,"Ingreso","Egreso") -> Egreso | M30: =IF(AND(COUNTIFS($B$2:$B$3988,B30,$I$2:$I$3988,I30,$K$2:$K$3988,K30)>1,F30=""),"DUPLICADO","Único") -> Único
A31: Nomina | B31: 46026 | C31: 46113 | D31: 46026 | E31: 46113 | F31: Vacaciones | G31: Apple pay: COMPRA EN CASCAIS ALG TVM, CON LA TARJETA : 5489133210353841 EL 2026-03-30 | I31: -11.4 | K31: 2495.07 | L31: =IF(Gastos[[#This Row],[Importe]]>0,"Ingreso","Egreso") -> Egreso | M31: =IF(AND(COUNTIFS($B$2:$B$3988,B31,$I$2:$I$3988,I31,$K$2:$K$3988,K31)>1,F31=""),"DUPLICADO","Único") -> Único
A32: Nomina | B32: 46026 | C32: 46113 | D32: 46026 | E32: 46113 | F32: Vacaciones | G32: Apple pay: COMPRA EN CPPB - CASCAIS, CON LA TARJETA : 5489133210353841 EL 2026-03-30 | I32: -12 | K32: 2506.47 | L32: =IF(Gastos[[#This Row],[Importe]]>0,"Ingreso","Egreso") -> Egreso | M32: =IF(AND(COUNTIFS($B$2:$B$3988,B32,$I$2:$I$3988,I32,$K$2:$K$3988,K32)>1,F32=""),"DUPLICADO","Único") -> Único
A33: Nomina | B33: 46026 | C33: 46113 | D33: 46026 | E33: 46113 | F33: Vacaciones | G33: Apple pay: COMPRA EN NAVEGADOR, CON LA TARJETA : 5489133210353841 EL 2026-03-30 | I33: -39 | K33: 2518.47 | L33: =IF(Gastos[[#This Row],[Importe]]>0,"Ingreso","Egreso") -> Egreso | M33: =IF(AND(COUNTIFS($B$2:$B$3988,B33,$I$2:$I$3988,I33,$K$2:$K$3988,K33)>1,F33=""),"DUPLICADO","Único") -> Único
A34: Nomina | B34: 46026 | C34: 46113 | D34: 46026 | E34: 46113 | F34: Vacaciones | G34: Apple pay: COMPRA EN UBER * EATS PENDING, CON LA TARJETA : 5489133210353841 EL 2026-03-29 | I34: -26.59 | K34: 2557.47 | L34: =IF(Gastos[[#This Row],[Importe]]>0,"Ingreso","Egreso") -> Egreso | M34: =IF(AND(COUNTIFS($B$2:$B$3988,B34,$I$2:$I$3988,I34,$K$2:$K$3988,K34)>1,F34=""),"DUPLICADO","Único") -> Único
A35: Nomina | B35: 46026 | C35: 46113 | D35: 46026 | E35: 46113 | F35: Entretenimiento | G35: TRANSFERENCIA A FAVOR DE N Pérez Pantó & C Paz Rodriguez CONCEPTO: Transferencia mensual | I35: -300 | K35: 2584.06 | L35: =IF(Gastos[[#This Row],[Importe]]>0,"Ingreso","Egreso") -> Egreso | M35: =IF(AND(COUNTIFS($B$2:$B$3988,B35,$I$2:$I$3988,I35,$K$2:$K$3988,K35)>1,F35=""),"DUPLICADO","Único") -> Único
A36: Cuentas | B36: 31/03/2026 | C36: 46112 | D36: 31/03/2026 | E36: 46112 | F36: Mercado | G36: Apple pay: COMPRA EN PINGO DOCE CAMPO PEQ, CON LA TARJETA : 5489133208360204 EL 2026-03-29 | I36: -3.08 | K36: 1686.81 | L36: =IF(Gastos[[#This Row],[Importe]]>0,"Ingreso","Egreso") -> Egreso | M36: =IF(AND(COUNTIFS($B$2:$B$3988,B36,$I$2:$I$3988,I36,$K$2:$K$3988,K36)>1,F36=""),"DUPLICADO","Único") -> Único
A37: Cristina | B37: 31/03/2026 | C37: 46112 | D37: 31/03/2026 | E37: 46112 | F37: Alquiler | G37: TRANSFERENCIA INMEDIATA A FAVOR DE Jesús Gonzalez CONCEPTO Alquiler | I37: -811 | K37: 35513.7 | L37: =IF(Gastos[[#This Row],[Importe]]>0,"Ingreso","Egreso") -> Egreso | M37: =IF(AND(COUNTIFS($B$2:$B$3988,B37,$I$2:$I$3988,I37,$K$2:$K$3988,K37)>1,F37=""),"DUPLICADO","Único") -> Único
A38: Cristina | B38: 31/03/2026 | C38: 46112 | D38: 31/03/2026 | E38: 46112 | F38: Compras | G38: Apple pay: COMPRA EN 147-MINIT SPAIN ALC MORAT, CON LA TARJETA : 5489133208122208 EL 2026-03-31 | I38: -4.6 | K38: 36324.7 | L38: =IF(Gastos[[#This Row],[Importe]]>0,"Ingreso","Egreso") -> Egreso | M38: =IF(AND(COUNTIFS($B$2:$B$3988,B38,$I$2:$I$3988,I38,$K$2:$K$3988,K38)>1,F38=""),"DUPLICADO","Único") -> Único
A39: Cristina | B39: 31/03/2026 | C39: 46112 | D39: 31/03/2026 | E39: 46112 | F39: Mercado | G39: Apple pay: COMPRA EN ALCAMPO MORATALAZ, CON LA TARJETA : 5489133208122208 EL 2026-03-31 | I39: -7.56 | K39: 36329.3 | L39: =IF(Gastos[[#This Row],[Importe]]>0,"Ingreso","Egreso") -> Egreso | M39: =IF(AND(COUNTIFS($B$2:$B$3988,B39,$I$2:$I$3988,I39,$K$2:$K$3988,K39)>1,F39=""),"DUPLICADO","Único") -> Único
A40: Cristina | B40: 31/03/2026 | C40: 46112 | D40: 31/03/2026 | E40: 46112 | F40: Sueldo | G40: TRANSFERENCIA DE Currie Brown Iberia SLU, CONCEPTO Marzo Nomina | I40: 2304.31 | K40: 36336.86 | L40: =IF(Gastos[[#This Row],[Importe]]>0,"Ingreso","Egreso") -> Ingreso | M40: =IF(AND(COUNTIFS($B$2:$B$3988,B40,$I$2:$I$3988,I40,$K$2:$K$3988,K40)>1,F40=""),"DUPLICADO","Único") -> Único
A41: Nomina | B41: 31/03/2026 | C41: 46112 | D41: 31/03/2026 | E41: 46112 | F41: Sueldo | G41: TRANSFERENCIA INMEDIATA DE E KABEL ESPANA S.L. CONCEPTO pago nomina NP marzo 2026 pag | I41: 2295.03 | K41: 2884.06 | L41: =IF(Gastos[[#This Row],[Importe]]>0,"Ingreso","Egreso") -> Ingreso | M41: =IF(AND(COUNTIFS($B$2:$B$3988,B41,$I$2:$I$3988,I41,$K$2:$K$3988,K41)>1,F41=""),"DUPLICADO","Único") -> Único
A42: Nomina | B42: 31/03/2026 | C42: 46112 | D42: 31/03/2026 | E42: 46112 | F42: Vacaciones | G42: Apple pay: COMPRA EN MEDITERRANEO C PEQ, CON LA TARJETA : 5489133210353841 EL 2026-03-29 | I42: -19.9 | K42: 589.03 | L42: =IF(Gastos[[#This Row],[Importe]]>0,"Ingreso","Egreso") -> Egreso | M42: =IF(AND(COUNTIFS($B$2:$B$3988,B42,$I$2:$I$3988,I42,$K$2:$K$3988,K42)>1,F42=""),"DUPLICADO","Único") -> Único
A43: Nomina | B43: 31/03/2026 | C43: 46112 | D43: 31/03/2026 | E43: 46112 | F43: Compras | G43: Apple pay: COMPRA EN NORMAL LISBOA, CON LA TARJETA : 5489133210353841 EL 2026-03-29 | I43: -2.9 | K43: 608.93 | L43: =IF(Gastos[[#This Row],[Importe]]>0,"Ingreso","Egreso") -> Egreso | M43: =IF(AND(COUNTIFS($B$2:$B$3988,B43,$I$2:$I$3988,I43,$K$2:$K$3988,K43)>1,F43=""),"DUPLICADO","Único") -> Único
A44: Nomina | B44: 31/03/2026 | C44: 46112 | D44: 31/03/2026 | E44: 46112 | F44: Vacaciones | G44: Apple pay: COMPRA EN CD R.C.SANCHES II, CON LA TARJETA : 5489133210353841 EL 2026-03-29 | I44: -7.85 | K44: 611.83 | L44: =IF(Gastos[[#This Row],[Importe]]>0,"Ingreso","Egreso") -> Egreso | M44: =IF(AND(COUNTIFS($B$2:$B$3988,B44,$I$2:$I$3988,I44,$K$2:$K$3988,K44)>1,F44=""),"DUPLICADO","Único") -> Único
A45: Nomina | B45: 31/03/2026 | C45: 46112 | D45: 31/03/2026 | E45: 46112 | F45: Suscripciones | G45: Apple pay: COMPRA EN APPLE.COM/BILL, CON LA TARJETA : 5489133210353841 EL 2026-03-29 | I45: -22 | K45: 619.68 | L45: =IF(Gastos[[#This Row],[Importe]]>0,"Ingreso","Egreso") -> Egreso | M45: =IF(AND(COUNTIFS($B$2:$B$3988,B45,$I$2:$I$3988,I45,$K$2:$K$3988,K45)>1,F45=""),"DUPLICADO","Único") -> Único
A46: Nomina | B46: 31/03/2026 | C46: 46112 | D46: 31/03/2026 | E46: 46112 | F46: Vacaciones | G46: Apple pay: COMPRA EN AEROPORTO, CON LA TARJETA : 5489133210353841 EL 2026-03-29 | I46: -15.5 | K46: 641.68 | L46: =IF(Gastos[[#This Row],[Importe]]>0,"Ingreso","Egreso") -> Egreso | M46: =IF(AND(COUNTIFS($B$2:$B$3988,B46,$I$2:$I$3988,I46,$K$2:$K$3988,K46)>1,F46=""),"DUPLICADO","Único") -> Único
A47: Nomina | B47: 31/03/2026 | C47: 46112 | D47: 31/03/2026 | E47: 46112 | F47: Inversión | G47: TRANSFERENCIA A FAVOR DE IBKR CONCEPTO: U6384508 / NICOLAS D Perez | I47: -400 | K47: 657.18 | L47: =IF(Gastos[[#This Row],[Importe]]>0,"Ingreso","Egreso") -> Egreso | M47: =IF(AND(COUNTIFS($B$2:$B$3988,B47,$I$2:$I$3988,I47,$K$2:$K$3988,K47)>1,F47=""),"DUPLICADO","Único") -> Único
... A63: Cuentas | B63: 26/03/2026 | C63: 46107 | D63: 26/03/2026 | E63: 46107 | F63: Servicios | G63: RECIBO TotalEnergies ClientesSAU Nº RECIBO 0073 0100 755 CPZMQMX REF. MANDATO NCESIGS241020230000000 | I63: -100.47 | K63: 1485.03 | L63: =IF(Gastos[[#This Row],[Importe]]>0,"Ingreso","Egreso") -> Egreso | M63: =IF(AND(COUNTIFS($B$2:$B$3988,B63,$I$2:$I$3988,I63,$K$2:$K$3988,K63)>1,F63=""),"DUPLICADO","Único") -> Único
A64: Cristina | B64: 26/03/2026 | C64: 46107 | D64: 26/03/2026 | E64: 46107 | G64: Apple pay: COMPRA EN 147-MINIT SPAIN ALC MORAT, CON LA TARJETA : 5489133208122208 EL 2026-03-26 | I64: -25.9 | K64: 35193.57 | L64: =IF(Gastos[[#This Row],[Importe]]>0,"Ingreso","Egreso") -> Egreso | M64: =IF(AND(COUNTIFS($B$2:$B$3988,B64,$I$2:$I$3988,I64,$K$2:$K$3988,K64)>1,F64=""),"DUPLICADO","Único") -> Único
A65: Cristina | B65: 26/03/2026 | C65: 46107 | D65: 26/03/2026 | E65: 46107 | F65: Alquiler | G65: TRANSFERENCIA INMEDIATA A FAVOR DE María Luz Asenjo Sainz De La Maza CONCEPTO Fianza+mes en curso | I65: -1500 | K65: 35219.47 | L65: =IF(Gastos[[#This Row],[Importe]]>0,"Ingreso","Egreso") -> Egreso | M65: =IF(AND(COUNTIFS($B$2:$B$3988,B65,$I$2:$I$3988,I65,$K$2:$K$3988,K65)>1,F65=""),"DUPLICADO","Único") -> Único
A66: Cuentas | B66: 25/03/2026 | C66: 46106 | D66: 25/03/2026 | E66: 46106 | F66: Servicios | G66: RECIBO ORANGE ESPAGNE S.A. Nº RECIBO 0073 0100 755 CPZFHBT REF. MANDATO OSP202308KENAN02276921506 | I66: -90.87 | K66: 1585.5 | L66: =IF(Gastos[[#This Row],[Importe]]>0,"Ingreso","Egreso") -> Egreso | M66: =IF(AND(COUNTIFS($B$2:$B$3988,B66,$I$2:$I$3988,I66,$K$2:$K$3988,K66)>1,F66=""),"DUPLICADO","Único") -> Único
A67: Cristina | B67: 25/03/2026 | C67: 46106 | D67: 25/03/2026 | E67: 46106 | F67: Compras | G67: Apple pay: COMPRA EN FARMACIA GOYA, CON LA TARJETA : 5489133208122208 EL 2026-03-25 | I67: -5.45 | K67: 36719.47 | L67: =IF(Gastos[[#This Row],[Importe]]>0,"Ingreso","Egreso") -> Egreso | M67: =IF(AND(COUNTIFS($B$2:$B$3988,B67,$I$2:$I$3988,I67,$K$2:$K$3988,K67)>1,F67=""),"DUPLICADO","Único") -> Único
A68: Cristina | B68: 25/03/2026 | C68: 46106 | D68: 25/03/2026 | E68: 46106 | F68: Compras | G68: Apple pay: COMPRA EN PRIMOR GOYA, CON LA TARJETA : 5489133208122208 EL 2026-03-25 | I68: -3.49 | K68: 36724.92 | L68: =IF(Gastos[[#This Row],[Importe]]>0,"Ingreso","Egreso") -> Egreso | M68: =IF(AND(COUNTIFS($B$2:$B$3988,B68,$I$2:$I$3988,I68,$K$2:$K$3988,K68)>1,F68=""),"DUPLICADO","Único") -> Único
A69: Cristina | B69: 24/03/2026 | C69: 46105 | D69: 24/03/2026 | E69: 46105 | F69: Herencia | G69: TRANSFERENCIA DE RODRIGUES ALVES JENNY, CONCEPTO Transferencia Cristina | I69: 29500 | K69: 36728.41 | L69: =IF(Gastos[[#This Row],[Importe]]>0,"Ingreso","Egreso") -> Ingreso | M69: =IF(AND(COUNTIFS($B$2:$B$3988,B69,$I$2:$I$3988,I69,$K$2:$K$3988,K69)>1,F69=""),"DUPLICADO","Único") -> Único
A70: Cristina | B70: 24/03/2026 | C70: 46105 | D70: 24/03/2026 | E70: 46105 | F70: Presentes | G70: Apple pay: COMPRA EN KIKO MILANO, CON LA TARJETA : 5489133208122208 EL 2026-03-22 | I70: -39.13 | K70: 7228.41 | L70: =IF(Gastos[[#This Row],[Importe]]>0,"Ingreso","Egreso") -> Egreso | M70: =IF(AND(COUNTIFS($B$2:$B$3988,B70,$I$2:$I$3988,I70,$K$2:$K$3988,K70)>1,F70=""),"DUPLICADO","Único") -> Único
A71: Cristina | B71: 24/03/2026 | C71: 46105 | D71: 24/03/2026 | E71: 46105 | F71: Entretenimiento | G71: Apple pay: COMPRA EN EXPZURBANOII, CON LA TARJETA : 5489133208122208 EL 2026-03-24 | I71: -5.24 | K71: 7267.54 | L71: =IF(Gastos[[#This Row],[Importe]]>0,"Ingreso","Egreso") -> Egreso | M71: =IF(AND(COUNTIFS($B$2:$B$3988,B71,$I$2:$I$3988,I71,$K$2:$K$3988,K71)>1,F71=""),"DUPLICADO","Único") -> Único
A72: Nomina | B72: 24/03/2026 | C72: 46105 | D72: 24/03/2026 | E72: 46105 | F72: Presentes | G72: TRANSFERENCIA INMEDIATA A FAVOR DE Johana Poveda | I72: -10 | K72: 1113.34 | L72: =IF(Gastos[[#This Row],[Importe]]>0,"Ingreso","Egreso") -> Egreso | M72: =IF(AND(COUNTIFS($B$2:$B$3988,B72,$I$2:$I$3988,I72,$K$2:$K$3988,K72)>1,F72=""),"DUPLICADO","Único") -> Único
A73: Nomina | B73: 24/03/2026 | C73: 46105 | D73: 24/03/2026 | E73: 46105 | F73: Inversión | G73: TRANSFERENCIA A FAVOR DE IBKR CONCEPTO: Inversiones Hermana e Hij | I73: -300 | K73: 1123.34 | L73: =IF(Gastos[[#This Row],[Importe]]>0,"Ingreso","Egreso") -> Egreso | M73: =IF(AND(COUNTIFS($B$2:$B$3988,B73,$I$2:$I$3988,I73,$K$2:$K$3988,K73)>1,F73=""),"DUPLICADO","Único") -> Único
A74: Cuentas | B74: 23/03/2026 | C74: 46104 | D74: 23/03/2026 | E74: 46104 | F74: Mercado | G74: Apple pay: COMPRA EN MERCADONA MANUEL MACHADO, CON LA TARJETA : 5489133208360204 EL 2026-03-23 | I74: -2 | K74: 1676.37 | L74: =IF(Gastos[[#This Row],[Importe]]>0,"Ingreso","Egreso") -> Egreso | M74: =IF(AND(COUNTIFS($B$2:$B$3988,B74,$I$2:$I$3988,I74,$K$2:$K$3988,K74)>1,F74=""),"DUPLICADO","Único") -> Único
A75: Nomina | B75: 23/03/2026 | C75: 46104 | D75: 23/03/2026 | E75: 46104 | G75: Apple pay: COMPRA EN MAR MORA, CON LA TARJETA : 5489133210353841 EL 2026-03-23 | I75: -13.27 | K75: 1423.34 | L75: =IF(Gastos[[#This Row],[Importe]]>0,"Ingreso","Egreso") -> Egreso | M75: =IF(AND(COUNTIFS($B$2:$B$3988,B75,$I$2:$I$3988,I75,$K$2:$K$3988,K75)>1,F75=""),"DUPLICADO","Único") -> Único
A76: Cristina | B76: 23/03/2026 | C76: 46104 | D76: 21/03/2026 | E76: 46102 | F76: Mercado | G76: COMPRA EN MERCADONA ONLINE, CON LA TARJETA : 5489133208122208 EL 2026-03-21 | I76: -87.99 | K76: 7272.78 | L76: =IF(Gastos[[#This Row],[Importe]]>0,"Ingreso","Egreso") -> Egreso | M76: =IF(AND(COUNTIFS($B$2:$B$3988,B76,$I$2:$I$3988,I76,$K$2:$K$3988,K76)>1,F76=""),"DUPLICADO","Único") -> Único
A77: Cristina | B77: 20/03/2026 | C77: 46101 | D77: 20/03/2026 | E77: 46101 | G77: Apple pay: COMPRA EN MJ MU¥OZ, CON LA TARJETA : 5489133208122208 EL 2026-03-20 | I77: -12.1 | K77: 7360.77 | L77: =IF(Gastos[[#This Row],[Importe]]>0,"Ingreso","Egreso") -> Egreso | M77: =IF(AND(COUNTIFS($B$2:$B$3988,B77,$I$2:$I$3988,I77,$K$2:$K$3988,K77)>1,F77=""),"DUPLICADO","Único") -> Único
A78: Cuentas | B78: 19/03/2026 | C78: 46100 | D78: 19/03/2026 | E78: 46100 | F78: Mercado | G78: Apple pay: COMPRA EN ALCAMPO MORATALAZ, CON LA TARJETA : 5489133208360204 EL 2026-03-19 | I78: -29.03 | K78: 1678.37 | L78: =IF(Gastos[[#This Row],[Importe]]>0,"Ingreso","Egreso") -> Egreso | M78: =IF(AND(COUNTIFS($B$2:$B$3988,B78,$I$2:$I$3988,I78,$K$2:$K$3988,K78)>1,F78=""),"DUPLICADO","Único") -> Único
A79: Cuentas | B79: 19/03/2026 | C79: 46100 | D79: 19/03/2026 | E79: 46100 | F79: Mercado | G79: Apple pay: COMPRA EN MERCADONA MANUEL MACHADO, CON LA TARJETA : 5489133208360204 EL 2026-03-19 | I79: -4.1 | K79: 1707.4 | L79: =IF(Gastos[[#This Row],[Importe]]>0,"Ingreso","Egreso") -> Egreso | M79: =IF(AND(COUNTIFS($B$2:$B$3988,B79,$I$2:$I$3988,I79,$K$2:$K$3988,K79)>1,F79=""),"DUPLICADO","Único") -> Único
A80: Cristina | B80: 17/03/2026 | C80: 46098 | D80: 17/03/2026 | E80: 46098 | G80: Apple pay: COMPRA EN Revolut**6890*, CON LA TARJETA : 5489133208122208 EL 2026-03-15 | I80: -126 | K80: 7372.87 | L80: =IF(Gastos[[#This Row],[Importe]]>0,"Ingreso","Egreso") -> Egreso | M80: =IF(AND(COUNTIFS($B$2:$B$3988,B80,$I$2:$I$3988,I80,$K$2:$K$3988,K80)>1,F80=""),"DUPLICADO","Único") -> Único
A81: Cristina | B81: 17/03/2026 | C81: 46098 | D81: 17/03/2026 | E81: 46098 | G81: Apple pay: COMPRA EN LM FERNANDO EL SANTO MADR, CON LA TARJETA : 5489133208122208 EL 2026-03-17 | I81: -2.25 | K81: 7498.87 | L81: =IF(Gastos[[#This Row],[Importe]]>0,"Ingreso","Egreso") -> Egreso | M81: =IF(AND(COUNTIFS($B$2:$B$3988,B81,$I$2:$I$3988,I81,$K$2:$K$3988,K81)>1,F81=""),"DUPLICADO","Único") -> Único
A82: Cuentas | B82: 16/03/2026 | C82: 46097 | D82: 16/03/2026 | E82: 46097 | F82: Suscripciones | G82: COMPRA EN APPLE.COM/BILL, CON LA TARJETA : 5489133208360204 EL 2026-03-13 | I82: -16.99 | K82: 1711.5 | L82: =IF(Gastos[[#This Row],[Importe]]>0,"Ingreso","Egreso") -> Egreso | M82: =IF(AND(COUNTIFS($B$2:$B$3988,B82,$I$2:$I$3988,I82,$K$2:$K$3988,K82)>1,F82=""),"DUPLICADO","Único") -> Único
A83: Cuentas | B83: 16/03/2026 | C83: 46097 | D83: 16/03/2026 | E83: 46097 | F83: Suscripciones | G83: COMPRA EN APPLE.COM/BILL, CON LA TARJETA : 5489133208360204 EL 2026-03-13 | I83: -2.99 | K83: 1728.49 | L83: =IF(Gastos[[#This Row],[Importe]]>0,"Ingreso","Egreso") -> Egreso | M83: =IF(AND(COUNTIFS($B$2:$B$3988,B83,$I$2:$I$3988,I83,$K$2:$K$3988,K83)>1,F83=""),"DUPLICADO","Único") -> Único
A84: Cuentas | B84: 16/03/2026 | C84: 46097 | D84: 16/03/2026 | E84: 46097 | F84: Regularización | G84: TRANSFERENCIA DE PEREZ PANTO NICOLAS, CONCEPTO Traspaso - Regularización | I84: 1500 | K84: 1739.67 | L84: =IF(Gastos[[#This Row],[Importe]]>0,"Ingreso","Egreso") -> Ingreso | M84: =IF(AND(COUNTIFS($B$2:$B$3988,B84,$I$2:$I$3988,I84,$K$2:$K$3988,K84)>1,F84=""),"DUPLICADO","Único") -> Único
A85: Nomina | B85: 16/03/2026 | C85: 46097 | D85: 16/03/2026 | E85: 46097 | G85: RECIBO IBERIA CARDS Nº RECIBO 0073 0100 755 CPXRNDZ REF. MANDATO 000010295927 | I85: -112.76 | K85: 1436.61 | L85: =IF(Gastos[[#This Row],[Importe]]>0,"Ingreso","Egreso") -> Egreso | M85: =IF(AND(COUNTIFS($B$2:$B$3988,B85,$I$2:$I$3988,I85,$K$2:$K$3988,K85)>1,F85=""),"DUPLICADO","Único") -> Único
A86: Nomina | B86: 16/03/2026 | C86: 46097 | D86: 16/03/2026 | E86: 46097 | F86: Regularización | G86: TRANSFERENCIA A FAVOR DE PEREZ PANTO NICOLAS CONCEPTO: Traspaso - Regularización | I86: -1500 | K86: 1549.37 | L86: =IF(Gastos[[#This Row],[Importe]]>0,"Ingreso","Egreso") -> Egreso | M86: =IF(AND(COUNTIFS($B$2:$B$3988,B86,$I$2:$I$3988,I86,$K$2:$K$3988,K86)>1,F86=""),"DUPLICADO","Único") -> Único
A87: Cuentas | B87: 16/03/2026 | C87: 46097 | D87: 15/03/2026 | E87: 46096 | F87: Mercado | G87: Apple pay: COMPRA EN ALCAMPO MORATALAZ, CON LA TARJETA : 5489133208360204 EL 2026-03-15 | I87: -8.19 | K87: 1731.48 | L87: =IF(Gastos[[#This Row],[Importe]]>0,"Ingreso","Egreso") -> Egreso | M87: =IF(AND(COUNTIFS($B$2:$B$3988,B87,$I$2:$I$3988,I87,$K$2:$K$3988,K87)>1,F87=""),"DUPLICADO","Único") -> Único
A88: Cristina | B88: 16/03/2026 | C88: 46097 | D88: 15/03/2026 | E88: 46096 | F88: Mercado | G88: BIZUM A FAVOR DE FATIMA N C CONCEPTO: Sin concepto | I88: -23.99 | K88: 7501.12 | L88: =IF(Gastos[[#This Row],[Importe]]>0,"Ingreso","Egreso") -> Egreso | M88: =IF(AND(COUNTIFS($B$2:$B$3988,B88,$I$2:$I$3988,I88,$K$2:$K$3988,K88)>1,F88=""),"DUPLICADO","Único") -> Único
A89: Cuentas | B89: 16/03/2026 | C89: 46097 | D89: 14/03/2026 | E89: 46095 | F89: Mercado | G89: Apple pay: COMPRA EN MERCADONA MANUEL MACHADO, CON LA TARJETA : 5489133208360204 EL 2026-03-14 | I89: -93 | K89: 239.67 | L89: =IF(Gastos[[#This Row],[Importe]]>0,"Ingreso","Egreso") -> Egreso | M89: =IF(AND(COUNTIFS($B$2:$B$3988,B89,$I$2:$I$3988,I89,$K$2:$K$3988,K89)>1,F89=""),"DUPLICADO","Único") -> Único
A90: Nomina | B90: 46094 | C90: 46094 | D90: 46094 | E90: 46094 | F90: Entretenimiento | G90: COMPRA EN SSR CASTELLO-GOYA., CON LA TARJETA : 5489133210353841 EL 2026-03-13 | I90: -6.49 | K90: 3049.37 | L90: =IF(Gastos[[#This Row],[Importe]]>0,"Ingreso","Egreso") -> Egreso | M90: =IF(AND(COUNTIFS($B$2:$B$3988,B90,$I$2:$I$3988,I90,$K$2:$K$3988,K90)>1,F90=""),"DUPLICADO","Único") -> Único
A91: Cristina | B91: 46094 | C91: 46094 | D91: 46094 | E91: 46094 | F91: Entretenimiento | G91: Apple pay: COMPRA EN MCDONALDS GOYA, CON LA TARJETA : 5489133208122208 EL 2026-03-13 | I91: -5.65 | K91: 7525.11 | L91: =IF(Gastos[[#This Row],[Importe]]>0,"Ingreso","Egreso") -> Egreso | M91: =IF(AND(COUNTIFS($B$2:$B$3988,B91,$I$2:$I$3988,I91,$K$2:$K$3988,K91)>1,F91=""),"DUPLICADO","Único") -> Único
A92: Cristina | B92: 46094 | C92: 46094 | D92: 46094 | E92: 46094 | F92: Compras | G92: Apple pay: COMPRA EN PRIMAPRIX HERMOSILLA, CON LA TARJETA : 5489133208122208 EL 2026-03-13 | I92: -2.6 | K92: 7530.76 | L92: =IF(Gastos[[#This Row],[Importe]]>0,"Ingreso","Egreso") -> Egreso | M92: =IF(AND(COUNTIFS($B$2:$B$3988,B92,$I$2:$I$3988,I92,$K$2:$K$3988,K92)>1,F92=""),"DUPLICADO","Único") -> Único
A93: Cuentas | B93: 46094 | C93: 46094 | D93: 46094 | E93: 46094 | F93: Mercado | G93: Apple pay: COMPRA EN EXPZURBANOII, CON LA TARJETA : 5489133208360204 EL 2026-03-13 | I93: -4.79 | K93: 332.67 | L93: =IF(Gastos[[#This Row],[Importe]]>0,"Ingreso","Egreso") -> Egreso | M93: =IF(AND(COUNTIFS($B$2:$B$3988,B93,$I$2:$I$3988,I93,$K$2:$K$3988,K93)>1,F93=""),"DUPLICADO","Único") -> Único
A94: Cuentas | B94: 13/03/2026 | C94: 46094 | D94: 13/03/2026 | E94: 46094 | F94: Mercado | G94: Apple pay: COMPRA EN EXPZURBANOII, CON LA TARJETA : 5489133208360204 EL 2026-03-13 | I94: -4.79 | K94: 332.67 | L94: =IF(Gastos[[#This Row],[Importe]]>0,"Ingreso","Egreso") -> Egreso | M94: =IF(AND(COUNTIFS($B$2:$B$3988,B94,$I$2:$I$3988,I94,$K$2:$K$3988,K94)>1,F94=""),"DUPLICADO","Único") -> Único
A95: Cristina | B95: 13/03/2026 | C95: 46094 | D95: 13/03/2026 | E95: 46094 | F95: Entretenimiento | G95: Apple pay: COMPRA EN MCDONALDS GOYA, CON LA TARJETA : 5489133208122208 EL 2026-03-13 | I95: -5.65 | K95: 7525.11 | L95: =IF(Gastos[[#This Row],[Importe]]>0,"Ingreso","Egreso") -> Egreso | M95: =IF(AND(COUNTIFS($B$2:$B$3988,B95,$I$2:$I$3988,I95,$K$2:$K$3988,K95)>1,F95=""),"DUPLICADO","Único") -> Único
A96: Cristina | B96: 13/03/2026 | C96: 46094 | D96: 13/03/2026 | E96: 46094 | F96: Entretenimiento | G96: Apple pay: COMPRA EN PRIMAPRIX HERMOSILLA, CON LA TARJETA : 5489133208122208 EL 2026-03-13 | I96: -2.6 | K96: 7530.76 | L96: =IF(Gastos[[#This Row],[Importe]]>0,"Ingreso","Egreso") -> Egreso | M96: =IF(AND(COUNTIFS($B$2:$B$3988,B96,$I$2:$I$3988,I96,$K$2:$K$3988,K96)>1,F96=""),"DUPLICADO","Único") -> Único
A97: Nomina | B97: 13/03/2026 | C97: 46094 | D97: 13/03/2026 | E97: 46094 | F97: Mercado | G97: COMPRA EN SSR CASTELLO-GOYA., CON LA TARJETA : 5489133210353841 EL 2026-03-13 | I97: -6.49 | K97: 3049.37 | L97: =IF(Gastos[[#This Row],[Importe]]>0,"Ingreso","Egreso") -> Egreso | M97: =IF(AND(COUNTIFS($B$2:$B$3988,B97,$I$2:$I$3988,I97,$K$2:$K$3988,K97)>1,F97=""),"DUPLICADO","Único") -> Único
A98: Cristina | B98: 46359 | C98: 46093 | D98: 46359 | E98: 46093 | F98: Mercado | G98: COMPRA EN SSR CASTELLO-GOYA., CON LA TARJETA : 5489133208122208 EL 2026-03-12 | I98: -3.15 | K98: 7533.36 | L98: =IF(Gastos[[#This Row],[Importe]]>0,"Ingreso","Egreso") -> Egreso | M98: =IF(AND(COUNTIFS($B$2:$B$3988,B98,$I$2:$I$3988,I98,$K$2:$K$3988,K98)>1,F98=""),"DUPLICADO","Único") -> Único
A99: Nomina | B99: 46329 | C99: 46092 | D99: 46329 | E99: 46092 | F99: Reparaciones | G99: COMPRA EN WWW.AMAZON* N56I397K5, CON LA TARJETA : 5489133210353841 EL 2026-03-09 | I99: -13.99 | K99: 3045.91 | L99: =IF(Gastos[[#This Row],[Importe]]>0,"Ingreso","Egreso") -> Egreso | M99: =IF(AND(COUNTIFS($B$2:$B$3988,B99,$I$2:$I$3988,I99,$K$2:$K$3988,K99)>1,F99=""),"DUPLICADO","Único") -> Único
A100: Cristina | B100: 46329 | C100: 46092 | D100: 46329 | E100: 46092 | F100: Transporte | G100: BIZUM DE BEATRIZ V C CONCEPTO Sin concepto | I100: 8 | K100: 7536.51 | L100: =IF(Gastos[[#This Row],[Importe]]>0,"Ingreso","Egreso") -> Ingreso | M100: =IF(AND(COUNTIFS($B$2:$B$3988,B100,$I$2:$I$3988,I100,$K$2:$K$3988,K100)>1,F100=""),"DUPLICADO","Único") -> Único
A101: Cristina | B101: 46329 | C101: 46092 | D101: 46329 | E101: 46092 | F101: Mercado | G101: Apple pay: COMPRA EN LM FERNANDO EL SANTO MADR, CON LA TARJETA : 5489133208122208 EL 2026-03-11 | I101: -3 | K101: 7528.51 | L101: =IF(Gastos[[#This Row],[Importe]]>0,"Ingreso","Egreso") -> Egreso | M101: =IF(AND(COUNTIFS($B$2:$B$3988,B101,$I$2:$I$3988,I101,$K$2:$K$3988,K101)>1,F101=""),"DUPLICADO","Único") -> Único
A102: Nomina | B102: 46359 | C102: 46093 | D102: 46298 | E102: 46091 | F102: Compras | G102: ABONO EN LA TARJETA 5489133210353841 EL 2026-03-10 | I102: 9.95 | K102: 3055.86 | L102: =IF(Gastos[[#This Row],[Importe]]>0,"Ingreso","Egreso") -> Ingreso | M102: =IF(AND(COUNTIFS($B$2:$B$3988,B102,$I$2:$I$3988,I102,$K$2:$K$3988,K102)>1,F102=""),"DUPLICADO","Único") -> Único
A103: Nomina | B103: 46298 | C103: 46091 | D103: 46298 | E103: 46091 | F103: Entretenimiento | G103: Apple pay: COMPRA EN Revolut**8197*, CON LA TARJETA : 5489133210353841 EL 2026-03-08 | I103: -300 | K103: 3059.9 | L103: =IF(Gastos[[#This Row],[Importe]]>0,"Ingreso","Egreso") -> Egreso | M103: =IF(AND(COUNTIFS($B$2:$B$3988,B103,$I$2:$I$3988,I103,$K$2:$K$3988,K103)>1,F103=""),"DUPLICADO","Único") -> Único
A104: Cristina | B104: 46298 | C104: 46091 | D104: 46298 | E104: 46091 | F104: Entretenimiento | G104: Apple pay: COMPRA EN Revolut**6890*, CON LA TARJETA : 5489133208122208 EL 2026-03-08 | I104: -300 | K104: 7531.51 | L104: =IF(Gastos[[#This Row],[Importe]]>0,"Ingreso","Egreso") -> Egreso | M104: =IF(AND(COUNTIFS($B$2:$B$3988,B104,$I$2:$I$3988,I104,$K$2:$K$3988,K104)>1,F104=""),"DUPLICADO","Único") -> Único
A105: Cristina | B105: 46268 | C105: 46090 | D105: 46268 | E105: 46090 | F105: Mercado | G105: COMPRA EN SSR CASTELLO-GOYA., CON LA TARJETA : 5489133208122208 EL 2026-03-09 | I105: -3.31 | K105: 7831.51 | L105: =IF(Gastos[[#This Row],[Importe]]>0,"Ingreso","Egreso") -> Egreso | M105: =IF(AND(COUNTIFS($B$2:$B$3988,B105,$I$2:$I$3988,I105,$K$2:$K$3988,K105)>1,F105=""),"DUPLICADO","Único") -> Único
A106: Nomina | B106: 46268 | C106: 46090 | D106: 46237 | E106: 46089 | F106: Padres | G106: LIQUIDACION PERIODICA PRESTAMO 1781471 143 | I106: -81.89 | K106: 3359.9 | L106: =IF(Gastos[[#This Row],[Importe]]>0,"Ingreso","Egreso") -> Egreso | M106: =IF(AND(COUNTIFS($B$2:$B$3988,B106,$I$2:$I$3988,I106,$K$2:$K$3988,K106)>1,F106=""),"DUPLICADO","Único") -> Único
A107: Cristina | B107: 46268 | C107: 46090 | D107: 46206 | E107: 46088 | F107: Presentes | G107: COMPRA EN SFERA GOYA, CON LA TARJETA : 5489133208122208 EL 2026-03-07 | I107: -23.99 | K107: 7867.81 | L107: =IF(Gastos[[#This Row],[Importe]]>0,"Ingreso","Egreso") -> Egreso | M107: =IF(AND(COUNTIFS($B$2:$B$3988,B107,$I$2:$I$3988,I107,$K$2:$K$3988,K107)>1,F107=""),"DUPLICADO","Único") -> Único
A108: Cristina | B108: 46268 | C108: 46090 | D108: 46206 | E108: 46088 | F108: Mercado | G108: COMPRA EN MERCADONA COLMENA GETAFE, CON LA TARJETA : 5489133208122208 EL 2026-03-07 | I108: -95.45 | K108: 7891.8 | L108: =IF(Gastos[[#This Row],[Importe]]>0,"Ingreso","Egreso") -> Egreso | M108: =IF(AND(COUNTIFS($B$2:$B$3988,B108,$I$2:$I$3988,I108,$K$2:$K$3988,K108)>1,F108=""),"DUPLICADO","Único") -> Único
A109: Cuentas | B109: 46268 | C109: 46090 | D109: 46206 | E109: 46088 | F109: Transporte | G109: REGULARIZACION COMPRA EN APP CRTM, CON LA TARJETA : 5489133208360204 EL 2026-03-07 | I109: 32.7 | K109: 337.46 | L109: =IF(Gastos[[#This Row],[Importe]]>0,"Ingreso","Egreso") -> Ingreso | M109: =IF(AND(COUNTIFS($B$2:$B$3988,B109,$I$2:$I$3988,I109,$K$2:$K$3988,K109)>1,F109=""),"DUPLICADO","Único") -> Único
... A116: Cuentas | B116: 46145 | C116: 46086 | D116: 46145 | E116: 46086 | F116: Servicios | G116: RECIBO Naturgy Clientes, S.A.U. Nº RECIBO 0073 0100 755 CPVLFRX REF. MANDATO 000000259696 | I116: -54.45 | K116: 392.14 | L116: =IF(Gastos[[#This Row],[Importe]]>0,"Ingreso","Egreso") -> Egreso | M116: =IF(AND(COUNTIFS($B$2:$B$3988,B116,$I$2:$I$3988,I116,$K$2:$K$3988,K116)>1,F116=""),"DUPLICADO","Único") -> Único
A117: Cristina | B117: 46115 | C117: 46085 | D117: 46115 | E117: 46085 | G117: Apple pay: COMPRA EN LM FERNANDO EL SANTO MADR, CON LA TARJETA : 5489133208122208 EL 2026-03-04 | I117: -3 | K117: 7994.83 | L117: =IF(Gastos[[#This Row],[Importe]]>0,"Ingreso","Egreso") -> Egreso | M117: =IF(AND(COUNTIFS($B$2:$B$3988,B117,$I$2:$I$3988,I117,$K$2:$K$3988,K117)>1,F117=""),"DUPLICADO","Único") -> Único
A118: Nomina | B118: 46145 | C118: 46086 | D118: 46084 | E118: 46084 | F118: Compras | G118: ABONO EN LA TARJETA 5489133210353841 EL 2026-03-03 | I118: 8.25 | K118: 3441.79 | L118: =IF(Gastos[[#This Row],[Importe]]>0,"Ingreso","Egreso") -> Ingreso | M118: =IF(AND(COUNTIFS($B$2:$B$3988,B118,$I$2:$I$3988,I118,$K$2:$K$3988,K118)>1,F118=""),"DUPLICADO","Único") -> Único
A119: Cristina | B119: 46084 | C119: 46084 | D119: 46084 | E119: 46084 | F119: Suscripciones | G119: RECIBO DAN'S Nº RECIBO 0073 0100 755 CPTLDTR REF. MANDATO 1QJYY43XYCXGBUV0 | I119: -99 | K119: 7997.83 | L119: =IF(Gastos[[#This Row],[Importe]]>0,"Ingreso","Egreso") -> Egreso | M119: =IF(AND(COUNTIFS($B$2:$B$3988,B119,$I$2:$I$3988,I119,$K$2:$K$3988,K119)>1,F119=""),"DUPLICADO","Único") -> Único
A120: Cuentas | B120: 46115 | C120: 46085 | D120: 46084 | E120: 46084 | F120: Financiero | G120: LIQUIDACION DE COMISIONES Y GASTOS | I120: 0.39 | K120: 446.59 | L120: =IF(Gastos[[#This Row],[Importe]]>0,"Ingreso","Egreso") -> Ingreso | M120: =IF(AND(COUNTIFS($B$2:$B$3988,B120,$I$2:$I$3988,I120,$K$2:$K$3988,K120)>1,F120=""),"DUPLICADO","Único") -> Único
A121: Nomina | B121: 46056 | C121: 46083 | D121: 46056 | E121: 46083 | F121: Suscripciones | G121: Apple pay: COMPRA EN APPLE.COM/BILL, CON LA TARJETA : 5489133210353841 EL 2026-02-28 | I121: -22 | K121: 3433.54 | L121: =IF(Gastos[[#This Row],[Importe]]>0,"Ingreso","Egreso") -> Egreso | M121: =IF(AND(COUNTIFS($B$2:$B$3988,B121,$I$2:$I$3988,I121,$K$2:$K$3988,K121)>1,F121=""),"DUPLICADO","Único") -> Único
A122: Nomina | B122: 46056 | C122: 46083 | D122: 46056 | E122: 46083 | F122: Reparaciones | G122: COMPRA EN WWW.AMAZON*BJ1XX97E5, CON LA TARJETA : 5489133210353841 EL 2026-02-26 | I122: -8.25 | K122: 3455.54 | L122: =IF(Gastos[[#This Row],[Importe]]>0,"Ingreso","Egreso") -> Egreso | M122: =IF(AND(COUNTIFS($B$2:$B$3988,B122,$I$2:$I$3988,I122,$K$2:$K$3988,K122)>1,F122=""),"DUPLICADO","Único") -> Único
A123: Nomina | B123: 46056 | C123: 46083 | D123: 46056 | E123: 46083 | F123: Reparaciones | G123: COMPRA EN WWW.AMAZON*7045Y0XB5, CON LA TARJETA : 5489133210353841 EL 2026-03-01 | I123: -9.95 | K123: 3463.79 | L123: =IF(Gastos[[#This Row],[Importe]]>0,"Ingreso","Egreso") -> Egreso | M123: =IF(AND(COUNTIFS($B$2:$B$3988,B123,$I$2:$I$3988,I123,$K$2:$K$3988,K123)>1,F123=""),"DUPLICADO","Único") -> Único
A124: Nomina | B124: 46056 | C124: 46083 | D124: 46056 | E124: 46083 | F124: Inversión | G124: TRANSFERENCIA A FAVOR DE IBKR CONCEPTO: U6384508 / NICOLAS D Perez | I124: -400 | K124: 3473.74 | L124: =IF(Gastos[[#This Row],[Importe]]>0,"Ingreso","Egreso") -> Egreso | M124: =IF(AND(COUNTIFS($B$2:$B$3988,B124,$I$2:$I$3988,I124,$K$2:$K$3988,K124)>1,F124=""),"DUPLICADO","Único") -> Único
A125: Cristina | B125: 46056 | C125: 46083 | D125: 46056 | E125: 46083 | G125: Apple pay: COMPRA EN MAR MORA, CON LA TARJETA : 5489133208122208 EL 2026-03-02 | I125: -4.71 | K125: 8096.83 | L125: =IF(Gastos[[#This Row],[Importe]]>0,"Ingreso","Egreso") -> Egreso | M125: =IF(AND(COUNTIFS($B$2:$B$3988,B125,$I$2:$I$3988,I125,$K$2:$K$3988,K125)>1,F125=""),"DUPLICADO","Único") -> Único
A126: Cristina | B126: 46056 | C126: 46083 | D126: 46056 | E126: 46083 | F126: Alquiler | G126: TRANSFERENCIA A FAVOR DE Jesús Gonzalez CONCEPTO: Alquiler | I126: -936 | K126: 8101.54 | L126: =IF(Gastos[[#This Row],[Importe]]>0,"Ingreso","Egreso") -> Egreso | M126: =IF(AND(COUNTIFS($B$2:$B$3988,B126,$I$2:$I$3988,I126,$K$2:$K$3988,K126)>1,F126=""),"DUPLICADO","Único") -> Único
A127: Cristina | B127: 46056 | C127: 46083 | D127: 46056 | E127: 46083 | F127: Sueldo | G127: TRANSFERENCIA DE Currie Brown Iberia SLU, CONCEPTO Febrero Nomina | I127: 2304.31 | K127: 9051.59 | L127: =IF(Gastos[[#This Row],[Importe]]>0,"Ingreso","Egreso") -> Ingreso | M127: =IF(AND(COUNTIFS($B$2:$B$3988,B127,$I$2:$I$3988,I127,$K$2:$K$3988,K127)>1,F127=""),"DUPLICADO","Único") -> Único
A128: Cuentas | B128: 46084 | C128: 46084 | D128: 46056 | E128: 46083 | F128: Financiero | G128: COMISION POR COMPRAS REALIZADAS EN MONEDA NO EURO | I128: -0.54 | K128: 433.08 | L128: =IF(Gastos[[#This Row],[Importe]]>0,"Ingreso","Egreso") -> Egreso | M128: =IF(AND(COUNTIFS($B$2:$B$3988,B128,$I$2:$I$3988,I128,$K$2:$K$3988,K128)>1,F128=""),"DUPLICADO","Único") -> Único
A129: Cuentas | B129: 46084 | C129: 46084 | D129: 46056 | E129: 46083 | F129: Financiero | G129: COMISION POR COMPRAS REALIZADAS EN MONEDA NO EURO | I129: -0.39 | K129: 433.62 | L129: =IF(Gastos[[#This Row],[Importe]]>0,"Ingreso","Egreso") -> Egreso | M129: =IF(AND(COUNTIFS($B$2:$B$3988,B129,$I$2:$I$3988,I129,$K$2:$K$3988,K129)>1,F129=""),"DUPLICADO","Único") -> Único
A130: Cuentas | B130: 46056 | C130: 46083 | D130: 46056 | E130: 46083 | F130: Suscripciones | G130: COMPRA EN OPENAI *CHATGPT SUBSCR, CON LA TARJETA : 5489133208360204 EL 2026-02-27 | I130: -18.06 | K130: 434.01 | L130: =IF(Gastos[[#This Row],[Importe]]>0,"Ingreso","Egreso") -> Egreso | M130: =IF(AND(COUNTIFS($B$2:$B$3988,B130,$I$2:$I$3988,I130,$K$2:$K$3988,K130)>1,F130=""),"DUPLICADO","Único") -> Único
A131: Cuentas | B131: 46056 | C131: 46083 | D131: 46056 | E131: 46083 | F131: Entretenimiento | G131: COMPRA EN UBER *EATS HELP.UBER.C, CON LA TARJETA : 5489133208360204 EL 2026-02-27 | I131: -13.13 | K131: 452.07 | L131: =IF(Gastos[[#This Row],[Importe]]>0,"Ingreso","Egreso") -> Egreso | M131: =IF(AND(COUNTIFS($B$2:$B$3988,B131,$I$2:$I$3988,I131,$K$2:$K$3988,K131)>1,F131=""),"DUPLICADO","Único") -> Único
A132: Cuentas | B132: 46056 | C132: 46083 | D132: 46056 | E132: 46083 | F132: Seguro | G132: RECIBO SANITAS S A DE SEGUROS Nº RECIBO 0073 0100 755 CPQHMCL REF. MANDATO 800018385362 | I132: -115.84 | K132: 465.2 | L132: =IF(Gastos[[#This Row],[Importe]]>0,"Ingreso","Egreso") -> Egreso | M132: =IF(AND(COUNTIFS($B$2:$B$3988,B132,$I$2:$I$3988,I132,$K$2:$K$3988,K132)>1,F132=""),"DUPLICADO","Único") -> Único
...

Sheet Dashboard Gastos
A1: Dashboard de gastos | AA1: Agrupar | AB1: Año | AC1: Trimestre | AD1: Mes | AE1: Cuenta | AH1: {=_xlfn.LET(_xlpm.fechas,Data!$E$2:$E$3988,_xlpm.cuentas,Data!$A$2:$A$3988,_xlpm.tiposBase,Data!$F$2:$F$3988,_xlpm.imp,IFERROR(1*Data!$I$2:$I$3988,0),_xlpm.tipos,_xlfn._xlws.SORT(_xlfn.UNIQUE(_xlfn._xlws.FILTER(_xlpm.tiposBase,_xlpm.tiposBase<>""))),_xlpm.f,IF($B$5="Todos",1,--(YEAR(_xlpm.fechas)=$B$5))*IF($B$6="Todos",1,--("T"&ROUNDUP(MONTH(_xlpm.fechas)/3,0)=$B$6))*IF($B$7="Todos",1,--(TEXT(_xlpm.fechas,"[$-es-ES]mmmm")=$B$7))*IF($B$8="Todas",1,--(_xlpm.cuentas=$B$8)),_xlpm.g,_xlfn.MAP(_xlpm.tipos,_xlfn.LAMBDA(_xlpm.t,-SUMPRODUCT((_xlpm.tiposBase=_xlpm.t)*(_xlpm.imp<0)*_xlpm.f*_xlpm.imp))),_xlpm.tabla,IFERROR(_xlfn.SORTBY(_xlfn._xlws.FILTER(_xlfn.HSTACK(_xlpm.tipos,_xlpm.g),_xlpm.g<>0),_xlfn._xlws.FILTER(_xlpm.g,_xlpm.g<>0),-1),{"Sin datos",0}),_xlfn.VSTACK({"Tipo","Gasto"},_xlpm.tabla))} -> Tipo | AI1: Gasto | AK1: {=_xlfn.LET(_xlpm.fechas,Data!$E$2:$E$3988,_xlpm.cuentas,Data!$A$2:$A$3988,_xlpm.imp,IFERROR(1*Data!$I$2:$I$3988,0),_xlpm.f,IF($B$5="Todos",1,--(YEAR(_xlpm.fechas)=$B$5))*IF($B$6="Todos",1,--("T"&ROUNDUP(MONTH(_xlpm.fechas)/3,0)=$B$6))*IF($B$7="Todos",1,--(TEXT(_xlpm.fechas,"[$-es-ES]mmmm")=$B$7))*IF($B$8="Todas",1,--(_xlpm.cuentas=$B$8)),_xlpm.periodo,IF($B$4="Mensual",TEXT(_xlpm.fechas,"yyyy-mm"),IF($B$4="Trimestral",YEAR(_xlpm.fechas)&"-T"&ROUNDUP(MONTH(_xlpm.fechas)/3,0),TEXT(YEAR(_xlpm.fechas),"0"))),_xlpm.periodos,IFERROR(_xlfn._xlws.SORT(_xlfn.UNIQUE(_xlfn._xlws.FILTER(_xlpm.periodo,_xlpm.f>0))),{"Sin datos"}),_xlpm.gastos,_xlfn.MAP(_xlpm.periodos,_xlfn.LAMBDA(_xlpm.p,IF(_xlpm.p="Sin datos",0,-SUMPRODUCT((_xlpm.periodo=_xlpm.p)*(_xlpm.imp<0)*_xlpm.f*_xlpm.imp)))),_xlpm.ingresos,_xlfn.MAP(_xlpm.periodos,_xlfn.LAMBDA(_xlpm.p,IF(_xlpm.p="Sin datos",0,SUMPRODUCT((_xlpm.periodo=_xlpm.p)*(_xlpm.imp>0)*_xlpm.f*_xlpm.imp)))),_xlpm.neto,_xlfn.MAP(_xlpm.periodos,_xlfn.LAMBDA(_xlpm.p,IF(_xlpm.p="Sin datos",0,SUMPRODUCT((_xlpm.periodo=_xlpm.p)*_xlpm.f*_xlpm.imp)))),_xlfn.VSTACK({"Periodo","Gastos","Ingresos","Neto"},_xlfn.HSTACK(_xlpm.periodos,_xlpm.gastos,_xlpm.ingresos,_xlpm.neto)))} -> Periodo | AL1: Gastos | AM1: Ingresos | AN1: Neto | AP1: Periodo | AQ1: {=TRANSPOSE(_xlfn._xlws.FILTER(AE3:AE20,AE3:AE20<>""))} -> Crédito | AR1: Cristina | AS1: Cuentas | AT1: Nomina | BB1: {=_xlfn.LET(_xlpm.sel,$B$8,_xlpm.periodos,_xlfn._xlws.FILTER($AP$2:$AP$50,$AP$2:$AP$50<>""),_xlpm.headers,_xlfn._xlws.FILTER($AQ$1:$AZ$1,$AQ$1:$AZ$1<>""),_xlpm.base,_xlfn.TAKE($AQ$2:$AZ$50,ROWS(_xlpm.periodos),COLUMNS(_xlpm.headers)),_xlpm.headersOut,IF(_xlpm.sel="Todas",_xlpm.headers,_xlfn.HSTACK(_xlpm.sel)),_xlpm.dataOut,IF(_xlpm.sel="Todas",_xlpm.base,_xlfn.CHOOSECOLS(_xlpm.base,_xlfn.XMATCH(_xlpm.sel,$AQ$1:$AZ$1))),_xlfn.VSTACK(_xlfn.HSTACK("Periodo",_xlpm.headersOut),_xlfn.HSTACK(_xlpm.periodos,_xlpm.dataOut)))} -> Periodo | BC1: Crédito | BD1: Cristina | BE1: Cuentas | BF1: Nomina
A2: ="Periodo de datos: "&TEXT(MIN(Gastos[Fecha valor REAL]),"dd/mm/yyyy")&" a "&TEXT(MAX(Gastos[Fecha valor REAL]),"dd/mm/yyyy") -> Periodo de datos: 13/06/2023 a 06/04/2026 | AA2: Mensual | AB2: Todos | AC2: Todos | AD2: Todos | AE2: Todas | AH2: Alquiler | AI2: 5433 | AK2: 2026-01 | AL2: 7602.52 | AM2: 4050.1 | AN2: -3552.42 | AP2: {=_xlfn.CHOOSECOLS(_xlfn.DROP(_xlfn.ANCHORARRAY(AK1),1),1)} -> 2026-01 | AQ2: {=IF(OR($AP2="",AQ$1=""),NA(),IFERROR(AVERAGE(_xlfn._xlws.FILTER(Data!$K$2:$K$3988,((Data!$A$2:$A$3988=AQ$1)*IF($B$8="Todas",1,--(AQ$1=$B$8))*IF($B$5="Todos",1,--(YEAR(Data!$E$2:$E$3988)=$B$5))*IF($B$6="Todos",1,--("T"&ROUNDUP(MONTH(Data!$E$2:$E$3988)/3,0)=$B$6))*IF($B$7="Todos",1,--(TEXT(Data!$E$2:$E$3988,"[$-es-ES]mmmm")=$B$7))*--(CHOOSE(MATCH($B$4,{"Mensual","Trimestral","Anual"},0),TEXT(Data!$E$2:$E$3988,"yyyy-mm"),YEAR(Data!$E$2:$E$3988)&"-T"&ROUNDUP(MONTH(Data!$E$2:$E$3988)/3,0),TEXT(YEAR(Data!$E$2:$E$3988),"0"))=$AP2))>0)),NA()))} -> #N/A | AR2: {=IF(OR($AP2="",AR$1=""),NA(),IFERROR(AVERAGE(_xlfn._xlws.FILTER(Data!$K$2:$K$3988,((Data!$A$2:$A$3988=AR$1)*IF($B$8="Todas",1,--(AR$1=$B$8))*IF($B$5="Todos",1,--(YEAR(Data!$E$2:$E$3988)=$B$5))*IF($B$6="Todos",1,--("T"&ROUNDUP(MONTH(Data!$E$2:$E$3988)/3,0)=$B$6))*IF($B$7="Todos",1,--(TEXT(Data!$E$2:$E$3988,"[$-es-ES]mmmm")=$B$7))*--(CHOOSE(MATCH($B$4,{"Mensual","Trimestral","Anual"},0),TEXT(Data!$E$2:$E$3988,"yyyy-mm"),YEAR(Data!$E$2:$E$3988)&"-T"&ROUNDUP(MONTH(Data!$E$2:$E$3988)/3,0),TEXT(YEAR(Data!$E$2:$E$3988),"0"))=$AP2))>0)),NA()))} -> 6032.2852 | AS2: {=IF(OR($AP2="",AS$1=""),NA(),IFERROR(AVERAGE(_xlfn._xlws.FILTER(Data!$K$2:$K$3988,((Data!$A$2:$A$3988=AS$1)*IF($B$8="Todas",1,--(AS$1=$B$8))*IF($B$5="Todos",1,--(YEAR(Data!$E$2:$E$3988)=$B$5))*IF($B$6="Todos",1,--("T"&ROUNDUP(MONTH(Data!$E$2:$E$3988)/3,0)=$B$6))*IF($B$7="Todos",1,--(TEXT(Data!$E$2:$E$3988,"[$-es-ES]mmmm")=$B$7))*--(CHOOSE(MATCH($B$4,{"Mensual","Trimestral","Anual"},0),TEXT(Data!$E$2:$E$3988,"yyyy-mm"),YEAR(Data!$E$2:$E$3988)&"-T"&ROUNDUP(MONTH(Data!$E$2:$E$3988)/3,0),TEXT(YEAR(Data!$E$2:$E$3988),"0"))=$AP2))>0)),NA()))} -> 1805.7969 | AT2: {=IF(OR($AP2="",AT$1=""),NA(),IFERROR(AVERAGE(_xlfn._xlws.FILTER(Data!$K$2:$K$3988,((Data!$A$2:$A$3988=AT$1)*IF($B$8="Todas",1,--(AT$1=$B$8))*IF($B$5="Todos",1,--(YEAR(Data!$E$2:$E$3988)=$B$5))*IF($B$6="Todos",1,--("T"&ROUNDUP(MONTH(Data!$E$2:$E$3988)/3,0)=$B$6))*IF($B$7="Todos",1,--(TEXT(Data!$E$2:$E$3988,"[$-es-ES]mmmm")=$B$7))*--(CHOOSE(MATCH($B$4,{"Mensual","Trimestral","Anual"},0),TEXT(Data!$E$2:$E$3988,"yyyy-mm"),YEAR(Data!$E$2:$E$3988)&"-T"&ROUNDUP(MONTH(Data!$E$2:$E$3988)/3,0),TEXT(YEAR(Data!$E$2:$E$3988),"0"))=$AP2))>0)),NA()))} -> 2261.4176 | BB2: 2026-01 | BC2: #N/A | BD2: 6032.2852 | BE2: 1805.7969 | BF2: 2261.4176
A3: Filtros | AA3: Trimestral | AB3: {=_xlfn._xlws.SORT(_xlfn.UNIQUE(YEAR(Gastos[Fecha valor REAL])))} -> 2023 | AC3: T1 | AD3: Enero | AE3: {=_xlfn._xlws.SORT(_xlfn.UNIQUE(_xlfn._xlws.FILTER(Gastos[Cuenta],Gastos[Cuenta]<>"")))} -> Crédito | AH3: Compras | AI3: 3286.87 | AK3: 2026-02 | AL3: 4737.56 | AM3: 4835.51 | AN3: 97.95 | AP3: 2026-02 | AQ3: {=IF(OR($AP3="",AQ$1=""),NA(),IFERROR(AVERAGE(_xlfn._xlws.FILTER(Data!$K$2:$K$3988,((Data!$A$2:$A$3988=AQ$1)*IF($B$8="Todas",1,--(AQ$1=$B$8))*IF($B$5="Todos",1,--(YEAR(Data!$E$2:$E$3988)=$B$5))*IF($B$6="Todos",1,--("T"&ROUNDUP(MONTH(Data!$E$2:$E$3988)/3,0)=$B$6))*IF($B$7="Todos",1,--(TEXT(Data!$E$2:$E$3988,"[$-es-ES]mmmm")=$B$7))*--(CHOOSE(MATCH($B$4,{"Mensual","Trimestral","Anual"},0),TEXT(Data!$E$2:$E$3988,"yyyy-mm"),YEAR(Data!$E$2:$E$3988)&"-T"&ROUNDUP(MONTH(Data!$E$2:$E$3988)/3,0),TEXT(YEAR(Data!$E$2:$E$3988),"0"))=$AP3))>0)),NA()))} -> #N/A | AR3: {=IF(OR($AP3="",AR$1=""),NA(),IFERROR(AVERAGE(_xlfn._xlws.FILTER(Data!$K$2:$K$3988,((Data!$A$2:$A$3988=AR$1)*IF($B$8="Todas",1,--(AR$1=$B$8))*IF($B$5="Todos",1,--(YEAR(Data!$E$2:$E$3988)=$B$5))*IF($B$6="Todos",1,--("T"&ROUNDUP(MONTH(Data!$E$2:$E$3988)/3,0)=$B$6))*IF($B$7="Todos",1,--(TEXT(Data!$E$2:$E$3988,"[$-es-ES]mmmm")=$B$7))*--(CHOOSE(MATCH($B$4,{"Mensual","Trimestral","Anual"},0),TEXT(Data!$E$2:$E$3988,"yyyy-mm"),YEAR(Data!$E$2:$E$3988)&"-T"&ROUNDUP(MONTH(Data!$E$2:$E$3988)/3,0),TEXT(YEAR(Data!$E$2:$E$3988),"0"))=$AP3))>0)),NA()))} -> 7020.4471 | AS3: {=IF(OR($AP3="",AS$1=""),NA(),IFERROR(AVERAGE(_xlfn._xlws.FILTER(Data!$K$2:$K$3988,((Data!$A$2:$A$3988=AS$1)*IF($B$8="Todas",1,--(AS$1=$B$8))*IF($B$5="Todos",1,--(YEAR(Data!$E$2:$E$3988)=$B$5))*IF($B$6="Todos",1,--("T"&ROUNDUP(MONTH(Data!$E$2:$E$3988)/3,0)=$B$6))*IF($B$7="Todos",1,--(TEXT(Data!$E$2:$E$3988,"[$-es-ES]mmmm")=$B$7))*--(CHOOSE(MATCH($B$4,{"Mensual","Trimestral","Anual"},0),TEXT(Data!$E$2:$E$3988,"yyyy-mm"),YEAR(Data!$E$2:$E$3988)&"-T"&ROUNDUP(MONTH(Data!$E$2:$E$3988)/3,0),TEXT(YEAR(Data!$E$2:$E$3988),"0"))=$AP3))>0)),NA()))} -> 962.85879 | AT3: {=IF(OR($AP3="",AT$1=""),NA(),IFERROR(AVERAGE(_xlfn._xlws.FILTER(Data!$K$2:$K$3988,((Data!$A$2:$A$3988=AT$1)*IF($B$8="Todas",1,--(AT$1=$B$8))*IF($B$5="Todos",1,--(YEAR(Data!$E$2:$E$3988)=$B$5))*IF($B$6="Todos",1,--("T"&ROUNDUP(MONTH(Data!$E$2:$E$3988)/3,0)=$B$6))*IF($B$7="Todos",1,--(TEXT(Data!$E$2:$E$3988,"[$-es-ES]mmmm")=$B$7))*--(CHOOSE(MATCH($B$4,{"Mensual","Trimestral","Anual"},0),TEXT(Data!$E$2:$E$3988,"yyyy-mm"),YEAR(Data!$E$2:$E$3988)&"-T"&ROUNDUP(MONTH(Data!$E$2:$E$3988)/3,0),TEXT(YEAR(Data!$E$2:$E$3988),"0"))=$AP3))>0)),NA()))} -> 2565.5343 | BB3: 2026-02 | BC3: #N/A | BD3: 7020.4471 | BE3: 962.85879 | BF3: 2565.5343
A4: Agrupar por | B4: Mensual | D4: Gasto total | G4: Ingresos | J4: Neto | M4: Transacciones | AA4: Anual | AB4: 2024 | AC4: T2 | AD4: Febrero | AE4: Cristina | AH4: Regularización | AI4: 2850 | AK4: 2026-03 | AL4: 9454.07 | AM4: 38456.06 | AN4: 29001.99 | AP4: 2026-03 | AQ4: {=IF(OR($AP4="",AQ$1=""),NA(),IFERROR(AVERAGE(_xlfn._xlws.FILTER(Data!$K$2:$K$3988,((Data!$A$2:$A$3988=AQ$1)*IF($B$8="Todas",1,--(AQ$1=$B$8))*IF($B$5="Todos",1,--(YEAR(Data!$E$2:$E$3988)=$B$5))*IF($B$6="Todos",1,--("T"&ROUNDUP(MONTH(Data!$E$2:$E$3988)/3,0)=$B$6))*IF($B$7="Todos",1,--(TEXT(Data!$E$2:$E$3988,"[$-es-ES]mmmm")=$B$7))*--(CHOOSE(MATCH($B$4,{"Mensual","Trimestral","Anual"},0),TEXT(Data!$E$2:$E$3988,"yyyy-mm"),YEAR(Data!$E$2:$E$3988)&"-T"&ROUNDUP(MONTH(Data!$E$2:$E$3988)/3,0),TEXT(YEAR(Data!$E$2:$E$3988),"0"))=$AP4))>0)),NA()))} -> #N/A | AR4: {=IF(OR($AP4="",AR$1=""),NA(),IFERROR(AVERAGE(_xlfn._xlws.FILTER(Data!$K$2:$K$3988,((Data!$A$2:$A$3988=AR$1)*IF($B$8="Todas",1,--(AR$1=$B$8))*IF($B$5="Todos",1,--(YEAR(Data!$E$2:$E$3988)=$B$5))*IF($B$6="Todos",1,--("T"&ROUNDUP(MONTH(Data!$E$2:$E$3988)/3,0)=$B$6))*IF($B$7="Todos",1,--(TEXT(Data!$E$2:$E$3988,"[$-es-ES]mmmm")=$B$7))*--(CHOOSE(MATCH($B$4,{"Mensual","Trimestral","Anual"},0),TEXT(Data!$E$2:$E$3988,"yyyy-mm"),YEAR(Data!$E$2:$E$3988)&"-T"&ROUNDUP(MONTH(Data!$E$2:$E$3988)/3,0),TEXT(YEAR(Data!$E$2:$E$3988),"0"))=$AP4))>0)),NA()))} -> 18071.061 | AS4: {=IF(OR($AP4="",AS$1=""),NA(),IFERROR(AVERAGE(_xlfn._xlws.FILTER(Data!$K$2:$K$3988,((Data!$A$2:$A$3988=AS$1)*IF($B$8="Todas",1,--(AS$1=$B$8))*IF($B$5="Todos",1,--(YEAR(Data!$E$2:$E$3988)=$B$5))*IF($B$6="Todos",1,--("T"&ROUNDUP(MONTH(Data!$E$2:$E$3988)/3,0)=$B$6))*IF($B$7="Todos",1,--(TEXT(Data!$E$2:$E$3988,"[$-es-ES]mmmm")=$B$7))*--(CHOOSE(MATCH($B$4,{"Mensual","Trimestral","Anual"},0),TEXT(Data!$E$2:$E$3988,"yyyy-mm"),YEAR(Data!$E$2:$E$3988)&"-T"&ROUNDUP(MONTH(Data!$E$2:$E$3988)/3,0),TEXT(YEAR(Data!$E$2:$E$3988),"0"))=$AP4))>0)),NA()))} -> 984.67706 | AT4: {=IF(OR($AP4="",AT$1=""),NA(),IFERROR(AVERAGE(_xlfn._xlws.FILTER(Data!$K$2:$K$3988,((Data!$A$2:$A$3988=AT$1)*IF($B$8="Todas",1,--(AT$1=$B$8))*IF($B$5="Todos",1,--(YEAR(Data!$E$2:$E$3988)=$B$5))*IF($B$6="Todos",1,--("T"&ROUNDUP(MONTH(Data!$E$2:$E$3988)/3,0)=$B$6))*IF($B$7="Todos",1,--(TEXT(Data!$E$2:$E$3988,"[$-es-ES]mmmm")=$B$7))*--(CHOOSE(MATCH($B$4,{"Mensual","Trimestral","Anual"},0),TEXT(Data!$E$2:$E$3988,"yyyy-mm"),YEAR(Data!$E$2:$E$3988)&"-T"&ROUNDUP(MONTH(Data!$E$2:$E$3988)/3,0),TEXT(YEAR(Data!$E$2:$E$3988),"0"))=$AP4))>0)),NA()))} -> 2051.0968 | BB4: 2026-03 | BC4: #N/A | BD4: 18071.061 | BE4: 984.67706 | BF4: 2051.0968
A5: Año | B5: 2026 | D5: {=_xlfn.LET(_xlpm.fechas,Data!$E$2:$E$3988,_xlpm.cuentas,Data!$A$2:$A$3988,_xlpm.imp,IFERROR(1*Data!$I$2:$I$3988,0),_xlpm.f,IF($B$5="Todos",1,--(YEAR(_xlpm.fechas)=$B$5))*IF($B$6="Todos",1,--("T"&ROUNDUP(MONTH(_xlpm.fechas)/3,0)=$B$6))*IF($B$7="Todos",1,--(TEXT(_xlpm.fechas,"[$-es-ES]mmmm")=$B$7))*IF($B$8="Todas",1,--(_xlpm.cuentas=$B$8)),-SUMPRODUCT((_xlpm.imp<0)*_xlpm.f*_xlpm.imp))} -> 25803.9 | G5: {=_xlfn.LET(_xlpm.fechas,Data!$E$2:$E$3988,_xlpm.cuentas,Data!$A$2:$A$3988,_xlpm.imp,IFERROR(1*Data!$I$2:$I$3988,0),_xlpm.f,IF($B$5="Todos",1,--(YEAR(_xlpm.fechas)=$B$5))*IF($B$6="Todos",1,--("T"&ROUNDUP(MONTH(_xlpm.fechas)/3,0)=$B$6))*IF($B$7="Todos",1,--(TEXT(_xlpm.fechas,"[$-es-ES]mmmm")=$B$7))*IF($B$8="Todas",1,--(_xlpm.cuentas=$B$8)),SUMPRODUCT((_xlpm.imp>0)*_xlpm.f*_xlpm.imp))} -> 47341.67 | J5: {=_xlfn.LET(_xlpm.fechas,Data!$E$2:$E$3988,_xlpm.cuentas,Data!$A$2:$A$3988,_xlpm.imp,IFERROR(1*Data!$I$2:$I$3988,0),_xlpm.f,IF($B$5="Todos",1,--(YEAR(_xlpm.fechas)=$B$5))*IF($B$6="Todos",1,--("T"&ROUNDUP(MONTH(_xlpm.fechas)/3,0)=$B$6))*IF($B$7="Todos",1,--(TEXT(_xlpm.fechas,"[$-es-ES]mmmm")=$B$7))*IF($B$8="Todas",1,--(_xlpm.cuentas=$B$8)),SUMPRODUCT(_xlpm.f*_xlpm.imp))} -> 21537.77 | M5: {=_xlfn.LET(_xlpm.fechas,Data!$E$2:$E$3988,_xlpm.cuentas,Data!$A$2:$A$3988,_xlpm.f,IF($B$5="Todos",1,--(YEAR(_xlpm.fechas)=$B$5))*IF($B$6="Todos",1,--("T"&ROUNDUP(MONTH(_xlpm.fechas)/3,0)=$B$6))*IF($B$7="Todos",1,--(TEXT(_xlpm.fechas,"[$-es-ES]mmmm")=$B$7))*IF($B$8="Todas",1,--(_xlpm.cuentas=$B$8)),SUMPRODUCT(_xlpm.f))} -> 305 | AB5: 2025 | AC5: T3 | AD5: Marzo | AE5: Cuentas | AH5: Entretenimiento | AI5: 2780.09 | AK5: 2026-04 | AL5: 4009.75 | AM5: 0 | AN5: -4009.75 | AP5: 2026-04 | AQ5: {=IF(OR($AP5="",AQ$1=""),NA(),IFERROR(AVERAGE(_xlfn._xlws.FILTER(Data!$K$2:$K$3988,((Data!$A$2:$A$3988=AQ$1)*IF($B$8="Todas",1,--(AQ$1=$B$8))*IF($B$5="Todos",1,--(YEAR(Data!$E$2:$E$3988)=$B$5))*IF($B$6="Todos",1,--("T"&ROUNDUP(MONTH(Data!$E$2:$E$3988)/3,0)=$B$6))*IF($B$7="Todos",1,--(TEXT(Data!$E$2:$E$3988,"[$-es-ES]mmmm")=$B$7))*--(CHOOSE(MATCH($B$4,{"Mensual","Trimestral","Anual"},0),TEXT(Data!$E$2:$E$3988,"yyyy-mm"),YEAR(Data!$E$2:$E$3988)&"-T"&ROUNDUP(MONTH(Data!$E$2:$E$3988)/3,0),TEXT(YEAR(Data!$E$2:$E$3988),"0"))=$AP5))>0)),NA()))} -> #N/A | AR5: {=IF(OR($AP5="",AR$1=""),NA(),IFERROR(AVERAGE(_xlfn._xlws.FILTER(Data!$K$2:$K$3988,((Data!$A$2:$A$3988=AR$1)*IF($B$8="Todas",1,--(AR$1=$B$8))*IF($B$5="Todos",1,--(YEAR(Data!$E$2:$E$3988)=$B$5))*IF($B$6="Todos",1,--("T"&ROUNDUP(MONTH(Data!$E$2:$E$3988)/3,0)=$B$6))*IF($B$7="Todos",1,--(TEXT(Data!$E$2:$E$3988,"[$-es-ES]mmmm")=$B$7))*--(CHOOSE(MATCH($B$4,{"Mensual","Trimestral","Anual"},0),TEXT(Data!$E$2:$E$3988,"yyyy-mm"),YEAR(Data!$E$2:$E$3988)&"-T"&ROUNDUP(MONTH(Data!$E$2:$E$3988)/3,0),TEXT(YEAR(Data!$E$2:$E$3988),"0"))=$AP5))>0)),NA()))} -> 34141.092 | AS5: {=IF(OR($AP5="",AS$1=""),NA(),IFERROR(AVERAGE(_xlfn._xlws.FILTER(Data!$K$2:$K$3988,((Data!$A$2:$A$3988=AS$1)*IF($B$8="Todas",1,--(AS$1=$B$8))*IF($B$5="Todos",1,--(YEAR(Data!$E$2:$E$3988)=$B$5))*IF($B$6="Todos",1,--("T"&ROUNDUP(MONTH(Data!$E$2:$E$3988)/3,0)=$B$6))*IF($B$7="Todos",1,--(TEXT(Data!$E$2:$E$3988,"[$-es-ES]mmmm")=$B$7))*--(CHOOSE(MATCH($B$4,{"Mensual","Trimestral","Anual"},0),TEXT(Data!$E$2:$E$3988,"yyyy-mm"),YEAR(Data!$E$2:$E$3988)&"-T"&ROUNDUP(MONTH(Data!$E$2:$E$3988)/3,0),TEXT(YEAR(Data!$E$2:$E$3988),"0"))=$AP5))>0)),NA()))} -> 1485.814 | AT5: {=IF(OR($AP5="",AT$1=""),NA(),IFERROR(AVERAGE(_xlfn._xlws.FILTER(Data!$K$2:$K$3988,((Data!$A$2:$A$3988=AT$1)*IF($B$8="Todas",1,--(AT$1=$B$8))*IF($B$5="Todos",1,--(YEAR(Data!$E$2:$E$3988)=$B$5))*IF($B$6="Todos",1,--("T"&ROUNDUP(MONTH(Data!$E$2:$E$3988)/3,0)=$B$6))*IF($B$7="Todos",1,--(TEXT(Data!$E$2:$E$3988,"[$-es-ES]mmmm")=$B$7))*--(CHOOSE(MATCH($B$4,{"Mensual","Trimestral","Anual"},0),TEXT(Data!$E$2:$E$3988,"yyyy-mm"),YEAR(Data!$E$2:$E$3988)&"-T"&ROUNDUP(MONTH(Data!$E$2:$E$3988)/3,0),TEXT(YEAR(Data!$E$2:$E$3988),"0"))=$AP5))>0)),NA()))} -> 2500.7467 | BB5: 2026-04 | BC5: #N/A | BD5: 34141.092 | BE5: 1485.814 | BF5: 2500.7467
A6: Trimestre | B6: Todos | AB6: 2026 | AC6: T4 | AD6: Abril | AE6: Nomina | AH6: Inversión | AI6: 2100 | AQ6: {=IF(OR($AP6="",AQ$1=""),NA(),IFERROR(AVERAGE(_xlfn._xlws.FILTER(Data!$K$2:$K$3988,((Data!$A$2:$A$3988=AQ$1)*IF($B$8="Todas",1,--(AQ$1=$B$8))*IF($B$5="Todos",1,--(YEAR(Data!$E$2:$E$3988)=$B$5))*IF($B$6="Todos",1,--("T"&ROUNDUP(MONTH(Data!$E$2:$E$3988)/3,0)=$B$6))*IF($B$7="Todos",1,--(TEXT(Data!$E$2:$E$3988,"[$-es-ES]mmmm")=$B$7))*--(CHOOSE(MATCH($B$4,{"Mensual","Trimestral","Anual"},0),TEXT(Data!$E$2:$E$3988,"yyyy-mm"),YEAR(Data!$E$2:$E$3988)&"-T"&ROUNDUP(MONTH(Data!$E$2:$E$3988)/3,0),TEXT(YEAR(Data!$E$2:$E$3988),"0"))=$AP6))>0)),NA()))} -> #N/A | AR6: {=IF(OR($AP6="",AR$1=""),NA(),IFERROR(AVERAGE(_xlfn._xlws.FILTER(Data!$K$2:$K$3988,((Data!$A$2:$A$3988=AR$1)*IF($B$8="Todas",1,--(AR$1=$B$8))*IF($B$5="Todos",1,--(YEAR(Data!$E$2:$E$3988)=$B$5))*IF($B$6="Todos",1,--("T"&ROUNDUP(MONTH(Data!$E$2:$E$3988)/3,0)=$B$6))*IF($B$7="Todos",1,--(TEXT(Data!$E$2:$E$3988,"[$-es-ES]mmmm")=$B$7))*--(CHOOSE(MATCH($B$4,{"Mensual","Trimestral","Anual"},0),TEXT(Data!$E$2:$E$3988,"yyyy-mm"),YEAR(Data!$E$2:$E$3988)&"-T"&ROUNDUP(MONTH(Data!$E$2:$E$3988)/3,0),TEXT(YEAR(Data!$E$2:$E$3988),"0"))=$AP6))>0)),NA()))} -> #N/A | AS6: {=IF(OR($AP6="",AS$1=""),NA(),IFERROR(AVERAGE(_xlfn._xlws.FILTER(Data!$K$2:$K$3988,((Data!$A$2:$A$3988=AS$1)*IF($B$8="Todas",1,--(AS$1=$B$8))*IF($B$5="Todos",1,--(YEAR(Data!$E$2:$E$3988)=$B$5))*IF($B$6="Todos",1,--("T"&ROUNDUP(MONTH(Data!$E$2:$E$3988)/3,0)=$B$6))*IF($B$7="Todos",1,--(TEXT(Data!$E$2:$E$3988,"[$-es-ES]mmmm")=$B$7))*--(CHOOSE(MATCH($B$4,{"Mensual","Trimestral","Anual"},0),TEXT(Data!$E$2:$E$3988,"yyyy-mm"),YEAR(Data!$E$2:$E$3988)&"-T"&ROUNDUP(MONTH(Data!$E$2:$E$3988)/3,0),TEXT(YEAR(Data!$E$2:$E$3988),"0"))=$AP6))>0)),NA()))} -> #N/A | AT6: {=IF(OR($AP6="",AT$1=""),NA(),IFERROR(AVERAGE(_xlfn._xlws.FILTER(Data!$K$2:$K$3988,((Data!$A$2:$A$3988=AT$1)*IF($B$8="Todas",1,--(AT$1=$B$8))*IF($B$5="Todos",1,--(YEAR(Data!$E$2:$E$3988)=$B$5))*IF($B$6="Todos",1,--("T"&ROUNDUP(MONTH(Data!$E$2:$E$3988)/3,0)=$B$6))*IF($B$7="Todos",1,--(TEXT(Data!$E$2:$E$3988,"[$-es-ES]mmmm")=$B$7))*--(CHOOSE(MATCH($B$4,{"Mensual","Trimestral","Anual"},0),TEXT(Data!$E$2:$E$3988,"yyyy-mm"),YEAR(Data!$E$2:$E$3988)&"-T"&ROUNDUP(MONTH(Data!$E$2:$E$3988)/3,0),TEXT(YEAR(Data!$E$2:$E$3988),"0"))=$AP6))>0)),NA()))} -> #N/A
A7: Mes | B7: Todos | D7: Ticket prom. | G7: Saldo medio | J7: Categorías activas | M7: Cuentas activas | AD7: Mayo | AH7: Mercado | AI7: 1819.04 | AQ7: {=IF(OR($AP7="",AQ$1=""),NA(),IFERROR(AVERAGE(_xlfn._xlws.FILTER(Data!$K$2:$K$3988,((Data!$A$2:$A$3988=AQ$1)*IF($B$8="Todas",1,--(AQ$1=$B$8))*IF($B$5="Todos",1,--(YEAR(Data!$E$2:$E$3988)=$B$5))*IF($B$6="Todos",1,--("T"&ROUNDUP(MONTH(Data!$E$2:$E$3988)/3,0)=$B$6))*IF($B$7="Todos",1,--(TEXT(Data!$E$2:$E$3988,"[$-es-ES]mmmm")=$B$7))*--(CHOOSE(MATCH($B$4,{"Mensual","Trimestral","Anual"},0),TEXT(Data!$E$2:$E$3988,"yyyy-mm"),YEAR(Data!$E$2:$E$3988)&"-T"&ROUNDUP(MONTH(Data!$E$2:$E$3988)/3,0),TEXT(YEAR(Data!$E$2:$E$3988),"0"))=$AP7))>0)),NA()))} -> #N/A | AR7: {=IF(OR($AP7="",AR$1=""),NA(),IFERROR(AVERAGE(_xlfn._xlws.FILTER(Data!$K$2:$K$3988,((Data!$A$2:$A$3988=AR$1)*IF($B$8="Todas",1,--(AR$1=$B$8))*IF($B$5="Todos",1,--(YEAR(Data!$E$2:$E$3988)=$B$5))*IF($B$6="Todos",1,--("T"&ROUNDUP(MONTH(Data!$E$2:$E$3988)/3,0)=$B$6))*IF($B$7="Todos",1,--(TEXT(Data!$E$2:$E$3988,"[$-es-ES]mmmm")=$B$7))*--(CHOOSE(MATCH($B$4,{"Mensual","Trimestral","Anual"},0),TEXT(Data!$E$2:$E$3988,"yyyy-mm"),YEAR(Data!$E$2:$E$3988)&"-T"&ROUNDUP(MONTH(Data!$E$2:$E$3988)/3,0),TEXT(YEAR(Data!$E$2:$E$3988),"0"))=$AP7))>0)),NA()))} -> #N/A | AS7: {=IF(OR($AP7="",AS$1=""),NA(),IFERROR(AVERAGE(_xlfn._xlws.FILTER(Data!$K$2:$K$3988,((Data!$A$2:$A$3988=AS$1)*IF($B$8="Todas",1,--(AS$1=$B$8))*IF($B$5="Todos",1,--(YEAR(Data!$E$2:$E$3988)=$B$5))*IF($B$6="Todos",1,--("T"&ROUNDUP(MONTH(Data!$E$2:$E$3988)/3,0)=$B$6))*IF($B$7="Todos",1,--(TEXT(Data!$E$2:$E$3988,"[$-es-ES]mmmm")=$B$7))*--(CHOOSE(MATCH($B$4,{"Mensual","Trimestral","Anual"},0),TEXT(Data!$E$2:$E$3988,"yyyy-mm"),YEAR(Data!$E$2:$E$3988)&"-T"&ROUNDUP(MONTH(Data!$E$2:$E$3988)/3,0),TEXT(YEAR(Data!$E$2:$E$3988),"0"))=$AP7))>0)),NA()))} -> #N/A | AT7: {=IF(OR($AP7="",AT$1=""),NA(),IFERROR(AVERAGE(_xlfn._xlws.FILTER(Data!$K$2:$K$3988,((Data!$A$2:$A$3988=AT$1)*IF($B$8="Todas",1,--(AT$1=$B$8))*IF($B$5="Todos",1,--(YEAR(Data!$E$2:$E$3988)=$B$5))*IF($B$6="Todos",1,--("T"&ROUNDUP(MONTH(Data!$E$2:$E$3988)/3,0)=$B$6))*IF($B$7="Todos",1,--(TEXT(Data!$E$2:$E$3988,"[$-es-ES]mmmm")=$B$7))*--(CHOOSE(MATCH($B$4,{"Mensual","Trimestral","Anual"},0),TEXT(Data!$E$2:$E$3988,"yyyy-mm"),YEAR(Data!$E$2:$E$3988)&"-T"&ROUNDUP(MONTH(Data!$E$2:$E$3988)/3,0),TEXT(YEAR(Data!$E$2:$E$3988),"0"))=$AP7))>0)),NA()))} -> #N/A
A8: Cuenta | B8: Todas | D8: {=_xlfn.LET(_xlpm.fechas,Data!$E$2:$E$3988,_xlpm.cuentas,Data!$A$2:$A$3988,_xlpm.imp,IFERROR(1*Data!$I$2:$I$3988,0),_xlpm.f,IF($B$5="Todos",1,--(YEAR(_xlpm.fechas)=$B$5))*IF($B$6="Todos",1,--("T"&ROUNDUP(MONTH(_xlpm.fechas)/3,0)=$B$6))*IF($B$7="Todos",1,--(TEXT(_xlpm.fechas,"[$-es-ES]mmmm")=$B$7))*IF($B$8="Todas",1,--(_xlpm.cuentas=$B$8)),IFERROR(SUMPRODUCT(ABS(_xlpm.imp)*_xlpm.f)/SUMPRODUCT(_xlpm.f),0))} -> 239.82154 | G8: {=_xlfn.LET(_xlpm.fechas,Data!$E$2:$E$3988,_xlpm.cuentas,Data!$A$2:$A$3988,_xlpm.sal,IFERROR(1*Data!$K$2:$K$3988,0),_xlpm.f,IF($B$5="Todos",1,--(YEAR(_xlpm.fechas)=$B$5))*IF($B$6="Todos",1,--("T"&ROUNDUP(MONTH(_xlpm.fechas)/3,0)=$B$6))*IF($B$7="Todos",1,--(TEXT(_xlpm.fechas,"[$-es-ES]mmmm")=$B$7))*IF($B$8="Todas",1,--(_xlpm.cuentas=$B$8)),IFERROR(SUMPRODUCT(_xlpm.sal*_xlpm.f)/SUMPRODUCT(_xlpm.f),0))} -> 6376.859 | J8: {=_xlfn.LET(_xlpm.fechas,Data!$E$2:$E$3988,_xlpm.cuentas,Data!$A$2:$A$3988,_xlpm.tipos,Data!$F$2:$F$3988,_xlpm.f,IF($B$5="Todos",1,--(YEAR(_xlpm.fechas)=$B$5))*IF($B$6="Todos",1,--("T"&ROUNDUP(MONTH(_xlpm.fechas)/3,0)=$B$6))*IF($B$7="Todos",1,--(TEXT(_xlpm.fechas,"[$-es-ES]mmmm")=$B$7))*IF($B$8="Todas",1,--(_xlpm.cuentas=$B$8)),IFERROR(COUNTA(_xlfn.UNIQUE(_xlfn._xlws.FILTER(_xlpm.tipos,_xlpm.f>0))),0))} -> 23 | M8: {=_xlfn.LET(_xlpm.fechas,Data!$E$2:$E$3988,_xlpm.cuentas,Data!$A$2:$A$3988,_xlpm.f,IF($B$5="Todos",1,--(YEAR(_xlpm.fechas)=$B$5))*IF($B$6="Todos",1,--("T"&ROUNDUP(MONTH(_xlpm.fechas)/3,0)=$B$6))*IF($B$7="Todos",1,--(TEXT(_xlpm.fechas,"[$-es-ES]mmmm")=$B$7))*IF($B$8="Todas",1,--(_xlpm.cuentas=$B$8)),IFERROR(COUNTA(_xlfn.UNIQUE(_xlfn._xlws.FILTER(_xlpm.cuentas,_xlpm.f>0))),0))} -> 3 | AD8: Junio | AH8: Ahorros | AI8: 1500 | AQ8: {=IF(OR($AP8="",AQ$1=""),NA(),IFERROR(AVERAGE(_xlfn._xlws.FILTER(Data!$K$2:$K$3988,((Data!$A$2:$A$3988=AQ$1)*IF($B$8="Todas",1,--(AQ$1=$B$8))*IF($B$5="Todos",1,--(YEAR(Data!$E$2:$E$3988)=$B$5))*IF($B$6="Todos",1,--("T"&ROUNDUP(MONTH(Data!$E$2:$E$3988)/3,0)=$B$6))*IF($B$7="Todos",1,--(TEXT(Data!$E$2:$E$3988,"[$-es-ES]mmmm")=$B$7))*--(CHOOSE(MATCH($B$4,{"Mensual","Trimestral","Anual"},0),TEXT(Data!$E$2:$E$3988,"yyyy-mm"),YEAR(Data!$E$2:$E$3988)&"-T"&ROUNDUP(MONTH(Data!$E$2:$E$3988)/3,0),TEXT(YEAR(Data!$E$2:$E$3988),"0"))=$AP8))>0)),NA()))} -> #N/A | AR8: {=IF(OR($AP8="",AR$1=""),NA(),IFERROR(AVERAGE(_xlfn._xlws.FILTER(Data!$K$2:$K$3988,((Data!$A$2:$A$3988=AR$1)*IF($B$8="Todas",1,--(AR$1=$B$8))*IF($B$5="Todos",1,--(YEAR(Data!$E$2:$E$3988)=$B$5))*IF($B$6="Todos",1,--("T"&ROUNDUP(MONTH(Data!$E$2:$E$3988)/3,0)=$B$6))*IF($B$7="Todos",1,--(TEXT(Data!$E$2:$E$3988,"[$-es-ES]mmmm")=$B$7))*--(CHOOSE(MATCH($B$4,{"Mensual","Trimestral","Anual"},0),TEXT(Data!$E$2:$E$3988,"yyyy-mm"),YEAR(Data!$E$2:$E$3988)&"-T"&ROUNDUP(MONTH(Data!$E$2:$E$3988)/3,0),TEXT(YEAR(Data!$E$2:$E$3988),"0"))=$AP8))>0)),NA()))} -> #N/A | AS8: {=IF(OR($AP8="",AS$1=""),NA(),IFERROR(AVERAGE(_xlfn._xlws.FILTER(Data!$K$2:$K$3988,((Data!$A$2:$A$3988=AS$1)*IF($B$8="Todas",1,--(AS$1=$B$8))*IF($B$5="Todos",1,--(YEAR(Data!$E$2:$E$3988)=$B$5))*IF($B$6="Todos",1,--("T"&ROUNDUP(MONTH(Data!$E$2:$E$3988)/3,0)=$B$6))*IF($B$7="Todos",1,--(TEXT(Data!$E$2:$E$3988,"[$-es-ES]mmmm")=$B$7))*--(CHOOSE(MATCH($B$4,{"Mensual","Trimestral","Anual"},0),TEXT(Data!$E$2:$E$3988,"yyyy-mm"),YEAR(Data!$E$2:$E$3988)&"-T"&ROUNDUP(MONTH(Data!$E$2:$E$3988)/3,0),TEXT(YEAR(Data!$E$2:$E$3988),"0"))=$AP8))>0)),NA()))} -> #N/A | AT8: {=IF(OR($AP8="",AT$1=""),NA(),IFERROR(AVERAGE(_xlfn._xlws.FILTER(Data!$K$2:$K$3988,((Data!$A$2:$A$3988=AT$1)*IF($B$8="Todas",1,--(AT$1=$B$8))*IF($B$5="Todos",1,--(YEAR(Data!$E$2:$E$3988)=$B$5))*IF($B$6="Todos",1,--("T"&ROUNDUP(MONTH(Data!$E$2:$E$3988)/3,0)=$B$6))*IF($B$7="Todos",1,--(TEXT(Data!$E$2:$E$3988,"[$-es-ES]mmmm")=$B$7))*--(CHOOSE(MATCH($B$4,{"Mensual","Trimestral","Anual"},0),TEXT(Data!$E$2:$E$3988,"yyyy-mm"),YEAR(Data!$E$2:$E$3988)&"-T"&ROUNDUP(MONTH(Data!$E$2:$E$3988)/3,0),TEXT(YEAR(Data!$E$2:$E$3988),"0"))=$AP8))>0)),NA()))} -> #N/A
AD9: Julio | AH9: Servicios | AI9: 679.82 | AQ9: {=IF(OR($AP9="",AQ$1=""),NA(),IFERROR(AVERAGE(_xlfn._xlws.FILTER(Data!$K$2:$K$3988,((Data!$A$2:$A$3988=AQ$1)*IF($B$8="Todas",1,--(AQ$1=$B$8))*IF($B$5="Todos",1,--(YEAR(Data!$E$2:$E$3988)=$B$5))*IF($B$6="Todos",1,--("T"&ROUNDUP(MONTH(Data!$E$2:$E$3988)/3,0)=$B$6))*IF($B$7="Todos",1,--(TEXT(Data!$E$2:$E$3988,"[$-es-ES]mmmm")=$B$7))*--(CHOOSE(MATCH($B$4,{"Mensual","Trimestral","Anual"},0),TEXT(Data!$E$2:$E$3988,"yyyy-mm"),YEAR(Data!$E$2:$E$3988)&"-T"&ROUNDUP(MONTH(Data!$E$2:$E$3988)/3,0),TEXT(YEAR(Data!$E$2:$E$3988),"0"))=$AP9))>0)),NA()))} -> #N/A | AR9: {=IF(OR($AP9="",AR$1=""),NA(),IFERROR(AVERAGE(_xlfn._xlws.FILTER(Data!$K$2:$K$3988,((Data!$A$2:$A$3988=AR$1)*IF($B$8="Todas",1,--(AR$1=$B$8))*IF($B$5="Todos",1,--(YEAR(Data!$E$2:$E$3988)=$B$5))*IF($B$6="Todos",1,--("T"&ROUNDUP(MONTH(Data!$E$2:$E$3988)/3,0)=$B$6))*IF($B$7="Todos",1,--(TEXT(Data!$E$2:$E$3988,"[$-es-ES]mmmm")=$B$7))*--(CHOOSE(MATCH($B$4,{"Mensual","Trimestral","Anual"},0),TEXT(Data!$E$2:$E$3988,"yyyy-mm"),YEAR(Data!$E$2:$E$3988)&"-T"&ROUNDUP(MONTH(Data!$E$2:$E$3988)/3,0),TEXT(YEAR(Data!$E$2:$E$3988),"0"))=$AP9))>0)),NA()))} -> #N/A | AS9: {=IF(OR($AP9="",AS$1=""),NA(),IFERROR(AVERAGE(_xlfn._xlws.FILTER(Data!$K$2:$K$3988,((Data!$A$2:$A$3988=AS$1)*IF($B$8="Todas",1,--(AS$1=$B$8))*IF($B$5="Todos",1,--(YEAR(Data!$E$2:$E$3988)=$B$5))*IF($B$6="Todos",1,--("T"&ROUNDUP(MONTH(Data!$E$2:$E$3988)/3,0)=$B$6))*IF($B$7="Todos",1,--(TEXT(Data!$E$2:$E$3988,"[$-es-ES]mmmm")=$B$7))*--(CHOOSE(MATCH($B$4,{"Mensual","Trimestral","Anual"},0),TEXT(Data!$E$2:$E$3988,"yyyy-mm"),YEAR(Data!$E$2:$E$3988)&"-T"&ROUNDUP(MONTH(Data!$E$2:$E$3988)/3,0),TEXT(YEAR(Data!$E$2:$E$3988),"0"))=$AP9))>0)),NA()))} -> #N/A | AT9: {=IF(OR($AP9="",AT$1=""),NA(),IFERROR(AVERAGE(_xlfn._xlws.FILTER(Data!$K$2:$K$3988,((Data!$A$2:$A$3988=AT$1)*IF($B$8="Todas",1,--(AT$1=$B$8))*IF($B$5="Todos",1,--(YEAR(Data!$E$2:$E$3988)=$B$5))*IF($B$6="Todos",1,--("T"&ROUNDUP(MONTH(Data!$E$2:$E$3988)/3,0)=$B$6))*IF($B$7="Todos",1,--(TEXT(Data!$E$2:$E$3988,"[$-es-ES]mmmm")=$B$7))*--(CHOOSE(MATCH($B$4,{"Mensual","Trimestral","Anual"},0),TEXT(Data!$E$2:$E$3988,"yyyy-mm"),YEAR(Data!$E$2:$E$3988)&"-T"&ROUNDUP(MONTH(Data!$E$2:$E$3988)/3,0),TEXT(YEAR(Data!$E$2:$E$3988),"0"))=$AP9))>0)),NA()))} -> #N/A
A10: Los filtros actualizan KPIs y gráficos. El gráfico por categoría muestra egresos. | AD10: Agosto | AH10: Suscripciones | AI10: 662.26 | AQ10: {=IF(OR($AP10="",AQ$1=""),NA(),IFERROR(AVERAGE(_xlfn._xlws.FILTER(Data!$K$2:$K$3988,((Data!$A$2:$A$3988=AQ$1)*IF($B$8="Todas",1,--(AQ$1=$B$8))*IF($B$5="Todos",1,--(YEAR(Data!$E$2:$E$3988)=$B$5))*IF($B$6="Todos",1,--("T"&ROUNDUP(MONTH(Data!$E$2:$E$3988)/3,0)=$B$6))*IF($B$7="Todos",1,--(TEXT(Data!$E$2:$E$3988,"[$-es-ES]mmmm")=$B$7))*--(CHOOSE(MATCH($B$4,{"Mensual","Trimestral","Anual"},0),TEXT(Data!$E$2:$E$3988,"yyyy-mm"),YEAR(Data!$E$2:$E$3988)&"-T"&ROUNDUP(MONTH(Data!$E$2:$E$3988)/3,0),TEXT(YEAR(Data!$E$2:$E$3988),"0"))=$AP10))>0)),NA()))} -> #N/A | AR10: {=IF(OR($AP10="",AR$1=""),NA(),IFERROR(AVERAGE(_xlfn._xlws.FILTER(Data!$K$2:$K$3988,((Data!$A$2:$A$3988=AR$1)*IF($B$8="Todas",1,--(AR$1=$B$8))*IF($B$5="Todos",1,--(YEAR(Data!$E$2:$E$3988)=$B$5))*IF($B$6="Todos",1,--("T"&ROUNDUP(MONTH(Data!$E$2:$E$3988)/3,0)=$B$6))*IF($B$7="Todos",1,--(TEXT(Data!$E$2:$E$3988,"[$-es-ES]mmmm")=$B$7))*--(CHOOSE(MATCH($B$4,{"Mensual","Trimestral","Anual"},0),TEXT(Data!$E$2:$E$3988,"yyyy-mm"),YEAR(Data!$E$2:$E$3988)&"-T"&ROUNDUP(MONTH(Data!$E$2:$E$3988)/3,0),TEXT(YEAR(Data!$E$2:$E$3988),"0"))=$AP10))>0)),NA()))} -> #N/A | AS10: {=IF(OR($AP10="",AS$1=""),NA(),IFERROR(AVERAGE(_xlfn._xlws.FILTER(Data!$K$2:$K$3988,((Data!$A$2:$A$3988=AS$1)*IF($B$8="Todas",1,--(AS$1=$B$8))*IF($B$5="Todos",1,--(YEAR(Data!$E$2:$E$3988)=$B$5))*IF($B$6="Todos",1,--("T"&ROUNDUP(MONTH(Data!$E$2:$E$3988)/3,0)=$B$6))*IF($B$7="Todos",1,--(TEXT(Data!$E$2:$E$3988,"[$-es-ES]mmmm")=$B$7))*--(CHOOSE(MATCH($B$4,{"Mensual","Trimestral","Anual"},0),TEXT(Data!$E$2:$E$3988,"yyyy-mm"),YEAR(Data!$E$2:$E$3988)&"-T"&ROUNDUP(MONTH(Data!$E$2:$E$3988)/3,0),TEXT(YEAR(Data!$E$2:$E$3988),"0"))=$AP10))>0)),NA()))} -> #N/A | AT10: {=IF(OR($AP10="",AT$1=""),NA(),IFERROR(AVERAGE(_xlfn._xlws.FILTER(Data!$K$2:$K$3988,((Data!$A$2:$A$3988=AT$1)*IF($B$8="Todas",1,--(AT$1=$B$8))*IF($B$5="Todos",1,--(YEAR(Data!$E$2:$E$3988)=$B$5))*IF($B$6="Todos",1,--("T"&ROUNDUP(MONTH(Data!$E$2:$E$3988)/3,0)=$B$6))*IF($B$7="Todos",1,--(TEXT(Data!$E$2:$E$3988,"[$-es-ES]mmmm")=$B$7))*--(CHOOSE(MATCH($B$4,{"Mensual","Trimestral","Anual"},0),TEXT(Data!$E$2:$E$3988,"yyyy-mm"),YEAR(Data!$E$2:$E$3988)&"-T"&ROUNDUP(MONTH(Data!$E$2:$E$3988)/3,0),TEXT(YEAR(Data!$E$2:$E$3988),"0"))=$AP10))>0)),NA()))} -> #N/A
AD11: Septiembre | AH11: Seguro | AI11: 479.36 | AQ11: {=IF(OR($AP11="",AQ$1=""),NA(),IFERROR(AVERAGE(_xlfn._xlws.FILTER(Data!$K$2:$K$3988,((Data!$A$2:$A$3988=AQ$1)*IF($B$8="Todas",1,--(AQ$1=$B$8))*IF($B$5="Todos",1,--(YEAR(Data!$E$2:$E$3988)=$B$5))*IF($B$6="Todos",1,--("T"&ROUNDUP(MONTH(Data!$E$2:$E$3988)/3,0)=$B$6))*IF($B$7="Todos",1,--(TEXT(Data!$E$2:$E$3988,"[$-es-ES]mmmm")=$B$7))*--(CHOOSE(MATCH($B$4,{"Mensual","Trimestral","Anual"},0),TEXT(Data!$E$2:$E$3988,"yyyy-mm"),YEAR(Data!$E$2:$E$3988)&"-T"&ROUNDUP(MONTH(Data!$E$2:$E$3988)/3,0),TEXT(YEAR(Data!$E$2:$E$3988),"0"))=$AP11))>0)),NA()))} -> #N/A | AR11: {=IF(OR($AP11="",AR$1=""),NA(),IFERROR(AVERAGE(_xlfn._xlws.FILTER(Data!$K$2:$K$3988,((Data!$A$2:$A$3988=AR$1)*IF($B$8="Todas",1,--(AR$1=$B$8))*IF($B$5="Todos",1,--(YEAR(Data!$E$2:$E$3988)=$B$5))*IF($B$6="Todos",1,--("T"&ROUNDUP(MONTH(Data!$E$2:$E$3988)/3,0)=$B$6))*IF($B$7="Todos",1,--(TEXT(Data!$E$2:$E$3988,"[$-es-ES]mmmm")=$B$7))*--(CHOOSE(MATCH($B$4,{"Mensual","Trimestral","Anual"},0),TEXT(Data!$E$2:$E$3988,"yyyy-mm"),YEAR(Data!$E$2:$E$3988)&"-T"&ROUNDUP(MONTH(Data!$E$2:$E$3988)/3,0),TEXT(YEAR(Data!$E$2:$E$3988),"0"))=$AP11))>0)),NA()))} -> #N/A | AS11: {=IF(OR($AP11="",AS$1=""),NA(),IFERROR(AVERAGE(_xlfn._xlws.FILTER(Data!$K$2:$K$3988,((Data!$A$2:$A$3988=AS$1)*IF($B$8="Todas",1,--(AS$1=$B$8))*IF($B$5="Todos",1,--(YEAR(Data!$E$2:$E$3988)=$B$5))*IF($B$6="Todos",1,--("T"&ROUNDUP(MONTH(Data!$E$2:$E$3988)/3,0)=$B$6))*IF($B$7="Todos",1,--(TEXT(Data!$E$2:$E$3988,"[$-es-ES]mmmm")=$B$7))*--(CHOOSE(MATCH($B$4,{"Mensual","Trimestral","Anual"},0),TEXT(Data!$E$2:$E$3988,"yyyy-mm"),YEAR(Data!$E$2:$E$3988)&"-T"&ROUNDUP(MONTH(Data!$E$2:$E$3988)/3,0),TEXT(YEAR(Data!$E$2:$E$3988),"0"))=$AP11))>0)),NA()))} -> #N/A | AT11: {=IF(OR($AP11="",AT$1=""),NA(),IFERROR(AVERAGE(_xlfn._xlws.FILTER(Data!$K$2:$K$3988,((Data!$A$2:$A$3988=AT$1)*IF($B$8="Todas",1,--(AT$1=$B$8))*IF($B$5="Todos",1,--(YEAR(Data!$E$2:$E$3988)=$B$5))*IF($B$6="Todos",1,--("T"&ROUNDUP(MONTH(Data!$E$2:$E$3988)/3,0)=$B$6))*IF($B$7="Todos",1,--(TEXT(Data!$E$2:$E$3988,"[$-es-ES]mmmm")=$B$7))*--(CHOOSE(MATCH($B$4,{"Mensual","Trimestral","Anual"},0),TEXT(Data!$E$2:$E$3988,"yyyy-mm"),YEAR(Data!$E$2:$E$3988)&"-T"&ROUNDUP(MONTH(Data!$E$2:$E$3988)/3,0),TEXT(YEAR(Data!$E$2:$E$3988),"0"))=$AP11))>0)),NA()))} -> #N/A
AD12: Octubre | AH12: Padres | AI12: 417.16 | AQ12: {=IF(OR($AP12="",AQ$1=""),NA(),IFERROR(AVERAGE(_xlfn._xlws.FILTER(Data!$K$2:$K$3988,((Data!$A$2:$A$3988=AQ$1)*IF($B$8="Todas",1,--(AQ$1=$B$8))*IF($B$5="Todos",1,--(YEAR(Data!$E$2:$E$3988)=$B$5))*IF($B$6="Todos",1,--("T"&ROUNDUP(MONTH(Data!$E$2:$E$3988)/3,0)=$B$6))*IF($B$7="Todos",1,--(TEXT(Data!$E$2:$E$3988,"[$-es-ES]mmmm")=$B$7))*--(CHOOSE(MATCH($B$4,{"Mensual","Trimestral","Anual"},0),TEXT(Data!$E$2:$E$3988,"yyyy-mm"),YEAR(Data!$E$2:$E$3988)&"-T"&ROUNDUP(MONTH(Data!$E$2:$E$3988)/3,0),TEXT(YEAR(Data!$E$2:$E$3988),"0"))=$AP12))>0)),NA()))} -> #N/A | AR12: {=IF(OR($AP12="",AR$1=""),NA(),IFERROR(AVERAGE(_xlfn._xlws.FILTER(Data!$K$2:$K$3988,((Data!$A$2:$A$3988=AR$1)*IF($B$8="Todas",1,--(AR$1=$B$8))*IF($B$5="Todos",1,--(YEAR(Data!$E$2:$E$3988)=$B$5))*IF($B$6="Todos",1,--("T"&ROUNDUP(MONTH(Data!$E$2:$E$3988)/3,0)=$B$6))*IF($B$7="Todos",1,--(TEXT(Data!$E$2:$E$3988,"[$-es-ES]mmmm")=$B$7))*--(CHOOSE(MATCH($B$4,{"Mensual","Trimestral","Anual"},0),TEXT(Data!$E$2:$E$3988,"yyyy-mm"),YEAR(Data!$E$2:$E$3988)&"-T"&ROUNDUP(MONTH(Data!$E$2:$E$3988)/3,0),TEXT(YEAR(Data!$E$2:$E$3988),"0"))=$AP12))>0)),NA()))} -> #N/A | AS12: {=IF(OR($AP12="",AS$1=""),NA(),IFERROR(AVERAGE(_xlfn._xlws.FILTER(Data!$K$2:$K$3988,((Data!$A$2:$A$3988=AS$1)*IF($B$8="Todas",1,--(AS$1=$B$8))*IF($B$5="Todos",1,--(YEAR(Data!$E$2:$E$3988)=$B$5))*IF($B$6="Todos",1,--("T"&ROUNDUP(MONTH(Data!$E$2:$E$3988)/3,0)=$B$6))*IF($B$7="Todos",1,--(TEXT(Data!$E$2:$E$3988,"[$-es-ES]mmmm")=$B$7))*--(CHOOSE(MATCH($B$4,{"Mensual","Trimestral","Anual"},0),TEXT(Data!$E$2:$E$3988,"yyyy-mm"),YEAR(Data!$E$2:$E$3988)&"-T"&ROUNDUP(MONTH(Data!$E$2:$E$3988)/3,0),TEXT(YEAR(Data!$E$2:$E$3988),"0"))=$AP12))>0)),NA()))} -> #N/A | AT12: {=IF(OR($AP12="",AT$1=""),NA(),IFERROR(AVERAGE(_xlfn._xlws.FILTER(Data!$K$2:$K$3988,((Data!$A$2:$A$3988=AT$1)*IF($B$8="Todas",1,--(AT$1=$B$8))*IF($B$5="Todos",1,--(YEAR(Data!$E$2:$E$3988)=$B$5))*IF($B$6="Todos",1,--("T"&ROUNDUP(MONTH(Data!$E$2:$E$3988)/3,0)=$B$6))*IF($B$7="Todos",1,--(TEXT(Data!$E$2:$E$3988,"[$-es-ES]mmmm")=$B$7))*--(CHOOSE(MATCH($B$4,{"Mensual","Trimestral","Anual"},0),TEXT(Data!$E$2:$E$3988,"yyyy-mm"),YEAR(Data!$E$2:$E$3988)&"-T"&ROUNDUP(MONTH(Data!$E$2:$E$3988)/3,0),TEXT(YEAR(Data!$E$2:$E$3988),"0"))=$AP12))>0)),NA()))} -> #N/A
AD13: Noviembre | AH13: Transporte | AI13: 327 | AQ13: {=IF(OR($AP13="",AQ$1=""),NA(),IFERROR(AVERAGE(_xlfn._xlws.FILTER(Data!$K$2:$K$3988,((Data!$A$2:$A$3988=AQ$1)*IF($B$8="Todas",1,--(AQ$1=$B$8))*IF($B$5="Todos",1,--(YEAR(Data!$E$2:$E$3988)=$B$5))*IF($B$6="Todos",1,--("T"&ROUNDUP(MONTH(Data!$E$2:$E$3988)/3,0)=$B$6))*IF($B$7="Todos",1,--(TEXT(Data!$E$2:$E$3988,"[$-es-ES]mmmm")=$B$7))*--(CHOOSE(MATCH($B$4,{"Mensual","Trimestral","Anual"},0),TEXT(Data!$E$2:$E$3988,"yyyy-mm"),YEAR(Data!$E$2:$E$3988)&"-T"&ROUNDUP(MONTH(Data!$E$2:$E$3988)/3,0),TEXT(YEAR(Data!$E$2:$E$3988),"0"))=$AP13))>0)),NA()))} -> #N/A | AR13: {=IF(OR($AP13="",AR$1=""),NA(),IFERROR(AVERAGE(_xlfn._xlws.FILTER(Data!$K$2:$K$3988,((Data!$A$2:$A$3988=AR$1)*IF($B$8="Todas",1,--(AR$1=$B$8))*IF($B$5="Todos",1,--(YEAR(Data!$E$2:$E$3988)=$B$5))*IF($B$6="Todos",1,--("T"&ROUNDUP(MONTH(Data!$E$2:$E$3988)/3,0)=$B$6))*IF($B$7="Todos",1,--(TEXT(Data!$E$2:$E$3988,"[$-es-ES]mmmm")=$B$7))*--(CHOOSE(MATCH($B$4,{"Mensual","Trimestral","Anual"},0),TEXT(Data!$E$2:$E$3988,"yyyy-mm"),YEAR(Data!$E$2:$E$3988)&"-T"&ROUNDUP(MONTH(Data!$E$2:$E$3988)/3,0),TEXT(YEAR(Data!$E$2:$E$3988),"0"))=$AP13))>0)),NA()))} -> #N/A | AS13: {=IF(OR($AP13="",AS$1=""),NA(),IFERROR(AVERAGE(_xlfn._xlws.FILTER(Data!$K$2:$K$3988,((Data!$A$2:$A$3988=AS$1)*IF($B$8="Todas",1,--(AS$1=$B$8))*IF($B$5="Todos",1,--(YEAR(Data!$E$2:$E$3988)=$B$5))*IF($B$6="Todos",1,--("T"&ROUNDUP(MONTH(Data!$E$2:$E$3988)/3,0)=$B$6))*IF($B$7="Todos",1,--(TEXT(Data!$E$2:$E$3988,"[$-es-ES]mmmm")=$B$7))*--(CHOOSE(MATCH($B$4,{"Mensual","Trimestral","Anual"},0),TEXT(Data!$E$2:$E$3988,"yyyy-mm"),YEAR(Data!$E$2:$E$3988)&"-T"&ROUNDUP(MONTH(Data!$E$2:$E$3988)/3,0),TEXT(YEAR(Data!$E$2:$E$3988),"0"))=$AP13))>0)),NA()))} -> #N/A | AT13: {=IF(OR($AP13="",AT$1=""),NA(),IFERROR(AVERAGE(_xlfn._xlws.FILTER(Data!$K$2:$K$3988,((Data!$A$2:$A$3988=AT$1)*IF($B$8="Todas",1,--(AT$1=$B$8))*IF($B$5="Todos",1,--(YEAR(Data!$E$2:$E$3988)=$B$5))*IF($B$6="Todos",1,--("T"&ROUNDUP(MONTH(Data!$E$2:$E$3988)/3,0)=$B$6))*IF($B$7="Todos",1,--(TEXT(Data!$E$2:$E$3988,"[$-es-ES]mmmm")=$B$7))*--(CHOOSE(MATCH($B$4,{"Mensual","Trimestral","Anual"},0),TEXT(Data!$E$2:$E$3988,"yyyy-mm"),YEAR(Data!$E$2:$E$3988)&"-T"&ROUNDUP(MONTH(Data!$E$2:$E$3988)/3,0),TEXT(YEAR(Data!$E$2:$E$3988),"0"))=$AP13))>0)),NA()))} -> #N/A
AD14: Diciembre | AH14: Financiero | AI14: 320.23 | AQ14: {=IF(OR($AP14="",AQ$1=""),NA(),IFERROR(AVERAGE(_xlfn._xlws.FILTER(Data!$K$2:$K$3988,((Data!$A$2:$A$3988=AQ$1)*IF($B$8="Todas",1,--(AQ$1=$B$8))*IF($B$5="Todos",1,--(YEAR(Data!$E$2:$E$3988)=$B$5))*IF($B$6="Todos",1,--("T"&ROUNDUP(MONTH(Data!$E$2:$E$3988)/3,0)=$B$6))*IF($B$7="Todos",1,--(TEXT(Data!$E$2:$E$3988,"[$-es-ES]mmmm")=$B$7))*--(CHOOSE(MATCH($B$4,{"Mensual","Trimestral","Anual"},0),TEXT(Data!$E$2:$E$3988,"yyyy-mm"),YEAR(Data!$E$2:$E$3988)&"-T"&ROUNDUP(MONTH(Data!$E$2:$E$3988)/3,0),TEXT(YEAR(Data!$E$2:$E$3988),"0"))=$AP14))>0)),NA()))} -> #N/A | AR14: {=IF(OR($AP14="",AR$1=""),NA(),IFERROR(AVERAGE(_xlfn._xlws.FILTER(Data!$K$2:$K$3988,((Data!$A$2:$A$3988=AR$1)*IF($B$8="Todas",1,--(AR$1=$B$8))*IF($B$5="Todos",1,--(YEAR(Data!$E$2:$E$3988)=$B$5))*IF($B$6="Todos",1,--("T"&ROUNDUP(MONTH(Data!$E$2:$E$3988)/3,0)=$B$6))*IF($B$7="Todos",1,--(TEXT(Data!$E$2:$E$3988,"[$-es-ES]mmmm")=$B$7))*--(CHOOSE(MATCH($B$4,{"Mensual","Trimestral","Anual"},0),TEXT(Data!$E$2:$E$3988,"yyyy-mm"),YEAR(Data!$E$2:$E$3988)&"-T"&ROUNDUP(MONTH(Data!$E$2:$E$3988)/3,0),TEXT(YEAR(Data!$E$2:$E$3988),"0"))=$AP14))>0)),NA()))} -> #N/A | AS14: {=IF(OR($AP14="",AS$1=""),NA(),IFERROR(AVERAGE(_xlfn._xlws.FILTER(Data!$K$2:$K$3988,((Data!$A$2:$A$3988=AS$1)*IF($B$8="Todas",1,--(AS$1=$B$8))*IF($B$5="Todos",1,--(YEAR(Data!$E$2:$E$3988)=$B$5))*IF($B$6="Todos",1,--("T"&ROUNDUP(MONTH(Data!$E$2:$E$3988)/3,0)=$B$6))*IF($B$7="Todos",1,--(TEXT(Data!$E$2:$E$3988,"[$-es-ES]mmmm")=$B$7))*--(CHOOSE(MATCH($B$4,{"Mensual","Trimestral","Anual"},0),TEXT(Data!$E$2:$E$3988,"yyyy-mm"),YEAR(Data!$E$2:$E$3988)&"-T"&ROUNDUP(MONTH(Data!$E$2:$E$3988)/3,0),TEXT(YEAR(Data!$E$2:$E$3988),"0"))=$AP14))>0)),NA()))} -> #N/A | AT14: {=IF(OR($AP14="",AT$1=""),NA(),IFERROR(AVERAGE(_xlfn._xlws.FILTER(Data!$K$2:$K$3988,((Data!$A$2:$A$3988=AT$1)*IF($B$8="Todas",1,--(AT$1=$B$8))*IF($B$5="Todos",1,--(YEAR(Data!$E$2:$E$3988)=$B$5))*IF($B$6="Todos",1,--("T"&ROUNDUP(MONTH(Data!$E$2:$E$3988)/3,0)=$B$6))*IF($B$7="Todos",1,--(TEXT(Data!$E$2:$E$3988,"[$-es-ES]mmmm")=$B$7))*--(CHOOSE(MATCH($B$4,{"Mensual","Trimestral","Anual"},0),TEXT(Data!$E$2:$E$3988,"yyyy-mm"),YEAR(Data!$E$2:$E$3988)&"-T"&ROUNDUP(MONTH(Data!$E$2:$E$3988)/3,0),TEXT(YEAR(Data!$E$2:$E$3988),"0"))=$AP14))>0)),NA()))} -> #N/A
AH15: Navidad | AI15: 252 | AQ15: {=IF(OR($AP15="",AQ$1=""),NA(),IFERROR(AVERAGE(_xlfn._xlws.FILTER(Data!$K$2:$K$3988,((Data!$A$2:$A$3988=AQ$1)*IF($B$8="Todas",1,--(AQ$1=$B$8))*IF($B$5="Todos",1,--(YEAR(Data!$E$2:$E$3988)=$B$5))*IF($B$6="Todos",1,--("T"&ROUNDUP(MONTH(Data!$E$2:$E$3988)/3,0)=$B$6))*IF($B$7="Todos",1,--(TEXT(Data!$E$2:$E$3988,"[$-es-ES]mmmm")=$B$7))*--(CHOOSE(MATCH($B$4,{"Mensual","Trimestral","Anual"},0),TEXT(Data!$E$2:$E$3988,"yyyy-mm"),YEAR(Data!$E$2:$E$3988)&"-T"&ROUNDUP(MONTH(Data!$E$2:$E$3988)/3,0),TEXT(YEAR(Data!$E$2:$E$3988),"0"))=$AP15))>0)),NA()))} -> #N/A | AR15: {=IF(OR($AP15="",AR$1=""),NA(),IFERROR(AVERAGE(_xlfn._xlws.FILTER(Data!$K$2:$K$3988,((Data!$A$2:$A$3988=AR$1)*IF($B$8="Todas",1,--(AR$1=$B$8))*IF($B$5="Todos",1,--(YEAR(Data!$E$2:$E$3988)=$B$5))*IF($B$6="Todos",1,--("T"&ROUNDUP(MONTH(Data!$E$2:$E$3988)/3,0)=$B$6))*IF($B$7="Todos",1,--(TEXT(Data!$E$2:$E$3988,"[$-es-ES]mmmm")=$B$7))*--(CHOOSE(MATCH($B$4,{"Mensual","Trimestral","Anual"},0),TEXT(Data!$E$2:$E$3988,"yyyy-mm"),YEAR(Data!$E$2:$E$3988)&"-T"&ROUNDUP(MONTH(Data!$E$2:$E$3988)/3,0),TEXT(YEAR(Data!$E$2:$E$3988),"0"))=$AP15))>0)),NA()))} -> #N/A | AS15: {=IF(OR($AP15="",AS$1=""),NA(),IFERROR(AVERAGE(_xlfn._xlws.FILTER(Data!$K$2:$K$3988,((Data!$A$2:$A$3988=AS$1)*IF($B$8="Todas",1,--(AS$1=$B$8))*IF($B$5="Todos",1,--(YEAR(Data!$E$2:$E$3988)=$B$5))*IF($B$6="Todos",1,--("T"&ROUNDUP(MONTH(Data!$E$2:$E$3988)/3,0)=$B$6))*IF($B$7="Todos",1,--(TEXT(Data!$E$2:$E$3988,"[$-es-ES]mmmm")=$B$7))*--(CHOOSE(MATCH($B$4,{"Mensual","Trimestral","Anual"},0),TEXT(Data!$E$2:$E$3988,"yyyy-mm"),YEAR(Data!$E$2:$E$3988)&"-T"&ROUNDUP(MONTH(Data!$E$2:$E$3988)/3,0),TEXT(YEAR(Data!$E$2:$E$3988),"0"))=$AP15))>0)),NA()))} -> #N/A | AT15: {=IF(OR($AP15="",AT$1=""),NA(),IFERROR(AVERAGE(_xlfn._xlws.FILTER(Data!$K$2:$K$3988,((Data!$A$2:$A$3988=AT$1)*IF($B$8="Todas",1,--(AT$1=$B$8))*IF($B$5="Todos",1,--(YEAR(Data!$E$2:$E$3988)=$B$5))*IF($B$6="Todos",1,--("T"&ROUNDUP(MONTH(Data!$E$2:$E$3988)/3,0)=$B$6))*IF($B$7="Todos",1,--(TEXT(Data!$E$2:$E$3988,"[$-es-ES]mmmm")=$B$7))*--(CHOOSE(MATCH($B$4,{"Mensual","Trimestral","Anual"},0),TEXT(Data!$E$2:$E$3988,"yyyy-mm"),YEAR(Data!$E$2:$E$3988)&"-T"&ROUNDUP(MONTH(Data!$E$2:$E$3988)/3,0),TEXT(YEAR(Data!$E$2:$E$3988),"0"))=$AP15))>0)),NA()))} -> #N/A
AH16: Vacaciones | AI16: 191.9 | AQ16: {=IF(OR($AP16="",AQ$1=""),NA(),IFERROR(AVERAGE(_xlfn._xlws.FILTER(Data!$K$2:$K$3988,((Data!$A$2:$A$3988=AQ$1)*IF($B$8="Todas",1,--(AQ$1=$B$8))*IF($B$5="Todos",1,--(YEAR(Data!$E$2:$E$3988)=$B$5))*IF($B$6="Todos",1,--("T"&ROUNDUP(MONTH(Data!$E$2:$E$3988)/3,0)=$B$6))*IF($B$7="Todos",1,--(TEXT(Data!$E$2:$E$3988,"[$-es-ES]mmmm")=$B$7))*--(CHOOSE(MATCH($B$4,{"Mensual","Trimestral","Anual"},0),TEXT(Data!$E$2:$E$3988,"yyyy-mm"),YEAR(Data!$E$2:$E$3988)&"-T"&ROUNDUP(MONTH(Data!$E$2:$E$3988)/3,0),TEXT(YEAR(Data!$E$2:$E$3988),"0"))=$AP16))>0)),NA()))} -> #N/A | AR16: {=IF(OR($AP16="",AR$1=""),NA(),IFERROR(AVERAGE(_xlfn._xlws.FILTER(Data!$K$2:$K$3988,((Data!$A$2:$A$3988=AR$1)*IF($B$8="Todas",1,--(AR$1=$B$8))*IF($B$5="Todos",1,--(YEAR(Data!$E$2:$E$3988)=$B$5))*IF($B$6="Todos",1,--("T"&ROUNDUP(MONTH(Data!$E$2:$E$3988)/3,0)=$B$6))*IF($B$7="Todos",1,--(TEXT(Data!$E$2:$E$3988,"[$-es-ES]mmmm")=$B$7))*--(CHOOSE(MATCH($B$4,{"Mensual","Trimestral","Anual"},0),TEXT(Data!$E$2:$E$3988,"yyyy-mm"),YEAR(Data!$E$2:$E$3988)&"-T"&ROUNDUP(MONTH(Data!$E$2:$E$3988)/3,0),TEXT(YEAR(Data!$E$2:$E$3988),"0"))=$AP16))>0)),NA()))} -> #N/A | AS16: {=IF(OR($AP16="",AS$1=""),NA(),IFERROR(AVERAGE(_xlfn._xlws.FILTER(Data!$K$2:$K$3988,((Data!$A$2:$A$3988=AS$1)*IF($B$8="Todas",1,--(AS$1=$B$8))*IF($B$5="Todos",1,--(YEAR(Data!$E$2:$E$3988)=$B$5))*IF($B$6="Todos",1,--("T"&ROUNDUP(MONTH(Data!$E$2:$E$3988)/3,0)=$B$6))*IF($B$7="Todos",1,--(TEXT(Data!$E$2:$E$3988,"[$-es-ES]mmmm")=$B$7))*--(CHOOSE(MATCH($B$4,{"Mensual","Trimestral","Anual"},0),TEXT(Data!$E$2:$E$3988,"yyyy-mm"),YEAR(Data!$E$2:$E$3988)&"-T"&ROUNDUP(MONTH(Data!$E$2:$E$3988)/3,0),TEXT(YEAR(Data!$E$2:$E$3988),"0"))=$AP16))>0)),NA()))} -> #N/A | AT16: {=IF(OR($AP16="",AT$1=""),NA(),IFERROR(AVERAGE(_xlfn._xlws.FILTER(Data!$K$2:$K$3988,((Data!$A$2:$A$3988=AT$1)*IF($B$8="Todas",1,--(AT$1=$B$8))*IF($B$5="Todos",1,--(YEAR(Data!$E$2:$E$3988)=$B$5))*IF($B$6="Todos",1,--("T"&ROUNDUP(MONTH(Data!$E$2:$E$3988)/3,0)=$B$6))*IF($B$7="Todos",1,--(TEXT(Data!$E$2:$E$3988,"[$-es-ES]mmmm")=$B$7))*--(CHOOSE(MATCH($B$4,{"Mensual","Trimestral","Anual"},0),TEXT(Data!$E$2:$E$3988,"yyyy-mm"),YEAR(Data!$E$2:$E$3988)&"-T"&ROUNDUP(MONTH(Data!$E$2:$E$3988)/3,0),TEXT(YEAR(Data!$E$2:$E$3988),"0"))=$AP16))>0)),NA()))} -> #N/A
AH17: Presentes | AI17: 120.81 | AQ17: {=IF(OR($AP17="",AQ$1=""),NA(),IFERROR(AVERAGE(_xlfn._xlws.FILTER(Data!$K$2:$K$3988,((Data!$A$2:$A$3988=AQ$1)*IF($B$8="Todas",1,--(AQ$1=$B$8))*IF($B$5="Todos",1,--(YEAR(Data!$E$2:$E$3988)=$B$5))*IF($B$6="Todos",1,--("T"&ROUNDUP(MONTH(Data!$E$2:$E$3988)/3,0)=$B$6))*IF($B$7="Todos",1,--(TEXT(Data!$E$2:$E$3988,"[$-es-ES]mmmm")=$B$7))*--(CHOOSE(MATCH($B$4,{"Mensual","Trimestral","Anual"},0),TEXT(Data!$E$2:$E$3988,"yyyy-mm"),YEAR(Data!$E$2:$E$3988)&"-T"&ROUNDUP(MONTH(Data!$E$2:$E$3988)/3,0),TEXT(YEAR(Data!$E$2:$E$3988),"0"))=$AP17))>0)),NA()))} -> #N/A | AR17: {=IF(OR($AP17="",AR$1=""),NA(),IFERROR(AVERAGE(_xlfn._xlws.FILTER(Data!$K$2:$K$3988,((Data!$A$2:$A$3988=AR$1)*IF($B$8="Todas",1,--(AR$1=$B$8))*IF($B$5="Todos",1,--(YEAR(Data!$E$2:$E$3988)=$B$5))*IF($B$6="Todos",1,--("T"&ROUNDUP(MONTH(Data!$E$2:$E$3988)/3,0)=$B$6))*IF($B$7="Todos",1,--(TEXT(Data!$E$2:$E$3988,"[$-es-ES]mmmm")=$B$7))*--(CHOOSE(MATCH($B$4,{"Mensual","Trimestral","Anual"},0),TEXT(Data!$E$2:$E$3988,"yyyy-mm"),YEAR(Data!$E$2:$E$3988)&"-T"&ROUNDUP(MONTH(Data!$E$2:$E$3988)/3,0),TEXT(YEAR(Data!$E$2:$E$3988),"0"))=$AP17))>0)),NA()))} -> #N/A | AS17: {=IF(OR($AP17="",AS$1=""),NA(),IFERROR(AVERAGE(_xlfn._xlws.FILTER(Data!$K$2:$K$3988,((Data!$A$2:$A$3988=AS$1)*IF($B$8="Todas",1,--(AS$1=$B$8))*IF($B$5="Todos",1,--(YEAR(Data!$E$2:$E$3988)=$B$5))*IF($B$6="Todos",1,--("T"&ROUNDUP(MONTH(Data!$E$2:$E$3988)/3,0)=$B$6))*IF($B$7="Todos",1,--(TEXT(Data!$E$2:$E$3988,"[$-es-ES]mmmm")=$B$7))*--(CHOOSE(MATCH($B$4,{"Mensual","Trimestral","Anual"},0),TEXT(Data!$E$2:$E$3988,"yyyy-mm"),YEAR(Data!$E$2:$E$3988)&"-T"&ROUNDUP(MONTH(Data!$E$2:$E$3988)/3,0),TEXT(YEAR(Data!$E$2:$E$3988),"0"))=$AP17))>0)),NA()))} -> #N/A | AT17: {=IF(OR($AP17="",AT$1=""),NA(),IFERROR(AVERAGE(_xlfn._xlws.FILTER(Data!$K$2:$K$3988,((Data!$A$2:$A$3988=AT$1)*IF($B$8="Todas",1,--(AT$1=$B$8))*IF($B$5="Todos",1,--(YEAR(Data!$E$2:$E$3988)=$B$5))*IF($B$6="Todos",1,--("T"&ROUNDUP(MONTH(Data!$E$2:$E$3988)/3,0)=$B$6))*IF($B$7="Todos",1,--(TEXT(Data!$E$2:$E$3988,"[$-es-ES]mmmm")=$B$7))*--(CHOOSE(MATCH($B$4,{"Mensual","Trimestral","Anual"},0),TEXT(Data!$E$2:$E$3988,"yyyy-mm"),YEAR(Data!$E$2:$E$3988)&"-T"&ROUNDUP(MONTH(Data!$E$2:$E$3988)/3,0),TEXT(YEAR(Data!$E$2:$E$3988),"0"))=$AP17))>0)),NA()))} -> #N/A
AH18: Reparaciones | AI18: 32.19 | AQ18: {=IF(OR($AP18="",AQ$1=""),NA(),IFERROR(AVERAGE(_xlfn._xlws.FILTER(Data!$K$2:$K$3988,((Data!$A$2:$A$3988=AQ$1)*IF($B$8="Todas",1,--(AQ$1=$B$8))*IF($B$5="Todos",1,--(YEAR(Data!$E$2:$E$3988)=$B$5))*IF($B$6="Todos",1,--("T"&ROUNDUP(MONTH(Data!$E$2:$E$3988)/3,0)=$B$6))*IF($B$7="Todos",1,--(TEXT(Data!$E$2:$E$3988,"[$-es-ES]mmmm")=$B$7))*--(CHOOSE(MATCH($B$4,{"Mensual","Trimestral","Anual"},0),TEXT(Data!$E$2:$E$3988,"yyyy-mm"),YEAR(Data!$E$2:$E$3988)&"-T"&ROUNDUP(MONTH(Data!$E$2:$E$3988)/3,0),TEXT(YEAR(Data!$E$2:$E$3988),"0"))=$AP18))>0)),NA()))} -> #N/A | AR18: {=IF(OR($AP18="",AR$1=""),NA(),IFERROR(AVERAGE(_xlfn._xlws.FILTER(Data!$K$2:$K$3988,((Data!$A$2:$A$3988=AR$1)*IF($B$8="Todas",1,--(AR$1=$B$8))*IF($B$5="Todos",1,--(YEAR(Data!$E$2:$E$3988)=$B$5))*IF($B$6="Todos",1,--("T"&ROUNDUP(MONTH(Data!$E$2:$E$3988)/3,0)=$B$6))*IF($B$7="Todos",1,--(TEXT(Data!$E$2:$E$3988,"[$-es-ES]mmmm")=$B$7))*--(CHOOSE(MATCH($B$4,{"Mensual","Trimestral","Anual"},0),TEXT(Data!$E$2:$E$3988,"yyyy-mm"),YEAR(Data!$E$2:$E$3988)&"-T"&ROUNDUP(MONTH(Data!$E$2:$E$3988)/3,0),TEXT(YEAR(Data!$E$2:$E$3988),"0"))=$AP18))>0)),NA()))} -> #N/A | AS18: {=IF(OR($AP18="",AS$1=""),NA(),IFERROR(AVERAGE(_xlfn._xlws.FILTER(Data!$K$2:$K$3988,((Data!$A$2:$A$3988=AS$1)*IF($B$8="Todas",1,--(AS$1=$B$8))*IF($B$5="Todos",1,--(YEAR(Data!$E$2:$E$3988)=$B$5))*IF($B$6="Todos",1,--("T"&ROUNDUP(MONTH(Data!$E$2:$E$3988)/3,0)=$B$6))*IF($B$7="Todos",1,--(TEXT(Data!$E$2:$E$3988,"[$-es-ES]mmmm")=$B$7))*--(CHOOSE(MATCH($B$4,{"Mensual","Trimestral","Anual"},0),TEXT(Data!$E$2:$E$3988,"yyyy-mm"),YEAR(Data!$E$2:$E$3988)&"-T"&ROUNDUP(MONTH(Data!$E$2:$E$3988)/3,0),TEXT(YEAR(Data!$E$2:$E$3988),"0"))=$AP18))>0)),NA()))} -> #N/A | AT18: {=IF(OR($AP18="",AT$1=""),NA(),IFERROR(AVERAGE(_xlfn._xlws.FILTER(Data!$K$2:$K$3988,((Data!$A$2:$A$3988=AT$1)*IF($B$8="Todas",1,--(AT$1=$B$8))*IF($B$5="Todos",1,--(YEAR(Data!$E$2:$E$3988)=$B$5))*IF($B$6="Todos",1,--("T"&ROUNDUP(MONTH(Data!$E$2:$E$3988)/3,0)=$B$6))*IF($B$7="Todos",1,--(TEXT(Data!$E$2:$E$3988,"[$-es-ES]mmmm")=$B$7))*--(CHOOSE(MATCH($B$4,{"Mensual","Trimestral","Anual"},0),TEXT(Data!$E$2:$E$3988,"yyyy-mm"),YEAR(Data!$E$2:$E$3988)&"-T"&ROUNDUP(MONTH(Data!$E$2:$E$3988)/3,0),TEXT(YEAR(Data!$E$2:$E$3988),"0"))=$AP18))>0)),NA()))} -> #N/A
AH19: Deporte | AI19: 14.82 | AQ19: {=IF(OR($AP19="",AQ$1=""),NA(),IFERROR(AVERAGE(_xlfn._xlws.FILTER(Data!$K$2:$K$3988,((Data!$A$2:$A$3988=AQ$1)*IF($B$8="Todas",1,--(AQ$1=$B$8))*IF($B$5="Todos",1,--(YEAR(Data!$E$2:$E$3988)=$B$5))*IF($B$6="Todos",1,--("T"&ROUNDUP(MONTH(Data!$E$2:$E$3988)/3,0)=$B$6))*IF($B$7="Todos",1,--(TEXT(Data!$E$2:$E$3988,"[$-es-ES]mmmm")=$B$7))*--(CHOOSE(MATCH($B$4,{"Mensual","Trimestral","Anual"},0),TEXT(Data!$E$2:$E$3988,"yyyy-mm"),YEAR(Data!$E$2:$E$3988)&"-T"&ROUNDUP(MONTH(Data!$E$2:$E$3988)/3,0),TEXT(YEAR(Data!$E$2:$E$3988),"0"))=$AP19))>0)),NA()))} -> #N/A | AR19: {=IF(OR($AP19="",AR$1=""),NA(),IFERROR(AVERAGE(_xlfn._xlws.FILTER(Data!$K$2:$K$3988,((Data!$A$2:$A$3988=AR$1)*IF($B$8="Todas",1,--(AR$1=$B$8))*IF($B$5="Todos",1,--(YEAR(Data!$E$2:$E$3988)=$B$5))*IF($B$6="Todos",1,--("T"&ROUNDUP(MONTH(Data!$E$2:$E$3988)/3,0)=$B$6))*IF($B$7="Todos",1,--(TEXT(Data!$E$2:$E$3988,"[$-es-ES]mmmm")=$B$7))*--(CHOOSE(MATCH($B$4,{"Mensual","Trimestral","Anual"},0),TEXT(Data!$E$2:$E$3988,"yyyy-mm"),YEAR(Data!$E$2:$E$3988)&"-T"&ROUNDUP(MONTH(Data!$E$2:$E$3988)/3,0),TEXT(YEAR(Data!$E$2:$E$3988),"0"))=$AP19))>0)),NA()))} -> #N/A | AS19: {=IF(OR($AP19="",AS$1=""),NA(),IFERROR(AVERAGE(_xlfn._xlws.FILTER(Data!$K$2:$K$3988,((Data!$A$2:$A$3988=AS$1)*IF($B$8="Todas",1,--(AS$1=$B$8))*IF($B$5="Todos",1,--(YEAR(Data!$E$2:$E$3988)=$B$5))*IF($B$6="Todos",1,--("T"&ROUNDUP(MONTH(Data!$E$2:$E$3988)/3,0)=$B$6))*IF($B$7="Todos",1,--(TEXT(Data!$E$2:$E$3988,"[$-es-ES]mmmm")=$B$7))*--(CHOOSE(MATCH($B$4,{"Mensual","Trimestral","Anual"},0),TEXT(Data!$E$2:$E$3988,"yyyy-mm"),YEAR(Data!$E$2:$E$3988)&"-T"&ROUNDUP(MONTH(Data!$E$2:$E$3988)/3,0),TEXT(YEAR(Data!$E$2:$E$3988),"0"))=$AP19))>0)),NA()))} -> #N/A | AT19: {=IF(OR($AP19="",AT$1=""),NA(),IFERROR(AVERAGE(_xlfn._xlws.FILTER(Data!$K$2:$K$3988,((Data!$A$2:$A$3988=AT$1)*IF($B$8="Todas",1,--(AT$1=$B$8))*IF($B$5="Todos",1,--(YEAR(Data!$E$2:$E$3988)=$B$5))*IF($B$6="Todos",1,--("T"&ROUNDUP(MONTH(Data!$E$2:$E$3988)/3,0)=$B$6))*IF($B$7="Todos",1,--(TEXT(Data!$E$2:$E$3988,"[$-es-ES]mmmm")=$B$7))*--(CHOOSE(MATCH($B$4,{"Mensual","Trimestral","Anual"},0),TEXT(Data!$E$2:$E$3988,"yyyy-mm"),YEAR(Data!$E$2:$E$3988)&"-T"&ROUNDUP(MONTH(Data!$E$2:$E$3988)/3,0),TEXT(YEAR(Data!$E$2:$E$3988),"0"))=$AP19))>0)),NA()))} -> #N/A
AH20: Café | AI20: 1.3 | AQ20: {=IF(OR($AP20="",AQ$1=""),NA(),IFERROR(AVERAGE(_xlfn._xlws.FILTER(Data!$K$2:$K$3988,((Data!$A$2:$A$3988=AQ$1)*IF($B$8="Todas",1,--(AQ$1=$B$8))*IF($B$5="Todos",1,--(YEAR(Data!$E$2:$E$3988)=$B$5))*IF($B$6="Todos",1,--("T"&ROUNDUP(MONTH(Data!$E$2:$E$3988)/3,0)=$B$6))*IF($B$7="Todos",1,--(TEXT(Data!$E$2:$E$3988,"[$-es-ES]mmmm")=$B$7))*--(CHOOSE(MATCH($B$4,{"Mensual","Trimestral","Anual"},0),TEXT(Data!$E$2:$E$3988,"yyyy-mm"),YEAR(Data!$E$2:$E$3988)&"-T"&ROUNDUP(MONTH(Data!$E$2:$E$3988)/3,0),TEXT(YEAR(Data!$E$2:$E$3988),"0"))=$AP20))>0)),NA()))} -> #N/A | AR20: {=IF(OR($AP20="",AR$1=""),NA(),IFERROR(AVERAGE(_xlfn._xlws.FILTER(Data!$K$2:$K$3988,((Data!$A$2:$A$3988=AR$1)*IF($B$8="Todas",1,--(AR$1=$B$8))*IF($B$5="Todos",1,--(YEAR(Data!$E$2:$E$3988)=$B$5))*IF($B$6="Todos",1,--("T"&ROUNDUP(MONTH(Data!$E$2:$E$3988)/3,0)=$B$6))*IF($B$7="Todos",1,--(TEXT(Data!$E$2:$E$3988,"[$-es-ES]mmmm")=$B$7))*--(CHOOSE(MATCH($B$4,{"Mensual","Trimestral","Anual"},0),TEXT(Data!$E$2:$E$3988,"yyyy-mm"),YEAR(Data!$E$2:$E$3988)&"-T"&ROUNDUP(MONTH(Data!$E$2:$E$3988)/3,0),TEXT(YEAR(Data!$E$2:$E$3988),"0"))=$AP20))>0)),NA()))} -> #N/A | AS20: {=IF(OR($AP20="",AS$1=""),NA(),IFERROR(AVERAGE(_xlfn._xlws.FILTER(Data!$K$2:$K$3988,((Data!$A$2:$A$3988=AS$1)*IF($B$8="Todas",1,--(AS$1=$B$8))*IF($B$5="Todos",1,--(YEAR(Data!$E$2:$E$3988)=$B$5))*IF($B$6="Todos",1,--("T"&ROUNDUP(MONTH(Data!$E$2:$E$3988)/3,0)=$B$6))*IF($B$7="Todos",1,--(TEXT(Data!$E$2:$E$3988,"[$-es-ES]mmmm")=$B$7))*--(CHOOSE(MATCH($B$4,{"Mensual","Trimestral","Anual"},0),TEXT(Data!$E$2:$E$3988,"yyyy-mm"),YEAR(Data!$E$2:$E$3988)&"-T"&ROUNDUP(MONTH(Data!$E$2:$E$3988)/3,0),TEXT(YEAR(Data!$E$2:$E$3988),"0"))=$AP20))>0)),NA()))} -> #N/A | AT20: {=IF(OR($AP20="",AT$1=""),NA(),IFERROR(AVERAGE(_xlfn._xlws.FILTER(Data!$K$2:$K$3988,((Data!$A$2:$A$3988=AT$1)*IF($B$8="Todas",1,--(AT$1=$B$8))*IF($B$5="Todos",1,--(YEAR(Data!$E$2:$E$3988)=$B$5))*IF($B$6="Todos",1,--("T"&ROUNDUP(MONTH(Data!$E$2:$E$3988)/3,0)=$B$6))*IF($B$7="Todos",1,--(TEXT(Data!$E$2:$E$3988,"[$-es-ES]mmmm")=$B$7))*--(CHOOSE(MATCH($B$4,{"Mensual","Trimestral","Anual"},0),TEXT(Data!$E$2:$E$3988,"yyyy-mm"),YEAR(Data!$E$2:$E$3988)&"-T"&ROUNDUP(MONTH(Data!$E$2:$E$3988)/3,0),TEXT(YEAR(Data!$E$2:$E$3988),"0"))=$AP20))>0)),NA()))} -> #N/A
AQ21: {=IF(OR($AP21="",AQ$1=""),NA(),IFERROR(AVERAGE(_xlfn._xlws.FILTER(Data!$K$2:$K$3988,((Data!$A$2:$A$3988=AQ$1)*IF($B$8="Todas",1,--(AQ$1=$B$8))*IF($B$5="Todos",1,--(YEAR(Data!$E$2:$E$3988)=$B$5))*IF($B$6="Todos",1,--("T"&ROUNDUP(MONTH(Data!$E$2:$E$3988)/3,0)=$B$6))*IF($B$7="Todos",1,--(TEXT(Data!$E$2:$E$3988,"[$-es-ES]mmmm")=$B$7))*--(CHOOSE(MATCH($B$4,{"Mensual","Trimestral","Anual"},0),TEXT(Data!$E$2:$E$3988,"yyyy-mm"),YEAR(Data!$E$2:$E$3988)&"-T"&ROUNDUP(MONTH(Data!$E$2:$E$3988)/3,0),TEXT(YEAR(Data!$E$2:$E$3988),"0"))=$AP21))>0)),NA()))} -> #N/A | AR21: {=IF(OR($AP21="",AR$1=""),NA(),IFERROR(AVERAGE(_xlfn._xlws.FILTER(Data!$K$2:$K$3988,((Data!$A$2:$A$3988=AR$1)*IF($B$8="Todas",1,--(AR$1=$B$8))*IF($B$5="Todos",1,--(YEAR(Data!$E$2:$E$3988)=$B$5))*IF($B$6="Todos",1,--("T"&ROUNDUP(MONTH(Data!$E$2:$E$3988)/3,0)=$B$6))*IF($B$7="Todos",1,--(TEXT(Data!$E$2:$E$3988,"[$-es-ES]mmmm")=$B$7))*--(CHOOSE(MATCH($B$4,{"Mensual","Trimestral","Anual"},0),TEXT(Data!$E$2:$E$3988,"yyyy-mm"),YEAR(Data!$E$2:$E$3988)&"-T"&ROUNDUP(MONTH(Data!$E$2:$E$3988)/3,0),TEXT(YEAR(Data!$E$2:$E$3988),"0"))=$AP21))>0)),NA()))} -> #N/A | AS21: {=IF(OR($AP21="",AS$1=""),NA(),IFERROR(AVERAGE(_xlfn._xlws.FILTER(Data!$K$2:$K$3988,((Data!$A$2:$A$3988=AS$1)*IF($B$8="Todas",1,--(AS$1=$B$8))*IF($B$5="Todos",1,--(YEAR(Data!$E$2:$E$3988)=$B$5))*IF($B$6="Todos",1,--("T"&ROUNDUP(MONTH(Data!$E$2:$E$3988)/3,0)=$B$6))*IF($B$7="Todos",1,--(TEXT(Data!$E$2:$E$3988,"[$-es-ES]mmmm")=$B$7))*--(CHOOSE(MATCH($B$4,{"Mensual","Trimestral","Anual"},0),TEXT(Data!$E$2:$E$3988,"yyyy-mm"),YEAR(Data!$E$2:$E$3988)&"-T"&ROUNDUP(MONTH(Data!$E$2:$E$3988)/3,0),TEXT(YEAR(Data!$E$2:$E$3988),"0"))=$AP21))>0)),NA()))} -> #N/A | AT21: {=IF(OR($AP21="",AT$1=""),NA(),IFERROR(AVERAGE(_xlfn._xlws.FILTER(Data!$K$2:$K$3988,((Data!$A$2:$A$3988=AT$1)*IF($B$8="Todas",1,--(AT$1=$B$8))*IF($B$5="Todos",1,--(YEAR(Data!$E$2:$E$3988)=$B$5))*IF($B$6="Todos",1,--("T"&ROUNDUP(MONTH(Data!$E$2:$E$3988)/3,0)=$B$6))*IF($B$7="Todos",1,--(TEXT(Data!$E$2:$E$3988,"[$-es-ES]mmmm")=$B$7))*--(CHOOSE(MATCH($B$4,{"Mensual","Trimestral","Anual"},0),TEXT(Data!$E$2:$E$3988,"yyyy-mm"),YEAR(Data!$E$2:$E$3988)&"-T"&ROUNDUP(MONTH(Data!$E$2:$E$3988)/3,0),TEXT(YEAR(Data!$E$2:$E$3988),"0"))=$AP21))>0)),NA()))} -> #N/A
AQ22: {=IF(OR($AP22="",AQ$1=""),NA(),IFERROR(AVERAGE(_xlfn._xlws.FILTER(Data!$K$2:$K$3988,((Data!$A$2:$A$3988=AQ$1)*IF($B$8="Todas",1,--(AQ$1=$B$8))*IF($B$5="Todos",1,--(YEAR(Data!$E$2:$E$3988)=$B$5))*IF($B$6="Todos",1,--("T"&ROUNDUP(MONTH(Data!$E$2:$E$3988)/3,0)=$B$6))*IF($B$7="Todos",1,--(TEXT(Data!$E$2:$E$3988,"[$-es-ES]mmmm")=$B$7))*--(CHOOSE(MATCH($B$4,{"Mensual","Trimestral","Anual"},0),TEXT(Data!$E$2:$E$3988,"yyyy-mm"),YEAR(Data!$E$2:$E$3988)&"-T"&ROUNDUP(MONTH(Data!$E$2:$E$3988)/3,0),TEXT(YEAR(Data!$E$2:$E$3988),"0"))=$AP22))>0)),NA()))} -> #N/A | AR22: {=IF(OR($AP22="",AR$1=""),NA(),IFERROR(AVERAGE(_xlfn._xlws.FILTER(Data!$K$2:$K$3988,((Data!$A$2:$A$3988=AR$1)*IF($B$8="Todas",1,--(AR$1=$B$8))*IF($B$5="Todos",1,--(YEAR(Data!$E$2:$E$3988)=$B$5))*IF($B$6="Todos",1,--("T"&ROUNDUP(MONTH(Data!$E$2:$E$3988)/3,0)=$B$6))*IF($B$7="Todos",1,--(TEXT(Data!$E$2:$E$3988,"[$-es-ES]mmmm")=$B$7))*--(CHOOSE(MATCH($B$4,{"Mensual","Trimestral","Anual"},0),TEXT(Data!$E$2:$E$3988,"yyyy-mm"),YEAR(Data!$E$2:$E$3988)&"-T"&ROUNDUP(MONTH(Data!$E$2:$E$3988)/3,0),TEXT(YEAR(Data!$E$2:$E$3988),"0"))=$AP22))>0)),NA()))} -> #N/A | AS22: {=IF(OR($AP22="",AS$1=""),NA(),IFERROR(AVERAGE(_xlfn._xlws.FILTER(Data!$K$2:$K$3988,((Data!$A$2:$A$3988=AS$1)*IF($B$8="Todas",1,--(AS$1=$B$8))*IF($B$5="Todos",1,--(YEAR(Data!$E$2:$E$3988)=$B$5))*IF($B$6="Todos",1,--("T"&ROUNDUP(MONTH(Data!$E$2:$E$3988)/3,0)=$B$6))*IF($B$7="Todos",1,--(TEXT(Data!$E$2:$E$3988,"[$-es-ES]mmmm")=$B$7))*--(CHOOSE(MATCH($B$4,{"Mensual","Trimestral","Anual"},0),TEXT(Data!$E$2:$E$3988,"yyyy-mm"),YEAR(Data!$E$2:$E$3988)&"-T"&ROUNDUP(MONTH(Data!$E$2:$E$3988)/3,0),TEXT(YEAR(Data!$E$2:$E$3988),"0"))=$AP22))>0)),NA()))} -> #N/A | AT22: {=IF(OR($AP22="",AT$1=""),NA(),IFERROR(AVERAGE(_xlfn._xlws.FILTER(Data!$K$2:$K$3988,((Data!$A$2:$A$3988=AT$1)*IF($B$8="Todas",1,--(AT$1=$B$8))*IF($B$5="Todos",1,--(YEAR(Data!$E$2:$E$3988)=$B$5))*IF($B$6="Todos",1,--("T"&ROUNDUP(MONTH(Data!$E$2:$E$3988)/3,0)=$B$6))*IF($B$7="Todos",1,--(TEXT(Data!$E$2:$E$3988,"[$-es-ES]mmmm")=$B$7))*--(CHOOSE(MATCH($B$4,{"Mensual","Trimestral","Anual"},0),TEXT(Data!$E$2:$E$3988,"yyyy-mm"),YEAR(Data!$E$2:$E$3988)&"-T"&ROUNDUP(MONTH(Data!$E$2:$E$3988)/3,0),TEXT(YEAR(Data!$E$2:$E$3988),"0"))=$AP22))>0)),NA()))} -> #N/A
AQ23: {=IF(OR($AP23="",AQ$1=""),NA(),IFERROR(AVERAGE(_xlfn._xlws.FILTER(Data!$K$2:$K$3988,((Data!$A$2:$A$3988=AQ$1)*IF($B$8="Todas",1,--(AQ$1=$B$8))*IF($B$5="Todos",1,--(YEAR(Data!$E$2:$E$3988)=$B$5))*IF($B$6="Todos",1,--("T"&ROUNDUP(MONTH(Data!$E$2:$E$3988)/3,0)=$B$6))*IF($B$7="Todos",1,--(TEXT(Data!$E$2:$E$3988,"[$-es-ES]mmmm")=$B$7))*--(CHOOSE(MATCH($B$4,{"Mensual","Trimestral","Anual"},0),TEXT(Data!$E$2:$E$3988,"yyyy-mm"),YEAR(Data!$E$2:$E$3988)&"-T"&ROUNDUP(MONTH(Data!$E$2:$E$3988)/3,0),TEXT(YEAR(Data!$E$2:$E$3988),"0"))=$AP23))>0)),NA()))} -> #N/A | AR23: {=IF(OR($AP23="",AR$1=""),NA(),IFERROR(AVERAGE(_xlfn._xlws.FILTER(Data!$K$2:$K$3988,((Data!$A$2:$A$3988=AR$1)*IF($B$8="Todas",1,--(AR$1=$B$8))*IF($B$5="Todos",1,--(YEAR(Data!$E$2:$E$3988)=$B$5))*IF($B$6="Todos",1,--("T"&ROUNDUP(MONTH(Data!$E$2:$E$3988)/3,0)=$B$6))*IF($B$7="Todos",1,--(TEXT(Data!$E$2:$E$3988,"[$-es-ES]mmmm")=$B$7))*--(CHOOSE(MATCH($B$4,{"Mensual","Trimestral","Anual"},0),TEXT(Data!$E$2:$E$3988,"yyyy-mm"),YEAR(Data!$E$2:$E$3988)&"-T"&ROUNDUP(MONTH(Data!$E$2:$E$3988)/3,0),TEXT(YEAR(Data!$E$2:$E$3988),"0"))=$AP23))>0)),NA()))} -> #N/A | AS23: {=IF(OR($AP23="",AS$1=""),NA(),IFERROR(AVERAGE(_xlfn._xlws.FILTER(Data!$K$2:$K$3988,((Data!$A$2:$A$3988=AS$1)*IF($B$8="Todas",1,--(AS$1=$B$8))*IF($B$5="Todos",1,--(YEAR(Data!$E$2:$E$3988)=$B$5))*IF($B$6="Todos",1,--("T"&ROUNDUP(MONTH(Data!$E$2:$E$3988)/3,0)=$B$6))*IF($B$7="Todos",1,--(TEXT(Data!$E$2:$E$3988,"[$-es-ES]mmmm")=$B$7))*--(CHOOSE(MATCH($B$4,{"Mensual","Trimestral","Anual"},0),TEXT(Data!$E$2:$E$3988,"yyyy-mm"),YEAR(Data!$E$2:$E$3988)&"-T"&ROUNDUP(MONTH(Data!$E$2:$E$3988)/3,0),TEXT(YEAR(Data!$E$2:$E$3988),"0"))=$AP23))>0)),NA()))} -> #N/A | AT23: {=IF(OR($AP23="",AT$1=""),NA(),IFERROR(AVERAGE(_xlfn._xlws.FILTER(Data!$K$2:$K$3988,((Data!$A$2:$A$3988=AT$1)*IF($B$8="Todas",1,--(AT$1=$B$8))*IF($B$5="Todos",1,--(YEAR(Data!$E$2:$E$3988)=$B$5))*IF($B$6="Todos",1,--("T"&ROUNDUP(MONTH(Data!$E$2:$E$3988)/3,0)=$B$6))*IF($B$7="Todos",1,--(TEXT(Data!$E$2:$E$3988,"[$-es-ES]mmmm")=$B$7))*--(CHOOSE(MATCH($B$4,{"Mensual","Trimestral","Anual"},0),TEXT(Data!$E$2:$E$3988,"yyyy-mm"),YEAR(Data!$E$2:$E$3988)&"-T"&ROUNDUP(MONTH(Data!$E$2:$E$3988)/3,0),TEXT(YEAR(Data!$E$2:$E$3988),"0"))=$AP23))>0)),NA()))} -> #N/A
AQ24: {=IF(OR($AP24="",AQ$1=""),NA(),IFERROR(AVERAGE(_xlfn._xlws.FILTER(Data!$K$2:$K$3988,((Data!$A$2:$A$3988=AQ$1)*IF($B$8="Todas",1,--(AQ$1=$B$8))*IF($B$5="Todos",1,--(YEAR(Data!$E$2:$E$3988)=$B$5))*IF($B$6="Todos",1,--("T"&ROUNDUP(MONTH(Data!$E$2:$E$3988)/3,0)=$B$6))*IF($B$7="Todos",1,--(TEXT(Data!$E$2:$E$3988,"[$-es-ES]mmmm")=$B$7))*--(CHOOSE(MATCH($B$4,{"Mensual","Trimestral","Anual"},0),TEXT(Data!$E$2:$E$3988,"yyyy-mm"),YEAR(Data!$E$2:$E$3988)&"-T"&ROUNDUP(MONTH(Data!$E$2:$E$3988)/3,0),TEXT(YEAR(Data!$E$2:$E$3988),"0"))=$AP24))>0)),NA()))} -> #N/A | AR24: {=IF(OR($AP24="",AR$1=""),NA(),IFERROR(AVERAGE(_xlfn._xlws.FILTER(Data!$K$2:$K$3988,((Data!$A$2:$A$3988=AR$1)*IF($B$8="Todas",1,--(AR$1=$B$8))*IF($B$5="Todos",1,--(YEAR(Data!$E$2:$E$3988)=$B$5))*IF($B$6="Todos",1,--("T"&ROUNDUP(MONTH(Data!$E$2:$E$3988)/3,0)=$B$6))*IF($B$7="Todos",1,--(TEXT(Data!$E$2:$E$3988,"[$-es-ES]mmmm")=$B$7))*--(CHOOSE(MATCH($B$4,{"Mensual","Trimestral","Anual"},0),TEXT(Data!$E$2:$E$3988,"yyyy-mm"),YEAR(Data!$E$2:$E$3988)&"-T"&ROUNDUP(MONTH(Data!$E$2:$E$3988)/3,0),TEXT(YEAR(Data!$E$2:$E$3988),"0"))=$AP24))>0)),NA()))} -> #N/A | AS24: {=IF(OR($AP24="",AS$1=""),NA(),IFERROR(AVERAGE(_xlfn._xlws.FILTER(Data!$K$2:$K$3988,((Data!$A$2:$A$3988=AS$1)*IF($B$8="Todas",1,--(AS$1=$B$8))*IF($B$5="Todos",1,--(YEAR(Data!$E$2:$E$3988)=$B$5))*IF($B$6="Todos",1,--("T"&ROUNDUP(MONTH(Data!$E$2:$E$3988)/3,0)=$B$6))*IF($B$7="Todos",1,--(TEXT(Data!$E$2:$E$3988,"[$-es-ES]mmmm")=$B$7))*--(CHOOSE(MATCH($B$4,{"Mensual","Trimestral","Anual"},0),TEXT(Data!$E$2:$E$3988,"yyyy-mm"),YEAR(Data!$E$2:$E$3988)&"-T"&ROUNDUP(MONTH(Data!$E$2:$E$3988)/3,0),TEXT(YEAR(Data!$E$2:$E$3988),"0"))=$AP24))>0)),NA()))} -> #N/A | AT24: {=IF(OR($AP24="",AT$1=""),NA(),IFERROR(AVERAGE(_xlfn._xlws.FILTER(Data!$K$2:$K$3988,((Data!$A$2:$A$3988=AT$1)*IF($B$8="Todas",1,--(AT$1=$B$8))*IF($B$5="Todos",1,--(YEAR(Data!$E$2:$E$3988)=$B$5))*IF($B$6="Todos",1,--("T"&ROUNDUP(MONTH(Data!$E$2:$E$3988)/3,0)=$B$6))*IF($B$7="Todos",1,--(TEXT(Data!$E$2:$E$3988,"[$-es-ES]mmmm")=$B$7))*--(CHOOSE(MATCH($B$4,{"Mensual","Trimestral","Anual"},0),TEXT(Data!$E$2:$E$3988,"yyyy-mm"),YEAR(Data!$E$2:$E$3988)&"-T"&ROUNDUP(MONTH(Data!$E$2:$E$3988)/3,0),TEXT(YEAR(Data!$E$2:$E$3988),"0"))=$AP24))>0)),NA()))} -> #N/A
AQ25: {=IF(OR($AP25="",AQ$1=""),NA(),IFERROR(AVERAGE(_xlfn._xlws.FILTER(Data!$K$2:$K$3988,((Data!$A$2:$A$3988=AQ$1)*IF($B$8="Todas",1,--(AQ$1=$B$8))*IF($B$5="Todos",1,--(YEAR(Data!$E$2:$E$3988)=$B$5))*IF($B$6="Todos",1,--("T"&ROUNDUP(MONTH(Data!$E$2:$E$3988)/3,0)=$B$6))*IF($B$7="Todos",1,--(TEXT(Data!$E$2:$E$3988,"[$-es-ES]mmmm")=$B$7))*--(CHOOSE(MATCH($B$4,{"Mensual","Trimestral","Anual"},0),TEXT(Data!$E$2:$E$3988,"yyyy-mm"),YEAR(Data!$E$2:$E$3988)&"-T"&ROUNDUP(MONTH(Data!$E$2:$E$3988)/3,0),TEXT(YEAR(Data!$E$2:$E$3988),"0"))=$AP25))>0)),NA()))} -> #N/A | AR25: {=IF(OR($AP25="",AR$1=""),NA(),IFERROR(AVERAGE(_xlfn._xlws.FILTER(Data!$K$2:$K$3988,((Data!$A$2:$A$3988=AR$1)*IF($B$8="Todas",1,--(AR$1=$B$8))*IF($B$5="Todos",1,--(YEAR(Data!$E$2:$E$3988)=$B$5))*IF($B$6="Todos",1,--("T"&ROUNDUP(MONTH(Data!$E$2:$E$3988)/3,0)=$B$6))*IF($B$7="Todos",1,--(TEXT(Data!$E$2:$E$3988,"[$-es-ES]mmmm")=$B$7))*--(CHOOSE(MATCH($B$4,{"Mensual","Trimestral","Anual"},0),TEXT(Data!$E$2:$E$3988,"yyyy-mm"),YEAR(Data!$E$2:$E$3988)&"-T"&ROUNDUP(MONTH(Data!$E$2:$E$3988)/3,0),TEXT(YEAR(Data!$E$2:$E$3988),"0"))=$AP25))>0)),NA()))} -> #N/A | AS25: {=IF(OR($AP25="",AS$1=""),NA(),IFERROR(AVERAGE(_xlfn._xlws.FILTER(Data!$K$2:$K$3988,((Data!$A$2:$A$3988=AS$1)*IF($B$8="Todas",1,--(AS$1=$B$8))*IF($B$5="Todos",1,--(YEAR(Data!$E$2:$E$3988)=$B$5))*IF($B$6="Todos",1,--("T"&ROUNDUP(MONTH(Data!$E$2:$E$3988)/3,0)=$B$6))*IF($B$7="Todos",1,--(TEXT(Data!$E$2:$E$3988,"[$-es-ES]mmmm")=$B$7))*--(CHOOSE(MATCH($B$4,{"Mensual","Trimestral","Anual"},0),TEXT(Data!$E$2:$E$3988,"yyyy-mm"),YEAR(Data!$E$2:$E$3988)&"-T"&ROUNDUP(MONTH(Data!$E$2:$E$3988)/3,0),TEXT(YEAR(Data!$E$2:$E$3988),"0"))=$AP25))>0)),NA()))} -> #N/A | AT25: {=IF(OR($AP25="",AT$1=""),NA(),IFERROR(AVERAGE(_xlfn._xlws.FILTER(Data!$K$2:$K$3988,((Data!$A$2:$A$3988=AT$1)*IF($B$8="Todas",1,--(AT$1=$B$8))*IF($B$5="Todos",1,--(YEAR(Data!$E$2:$E$3988)=$B$5))*IF($B$6="Todos",1,--("T"&ROUNDUP(MONTH(Data!$E$2:$E$3988)/3,0)=$B$6))*IF($B$7="Todos",1,--(TEXT(Data!$E$2:$E$3988,"[$-es-ES]mmmm")=$B$7))*--(CHOOSE(MATCH($B$4,{"Mensual","Trimestral","Anual"},0),TEXT(Data!$E$2:$E$3988,"yyyy-mm"),YEAR(Data!$E$2:$E$3988)&"-T"&ROUNDUP(MONTH(Data!$E$2:$E$3988)/3,0),TEXT(YEAR(Data!$E$2:$E$3988),"0"))=$AP25))>0)),NA()))} -> #N/A
AQ26: {=IF(OR($AP26="",AQ$1=""),NA(),IFERROR(AVERAGE(_xlfn._xlws.FILTER(Data!$K$2:$K$3988,((Data!$A$2:$A$3988=AQ$1)*IF($B$8="Todas",1,--(AQ$1=$B$8))*IF($B$5="Todos",1,--(YEAR(Data!$E$2:$E$3988)=$B$5))*IF($B$6="Todos",1,--("T"&ROUNDUP(MONTH(Data!$E$2:$E$3988)/3,0)=$B$6))*IF($B$7="Todos",1,--(TEXT(Data!$E$2:$E$3988,"[$-es-ES]mmmm")=$B$7))*--(CHOOSE(MATCH($B$4,{"Mensual","Trimestral","Anual"},0),TEXT(Data!$E$2:$E$3988,"yyyy-mm"),YEAR(Data!$E$2:$E$3988)&"-T"&ROUNDUP(MONTH(Data!$E$2:$E$3988)/3,0),TEXT(YEAR(Data!$E$2:$E$3988),"0"))=$AP26))>0)),NA()))} -> #N/A | AR26: {=IF(OR($AP26="",AR$1=""),NA(),IFERROR(AVERAGE(_xlfn._xlws.FILTER(Data!$K$2:$K$3988,((Data!$A$2:$A$3988=AR$1)*IF($B$8="Todas",1,--(AR$1=$B$8))*IF($B$5="Todos",1,--(YEAR(Data!$E$2:$E$3988)=$B$5))*IF($B$6="Todos",1,--("T"&ROUNDUP(MONTH(Data!$E$2:$E$3988)/3,0)=$B$6))*IF($B$7="Todos",1,--(TEXT(Data!$E$2:$E$3988,"[$-es-ES]mmmm")=$B$7))*--(CHOOSE(MATCH($B$4,{"Mensual","Trimestral","Anual"},0),TEXT(Data!$E$2:$E$3988,"yyyy-mm"),YEAR(Data!$E$2:$E$3988)&"-T"&ROUNDUP(MONTH(Data!$E$2:$E$3988)/3,0),TEXT(YEAR(Data!$E$2:$E$3988),"0"))=$AP26))>0)),NA()))} -> #N/A | AS26: {=IF(OR($AP26="",AS$1=""),NA(),IFERROR(AVERAGE(_xlfn._xlws.FILTER(Data!$K$2:$K$3988,((Data!$A$2:$A$3988=AS$1)*IF($B$8="Todas",1,--(AS$1=$B$8))*IF($B$5="Todos",1,--(YEAR(Data!$E$2:$E$3988)=$B$5))*IF($B$6="Todos",1,--("T"&ROUNDUP(MONTH(Data!$E$2:$E$3988)/3,0)=$B$6))*IF($B$7="Todos",1,--(TEXT(Data!$E$2:$E$3988,"[$-es-ES]mmmm")=$B$7))*--(CHOOSE(MATCH($B$4,{"Mensual","Trimestral","Anual"},0),TEXT(Data!$E$2:$E$3988,"yyyy-mm"),YEAR(Data!$E$2:$E$3988)&"-T"&ROUNDUP(MONTH(Data!$E$2:$E$3988)/3,0),TEXT(YEAR(Data!$E$2:$E$3988),"0"))=$AP26))>0)),NA()))} -> #N/A | AT26: {=IF(OR($AP26="",AT$1=""),NA(),IFERROR(AVERAGE(_xlfn._xlws.FILTER(Data!$K$2:$K$3988,((Data!$A$2:$A$3988=AT$1)*IF($B$8="Todas",1,--(AT$1=$B$8))*IF($B$5="Todos",1,--(YEAR(Data!$E$2:$E$3988)=$B$5))*IF($B$6="Todos",1,--("T"&ROUNDUP(MONTH(Data!$E$2:$E$3988)/3,0)=$B$6))*IF($B$7="Todos",1,--(TEXT(Data!$E$2:$E$3988,"[$-es-ES]mmmm")=$B$7))*--(CHOOSE(MATCH($B$4,{"Mensual","Trimestral","Anual"},0),TEXT(Data!$E$2:$E$3988,"yyyy-mm"),YEAR(Data!$E$2:$E$3988)&"-T"&ROUNDUP(MONTH(Data!$E$2:$E$3988)/3,0),TEXT(YEAR(Data!$E$2:$E$3988),"0"))=$AP26))>0)),NA()))} -> #N/A
AQ27: {=IF(OR($AP27="",AQ$1=""),NA(),IFERROR(AVERAGE(_xlfn._xlws.FILTER(Data!$K$2:$K$3988,((Data!$A$2:$A$3988=AQ$1)*IF($B$8="Todas",1,--(AQ$1=$B$8))*IF($B$5="Todos",1,--(YEAR(Data!$E$2:$E$3988)=$B$5))*IF($B$6="Todos",1,--("T"&ROUNDUP(MONTH(Data!$E$2:$E$3988)/3,0)=$B$6))*IF($B$7="Todos",1,--(TEXT(Data!$E$2:$E$3988,"[$-es-ES]mmmm")=$B$7))*--(CHOOSE(MATCH($B$4,{"Mensual","Trimestral","Anual"},0),TEXT(Data!$E$2:$E$3988,"yyyy-mm"),YEAR(Data!$E$2:$E$3988)&"-T"&ROUNDUP(MONTH(Data!$E$2:$E$3988)/3,0),TEXT(YEAR(Data!$E$2:$E$3988),"0"))=$AP27))>0)),NA()))} -> #N/A | AR27: {=IF(OR($AP27="",AR$1=""),NA(),IFERROR(AVERAGE(_xlfn._xlws.FILTER(Data!$K$2:$K$3988,((Data!$A$2:$A$3988=AR$1)*IF($B$8="Todas",1,--(AR$1=$B$8))*IF($B$5="Todos",1,--(YEAR(Data!$E$2:$E$3988)=$B$5))*IF($B$6="Todos",1,--("T"&ROUNDUP(MONTH(Data!$E$2:$E$3988)/3,0)=$B$6))*IF($B$7="Todos",1,--(TEXT(Data!$E$2:$E$3988,"[$-es-ES]mmmm")=$B$7))*--(CHOOSE(MATCH($B$4,{"Mensual","Trimestral","Anual"},0),TEXT(Data!$E$2:$E$3988,"yyyy-mm"),YEAR(Data!$E$2:$E$3988)&"-T"&ROUNDUP(MONTH(Data!$E$2:$E$3988)/3,0),TEXT(YEAR(Data!$E$2:$E$3988),"0"))=$AP27))>0)),NA()))} -> #N/A | AS27: {=IF(OR($AP27="",AS$1=""),NA(),IFERROR(AVERAGE(_xlfn._xlws.FILTER(Data!$K$2:$K$3988,((Data!$A$2:$A$3988=AS$1)*IF($B$8="Todas",1,--(AS$1=$B$8))*IF($B$5="Todos",1,--(YEAR(Data!$E$2:$E$3988)=$B$5))*IF($B$6="Todos",1,--("T"&ROUNDUP(MONTH(Data!$E$2:$E$3988)/3,0)=$B$6))*IF($B$7="Todos",1,--(TEXT(Data!$E$2:$E$3988,"[$-es-ES]mmmm")=$B$7))*--(CHOOSE(MATCH($B$4,{"Mensual","Trimestral","Anual"},0),TEXT(Data!$E$2:$E$3988,"yyyy-mm"),YEAR(Data!$E$2:$E$3988)&"-T"&ROUNDUP(MONTH(Data!$E$2:$E$3988)/3,0),TEXT(YEAR(Data!$E$2:$E$3988),"0"))=$AP27))>0)),NA()))} -> #N/A | AT27: {=IF(OR($AP27="",AT$1=""),NA(),IFERROR(AVERAGE(_xlfn._xlws.FILTER(Data!$K$2:$K$3988,((Data!$A$2:$A$3988=AT$1)*IF($B$8="Todas",1,--(AT$1=$B$8))*IF($B$5="Todos",1,--(YEAR(Data!$E$2:$E$3988)=$B$5))*IF($B$6="Todos",1,--("T"&ROUNDUP(MONTH(Data!$E$2:$E$3988)/3,0)=$B$6))*IF($B$7="Todos",1,--(TEXT(Data!$E$2:$E$3988,"[$-es-ES]mmmm")=$B$7))*--(CHOOSE(MATCH($B$4,{"Mensual","Trimestral","Anual"},0),TEXT(Data!$E$2:$E$3988,"yyyy-mm"),YEAR(Data!$E$2:$E$3988)&"-T"&ROUNDUP(MONTH(Data!$E$2:$E$3988)/3,0),TEXT(YEAR(Data!$E$2:$E$3988),"0"))=$AP27))>0)),NA()))} -> #N/A
AQ28: {=IF(OR($AP28="",AQ$1=""),NA(),IFERROR(AVERAGE(_xlfn._xlws.FILTER(Data!$K$2:$K$3988,((Data!$A$2:$A$3988=AQ$1)*IF($B$8="Todas",1,--(AQ$1=$B$8))*IF($B$5="Todos",1,--(YEAR(Data!$E$2:$E$3988)=$B$5))*IF($B$6="Todos",1,--("T"&ROUNDUP(MONTH(Data!$E$2:$E$3988)/3,0)=$B$6))*IF($B$7="Todos",1,--(TEXT(Data!$E$2:$E$3988,"[$-es-ES]mmmm")=$B$7))*--(CHOOSE(MATCH($B$4,{"Mensual","Trimestral","Anual"},0),TEXT(Data!$E$2:$E$3988,"yyyy-mm"),YEAR(Data!$E$2:$E$3988)&"-T"&ROUNDUP(MONTH(Data!$E$2:$E$3988)/3,0),TEXT(YEAR(Data!$E$2:$E$3988),"0"))=$AP28))>0)),NA()))} -> #N/A | AR28: {=IF(OR($AP28="",AR$1=""),NA(),IFERROR(AVERAGE(_xlfn._xlws.FILTER(Data!$K$2:$K$3988,((Data!$A$2:$A$3988=AR$1)*IF($B$8="Todas",1,--(AR$1=$B$8))*IF($B$5="Todos",1,--(YEAR(Data!$E$2:$E$3988)=$B$5))*IF($B$6="Todos",1,--("T"&ROUNDUP(MONTH(Data!$E$2:$E$3988)/3,0)=$B$6))*IF($B$7="Todos",1,--(TEXT(Data!$E$2:$E$3988,"[$-es-ES]mmmm")=$B$7))*--(CHOOSE(MATCH($B$4,{"Mensual","Trimestral","Anual"},0),TEXT(Data!$E$2:$E$3988,"yyyy-mm"),YEAR(Data!$E$2:$E$3988)&"-T"&ROUNDUP(MONTH(Data!$E$2:$E$3988)/3,0),TEXT(YEAR(Data!$E$2:$E$3988),"0"))=$AP28))>0)),NA()))} -> #N/A | AS28: {=IF(OR($AP28="",AS$1=""),NA(),IFERROR(AVERAGE(_xlfn._xlws.FILTER(Data!$K$2:$K$3988,((Data!$A$2:$A$3988=AS$1)*IF($B$8="Todas",1,--(AS$1=$B$8))*IF($B$5="Todos",1,--(YEAR(Data!$E$2:$E$3988)=$B$5))*IF($B$6="Todos",1,--("T"&ROUNDUP(MONTH(Data!$E$2:$E$3988)/3,0)=$B$6))*IF($B$7="Todos",1,--(TEXT(Data!$E$2:$E$3988,"[$-es-ES]mmmm")=$B$7))*--(CHOOSE(MATCH($B$4,{"Mensual","Trimestral","Anual"},0),TEXT(Data!$E$2:$E$3988,"yyyy-mm"),YEAR(Data!$E$2:$E$3988)&"-T"&ROUNDUP(MONTH(Data!$E$2:$E$3988)/3,0),TEXT(YEAR(Data!$E$2:$E$3988),"0"))=$AP28))>0)),NA()))} -> #N/A | AT28: {=IF(OR($AP28="",AT$1=""),NA(),IFERROR(AVERAGE(_xlfn._xlws.FILTER(Data!$K$2:$K$3988,((Data!$A$2:$A$3988=AT$1)*IF($B$8="Todas",1,--(AT$1=$B$8))*IF($B$5="Todos",1,--(YEAR(Data!$E$2:$E$3988)=$B$5))*IF($B$6="Todos",1,--("T"&ROUNDUP(MONTH(Data!$E$2:$E$3988)/3,0)=$B$6))*IF($B$7="Todos",1,--(TEXT(Data!$E$2:$E$3988,"[$-es-ES]mmmm")=$B$7))*--(CHOOSE(MATCH($B$4,{"Mensual","Trimestral","Anual"},0),TEXT(Data!$E$2:$E$3988,"yyyy-mm"),YEAR(Data!$E$2:$E$3988)&"-T"&ROUNDUP(MONTH(Data!$E$2:$E$3988)/3,0),TEXT(YEAR(Data!$E$2:$E$3988),"0"))=$AP28))>0)),NA()))} -> #N/A
AQ29: {=IF(OR($AP29="",AQ$1=""),NA(),IFERROR(AVERAGE(_xlfn._xlws.FILTER(Data!$K$2:$K$3988,((Data!$A$2:$A$3988=AQ$1)*IF($B$8="Todas",1,--(AQ$1=$B$8))*IF($B$5="Todos",1,--(YEAR(Data!$E$2:$E$3988)=$B$5))*IF($B$6="Todos",1,--("T"&ROUNDUP(MONTH(Data!$E$2:$E$3988)/3,0)=$B$6))*IF($B$7="Todos",1,--(TEXT(Data!$E$2:$E$3988,"[$-es-ES]mmmm")=$B$7))*--(CHOOSE(MATCH($B$4,{"Mensual","Trimestral","Anual"},0),TEXT(Data!$E$2:$E$3988,"yyyy-mm"),YEAR(Data!$E$2:$E$3988)&"-T"&ROUNDUP(MONTH(Data!$E$2:$E$3988)/3,0),TEXT(YEAR(Data!$E$2:$E$3988),"0"))=$AP29))>0)),NA()))} -> #N/A | AR29: {=IF(OR($AP29="",AR$1=""),NA(),IFERROR(AVERAGE(_xlfn._xlws.FILTER(Data!$K$2:$K$3988,((Data!$A$2:$A$3988=AR$1)*IF($B$8="Todas",1,--(AR$1=$B$8))*IF($B$5="Todos",1,--(YEAR(Data!$E$2:$E$3988)=$B$5))*IF($B$6="Todos",1,--("T"&ROUNDUP(MONTH(Data!$E$2:$E$3988)/3,0)=$B$6))*IF($B$7="Todos",1,--(TEXT(Data!$E$2:$E$3988,"[$-es-ES]mmmm")=$B$7))*--(CHOOSE(MATCH($B$4,{"Mensual","Trimestral","Anual"},0),TEXT(Data!$E$2:$E$3988,"yyyy-mm"),YEAR(Data!$E$2:$E$3988)&"-T"&ROUNDUP(MONTH(Data!$E$2:$E$3988)/3,0),TEXT(YEAR(Data!$E$2:$E$3988),"0"))=$AP29))>0)),NA()))} -> #N/A | AS29: {=IF(OR($AP29="",AS$1=""),NA(),IFERROR(AVERAGE(_xlfn._xlws.FILTER(Data!$K$2:$K$3988,((Data!$A$2:$A$3988=AS$1)*IF($B$8="Todas",1,--(AS$1=$B$8))*IF($B$5="Todos",1,--(YEAR(Data!$E$2:$E$3988)=$B$5))*IF($B$6="Todos",1,--("T"&ROUNDUP(MONTH(Data!$E$2:$E$3988)/3,0)=$B$6))*IF($B$7="Todos",1,--(TEXT(Data!$E$2:$E$3988,"[$-es-ES]mmmm")=$B$7))*--(CHOOSE(MATCH($B$4,{"Mensual","Trimestral","Anual"},0),TEXT(Data!$E$2:$E$3988,"yyyy-mm"),YEAR(Data!$E$2:$E$3988)&"-T"&ROUNDUP(MONTH(Data!$E$2:$E$3988)/3,0),TEXT(YEAR(Data!$E$2:$E$3988),"0"))=$AP29))>0)),NA()))} -> #N/A | AT29: {=IF(OR($AP29="",AT$1=""),NA(),IFERROR(AVERAGE(_xlfn._xlws.FILTER(Data!$K$2:$K$3988,((Data!$A$2:$A$3988=AT$1)*IF($B$8="Todas",1,--(AT$1=$B$8))*IF($B$5="Todos",1,--(YEAR(Data!$E$2:$E$3988)=$B$5))*IF($B$6="Todos",1,--("T"&ROUNDUP(MONTH(Data!$E$2:$E$3988)/3,0)=$B$6))*IF($B$7="Todos",1,--(TEXT(Data!$E$2:$E$3988,"[$-es-ES]mmmm")=$B$7))*--(CHOOSE(MATCH($B$4,{"Mensual","Trimestral","Anual"},0),TEXT(Data!$E$2:$E$3988,"yyyy-mm"),YEAR(Data!$E$2:$E$3988)&"-T"&ROUNDUP(MONTH(Data!$E$2:$E$3988)/3,0),TEXT(YEAR(Data!$E$2:$E$3988),"0"))=$AP29))>0)),NA()))} -> #N/A
